Workbook
Name m_avg_dd_episode: Data!$C$24:$E$24
Name m_avg_holding_sessions: Data!$C$40:$E$40
Name m_avg_loss: Data!$C$36:$E$36
Name m_avg_trade_net: Data!$C$34:$E$34
Name m_avg_win: Data!$C$35:$E$35
Name m_bench_cagr: Data!$C$10:$E$10
Name m_bench_max_dd: Data!$C$23:$E$23
Name m_bench_sharpe_rf0: Data!$C$18:$E$18
Name m_bench_sharpe_rf6: Data!$C$19:$E$19
Name m_bench_total_return: Data!$C$9:$E$9
Name m_bench_vol: Data!$C$15:$E$15
Name m_best_trade: Data!$C$38:$E$38
Name m_beta: Data!$C$26:$E$26
Name m_cagr: Data!$C$8:$E$8
Name m_calmar: Data!$C$21:$E$21
Name m_capacity_1pct_50fit_cr: Data!$C$46:$E$46
Name m_capacity_1pct_90fit_cr: Data!$C$44:$E$44
Name m_capacity_5pct_90fit_cr: Data!$C$45:$E$45
Name m_cvar95_daily: Data!$C$28:$E$28
Name m_end: Data!$C$5:$E$5
Name m_excess_cagr: Data!$C$11:$E$11
Name m_excess_kurt_daily: Data!$C$30:$E$30
Name m_longest_dd_sessions: Data!$C$25:$E$25
Name m_max_dd: Data!$C$22:$E$22
Name m_mean_trade_xs_nifty: Data!$C$13:$E$13
Name m_mean_trade_xs_univ_60d: Data!$C$12:$E$12
Name m_median_adv20_cr: Data!$C$42:$E$42
Name m_p10_adv20_cr: Data!$C$43:$E$43
Name m_payoff: Data!$C$37:$E$37
Name m_profit_factor: Data!$C$33:$E$33
Name m_sharpe_rf0: Data!$C$16:$E$16
Name m_sharpe_rf6: Data!$C$17:$E$17
Name m_skew_daily: Data!$C$29:$E$29
Name m_sortino_rf0: Data!$C$20:$E$20
Name m_start: Data!$C$4:$E$4
Name m_total_return: Data!$C$7:$E$7
Name m_trades: Data!$C$31:$E$31
Name m_turnover_one_way: Data!$C$41:$E$41
Name m_var95_daily: Data!$C$27:$E$27
Name m_vol: Data!$C$14:$E$14
Name m_win_rate: Data!$C$32:$E$32
Name m_worst_trade: Data!$C$39:$E$39
Name m_years: Data!$C$6:$E$6
Name PeriodHeaders: Data!$C$3:$E$3
Name SelPeriod: Cover!$L$3

Sheet Cover
A1: StackFlow PEAD V2 — Post-Earnings-Announcement Drift, NSE
A2: Thesis: Indian stocks with the largest point-in-time earnings surprise (ex-ante SUE, top quintile) keep drifting up for ~60 trading days after the filing; a 30-slot long-only non-financial book tries to harvest it.
A3: FORWARD-TEST CANDIDATE — NOT VALIDATED | F3: Generated 2026-09-23 | K3: View period ▸ | L3: Full Period | N3: ="Window: "&INDEX(m_start,1,MATCH(SelPeriod,PeriodHeaders,0))&" to "&INDEX(m_end,1,MATCH(SelPeriod,PeriodHeaders,0)) -> Window: 2021-08-11 to 2026-08-11
A5: =INDEX(m_cagr,1,MATCH(SelPeriod,PeriodHeaders,0)) -> 0.17155034 | C5: =INDEX(m_excess_cagr,1,MATCH(SelPeriod,PeriodHeaders,0)) -> 0.058715761 | E5: =INDEX(m_sharpe_rf0,1,MATCH(SelPeriod,PeriodHeaders,0)) -> 1.0827253
A7: CAGR | C7: Excess CAGR vs NIFTY 500 (price index)* | E7: Sharpe (rf = 0%)
A9: =INDEX(m_max_dd,1,MATCH(SelPeriod,PeriodHeaders,0)) -> -0.23675278 | C9: =INDEX(m_win_rate,1,MATCH(SelPeriod,PeriodHeaders,0)) -> 0.58377425 | E9: =INDEX(m_trades,1,MATCH(SelPeriod,PeriodHeaders,0)) -> 567
A11: Maximum drawdown | C11: Win rate (net of costs) | E11: Total trades
A12: KPI cards follow the period selector in L3 (Full Period / Discovery / Holdout). Charts show the full-period book with the two periods shaded.
A15: Discovery vs Holdout — the honesty check
A16: Metric | C16: Full Period | D16: Discovery | E16: Holdout | F16: Holdout, calendar split
A17: CAGR | C17: =Data!C8 -> 0.17155034 | D17: =Data!D8 -> 0.23156402 | E17: =Data!E8 -> 0.087085033 | F17: =Data!G8 -> 0.13045486
A18: NIFTY 500 (PR) CAGR | C18: =Data!C10 -> 0.11283458 | D18: =Data!D10 -> 0.1518874 | E18: =Data!E10 -> 0.07893447 | F18: =Data!G10 -> 0.078543654
A19: Excess CAGR vs NIFTY 500* | C19: =Data!C11 -> 0.058715761 | D19: =Data!D11 -> 0.079676621 | E19: =Data!E11 -> 0.0081505638 | F19: =Data!G11 -> 0.051911208
A20: Sharpe (rf = 0%) | C20: =Data!C16 -> 1.0827253 | D20: =Data!D16 -> 1.5005549 | E20: =Data!E16 -> 0.59298964 | F20: =Data!G16 -> 0.81859279
A21: NIFTY 500 Sharpe (rf = 0%) | C21: =Data!C18 -> 0.82364982 | D21: =Data!D18 -> 1.092487 | E21: =Data!E18 -> 0.59416204 | F21: =Data!G18 -> 0.59360632
A22: Sharpe (rf = 6%) | C22: =Data!C17 -> 0.72013335 | D22: =Data!D17 -> 1.1080203 | E22: =Data!E17 -> 0.24400845 | F22: =Data!G17 -> 0.47639337
A23: Maximum drawdown | C23: =Data!C22 -> -0.23675278 | D23: =Data!D22 -> -0.19281551 | E23: =Data!E22 -> -0.24950465 | F23: =Data!G22 -> -0.23675278
A24: Trades | C24: =Data!C31 -> 567 | D24: =Data!D31 -> 277 | E24: =Data!E31 -> 296 | F24: n/a
A25: Holdout = a book holding ONLY trades signalled on/after 2024-01-01, started empty. The calendar split of the continuous book (last column) looks better only because Q4-2023 discovery trades still open in Jan–Feb 2024 averaged +22% net; it is shown for transparency, not as holdout evidence. Holdout Sharpe equals the index's. The 2024–26 window was already seen by V1, the V2 grid and the exit-rule study, so it cannot validate the strategy.
A31: *Benchmark is the NIFTY 500 PRICE index; strategy prices are dividend-adjusted (yfinance auto_adjust). No NIFTY 500 TRI series is available in the repository, so every excess figure is overstated by roughly the index dividend yield (~1.0–1.5 pp/yr); holdout excess vs a TRI is ≈ 0% or below. Costs: 0.585% round trip on every trade (0.2925% per leg, LeadFlow NSE cost model). Status: forward-test candidate — NOT a validated live strategy. The only remaining clean test is the forward record (forward_record_pead_v2.csv).
A38: Source: corrected/period_metrics_corrected.csv, corrected/nav_daily_corrected.csv · Built from CORRECTED_REPORT.md (revision 2) outputs · Workbook generated 2026-09-23

Sheet Executive Summary
A1: Executive Summary — full KPI table (as at last completed trade, 2026-08-11)
A2: Status: FORWARD-TEST CANDIDATE — NOT VALIDATED. Discovery and Holdout are trade-attributed books (each holds only the trades signalled in its own period). Excess figures are vs the NIFTY 500 PRICE index (see Methodology).
A4: Metric | B4: Full Period | C4: Discovery | D4: Holdout | E4: Holdout, calendar split (flattered)
A5: Window
A6: Window start | B6: =Data!C4 -> 2021-08-11 | C6: =Data!D4 -> 2021-08-11 | D6: =Data!E4 -> 2024-01-17 | E6: =Data!G4 -> 2023-12-29
A7: Window end | B7: =Data!C5 -> 2026-08-11 | C7: =Data!D5 -> 2024-02-13 | D7: =Data!E5 -> 2026-08-11 | E7: =Data!G5 -> 2026-08-11
A8: Years | B8: =Data!C6 -> 4.9993155 | C8: =Data!D6 -> 2.5078713 | D8: =Data!E6 -> 2.5653662 | E8: =Data!G6 -> 2.6173854
A9: Return
A10: Total return | B10: =Data!C7 -> 1.2067733 | C10: =Data!D7 -> 0.68598808 | D10: =Data!E7 -> 0.23887988 | E10: =Data!G7 -> 0.3784284
A11: CAGR | B11: =Data!C8 -> 0.17155034 | C11: =Data!D8 -> 0.23156402 | D11: =Data!E8 -> 0.087085033 | E11: =Data!G8 -> 0.13045486
A12: NIFTY 500 (PR) CAGR | B12: =Data!C10 -> 0.11283458 | C12: =Data!D10 -> 0.1518874 | D12: =Data!E10 -> 0.07893447 | E12: =Data!G10 -> 0.078543654
A13: Excess CAGR vs NIFTY 500 (PR) | B13: =Data!C11 -> 0.058715761 | C13: =Data!D11 -> 0.079676621 | D13: =Data!E11 -> 0.0081505638 | E13: =Data!G11 -> 0.051911208
A14: Mean trade excess vs same-month event universe (60d) | B14: =Data!C12 -> 0.010602259 | C14: =Data!D12 -> 0.0033915041 | D14: =Data!E12 -> 0.010788755 | E14: n/a
A15: Mean trade excess vs NIFTY 500 (per trade) | B15: =Data!C13 -> 0.022942353 | C15: =Data!D13 -> 0.029213073 | D15: =Data!E13 -> 0.010525723 | E15: n/a
A16: Risk
A17: Annualised volatility | B17: =Data!C14 -> 0.16071962 | C17: =Data!D14 -> 0.14845989 | D17: =Data!E14 -> 0.16698793 | E17: =Data!G14 -> 0.17029732
A18: NIFTY 500 volatility | B18: =Data!C15 -> 0.14477536 | C18: =Data!D15 -> 0.14061415 | D18: =Data!E15 -> 0.14890391 | E18: =Data!G15 -> 0.14822808
A19: Sharpe (rf = 0%) | B19: =Data!C16 -> 1.0827253 | C19: =Data!D16 -> 1.5005549 | D19: =Data!E16 -> 0.59298964 | E19: =Data!G16 -> 0.81859279
A20: Sharpe (rf = 6%) | B20: =Data!C17 -> 0.72013335 | C20: =Data!D17 -> 1.1080203 | D20: =Data!E17 -> 0.24400845 | E20: =Data!G17 -> 0.47639337
A21: NIFTY 500 Sharpe (rf = 0%) | B21: =Data!C18 -> 0.82364982 | C21: =Data!D18 -> 1.092487 | D21: =Data!E18 -> 0.59416204 | E21: =Data!G18 -> 0.59360632
A22: NIFTY 500 Sharpe (rf = 6%) | B22: =Data!C19 -> 0.42112521 | C22: =Data!D19 -> 0.67805043 | D22: =Data!E19 -> 0.20279793 | E22: =Data!G19 -> 0.20045785
A23: Sortino (rf = 0%) | B23: =Data!C20 -> 1.4756578 | C23: =Data!D20 -> 2.0515544 | D23: =Data!E20 -> 0.80115462 | E23: =Data!G20 -> 1.1154854
A24: Calmar (CAGR / |max DD|) | B24: =Data!C21 -> 0.72459696 | C24: =Data!D21 -> 1.2009616 | D24: =Data!E21 -> 0.3490317 | E24: =Data!G21 -> 0.55101724
A25: Maximum drawdown | B25: =Data!C22 -> -0.23675278 | C25: =Data!D22 -> -0.19281551 | D25: =Data!E22 -> -0.24950465 | E25: =Data!G22 -> -0.23675278
A26: NIFTY 500 maximum drawdown | B26: =Data!C23 -> -0.18843201 | C26: =Data!D23 -> -0.18477731 | D26: =Data!E23 -> -0.18843201 | E26: =Data!G23 -> -0.18843201
A27: Average drawdown (mean episode trough) | B27: =Data!C24 -> -0.027338901 | C27: =Data!D24 -> -0.020194367 | D27: =Data!E24 -> -0.033755378 | E27: =Data!G24 -> -0.037260221
A28: Longest drawdown (trading sessions) | B28: =Data!C25 -> 423 | C28: =Data!D25 -> 184 | D28: =Data!E25 -> 431 | E28: =Data!G25 -> 423
A29: Beta to NIFTY 500 (daily) | B29: =Data!C26 -> 0.94573016 | C29: =Data!D26 -> 0.87303271 | D29: =Data!E26 -> 0.97843988 | E29: =Data!G26 -> 1.0002074
A30: Trades
A31: Total trades | B31: =Data!C31 -> 567 | C31: =Data!D31 -> 277 | D31: =Data!E31 -> 296 | E31: n/a
A32: Win rate | B32: =Data!C32 -> 0.58377425 | C32: =Data!D32 -> 0.59205776 | D32: =Data!E32 -> 0.56418919 | E32: n/a
A33: Profit factor | B33: =Data!C33 -> 2.0928063 | C33: =Data!D33 -> 2.670276 | D33: =Data!E33 -> 1.5129575 | E33: n/a
A34: Average net trade | B34: =Data!C34 -> 0.046084937 | C34: =Data!D34 -> 0.062456471 | D34: =Data!E34 -> 0.024053236 | E34: n/a
A35: Average win | B35: =Data!C35 -> 0.15118194 | C35: =Data!D35 -> 0.16864803 | D35: =Data!E35 -> 0.12574598 | E35: n/a
A36: Average loss | B36: =Data!C36 -> -0.10131806 | C36: =Data!D36 -> -0.091662251 | D36: =Data!E36 -> -0.10759551 | E36: n/a
A37: Payoff ratio (avg win / |avg loss|) | B37: =Data!C37 -> 1.4921519 | C37: =Data!D37 -> 1.8398853 | D37: =Data!E37 -> 1.1686917 | E37: n/a
A38: Best trade | B38: =Data!C38 -> 0.67123276 | C38: =Data!D38 -> 0.67123276 | D38: =Data!E38 -> 0.66616176 | E38: n/a
A39: Worst trade | B39: =Data!C39 -> -0.58684997 | C39: =Data!D39 -> -0.31865708 | D39: =Data!E39 -> -0.58684997 | E39: n/a
A40: Average holding period (sessions) | B40: =Data!C40 -> 60 | C40: =Data!D40 -> 60 | D40: =Data!E40 -> 60 | E40: n/a
A41: Capacity & turnover
A42: Annual one-way turnover | B42: =Data!C41 -> 3.8142463 | C42: =Data!D41 -> 3.7094262 | D42: =Data!E41 -> 3.8571927 | E42: n/a
A43: Median 20-day ADV of traded names (INR Cr) | B43: =Data!C42 -> 48.739937 | C43: =Data!D42 -> 33.072791 | D43: =Data!E42 -> 80.634739 | E43: n/a
A44: 10th-pct 20-day ADV (INR Cr) | B44: =Data!C43 -> 5.4258696 | C44: =Data!D43 -> 4.1569299 | D44: =Data!E43 -> 8.144975 | E44: n/a
A45: Capacity @1% ADV, 90% of trades fit (INR Cr) | B45: =Data!C44 -> 1.6277609 | C45: =Data!D44 -> 1.247079 | D45: =Data!E44 -> 2.4434925 | E45: n/a
A46: Capacity @5% ADV, 90% of trades fit (INR Cr) | B46: =Data!C45 -> 8.1388043 | C46: =Data!D45 -> 6.2353948 | D46: =Data!E45 -> 12.217462 | E46: n/a
A47: Capacity @1% ADV, only 50% of trades fit (INR Cr) | B47: =Data!C46 -> 14.621981 | C47: =Data!D46 -> 9.9218373 | D47: =Data!E46 -> 24.190422 | E47: n/a
A49: • Excess vs equal-weight event universe is reported at trade level (mean 60-day excess of the traded names over the same-month mean of all qualifying events), because no daily equal-weight universe NAV exists in the corrected outputs.
A50: • Capacity = AUM at which 90% of trades stay within 1% (or 5%) of the stock's 20-session median traded value before entry; the 50%-fit row shows how far the headline would have to stretch to reach the old 'INR 15–30 Cr' claim.
A51: • Holdout Sharpe (0.59) equals NIFTY 500's (0.59). At 1.0% round-trip cost the holdout excess is -0.88% (Risk Diagnostics, KT5).
A53: Source: corrected/period_metrics_corrected.csv · Built from CORRECTED_REPORT.md (revision 2) outputs · Workbook generated 2026-09-23

Sheet Performance Charts
A1: Performance Charts
A2: Forward-test candidate — not validated. Shaded bands: Discovery (2021-08 → 2023-12) and Holdout (2024-01 →).
A4: 1 · Equity curve (full history, rebased to 100) with Discovery / Holdout bands
A24: 2 · Underwater curve (same period, same x-axis)
A40: 3 · Rolling 12-month excess return vs NIFTY 500
A56: 4 · Monthly returns heatmap — strategy (full-period book)
A57: Strategy monthly return (YTD / Annual = calendar-year return; 2021 from 11-Aug, 2026 to 11-Aug)
A58: Year | B58: Jan | C58: Feb | D58: Mar | E58: Apr | F58: May | G58: Jun | H58: Jul | I58: Aug | J58: Sep | K58: Oct | L58: Nov | M58: Dec | N58: YTD / Annual | O58: NIFTY 500 | P58: Excess
A59: 2021 | B59: =IF(COUNTIFS(Data!$U$4:$U$64,2021,Data!$V$4:$V$64,1)=0,"",SUMIFS(Data!$W$4:$W$64,Data!$U$4:$U$64,2021,Data!$V$4:$V$64,1)) | C59: =IF(COUNTIFS(Data!$U$4:$U$64,2021,Data!$V$4:$V$64,2)=0,"",SUMIFS(Data!$W$4:$W$64,Data!$U$4:$U$64,2021,Data!$V$4:$V$64,2)) | D59: =IF(COUNTIFS(Data!$U$4:$U$64,2021,Data!$V$4:$V$64,3)=0,"",SUMIFS(Data!$W$4:$W$64,Data!$U$4:$U$64,2021,Data!$V$4:$V$64,3)) | E59: =IF(COUNTIFS(Data!$U$4:$U$64,2021,Data!$V$4:$V$64,4)=0,"",SUMIFS(Data!$W$4:$W$64,Data!$U$4:$U$64,2021,Data!$V$4:$V$64,4)) | F59: =IF(COUNTIFS(Data!$U$4:$U$64,2021,Data!$V$4:$V$64,5)=0,"",SUMIFS(Data!$W$4:$W$64,Data!$U$4:$U$64,2021,Data!$V$4:$V$64,5)) | G59: =IF(COUNTIFS(Data!$U$4:$U$64,2021,Data!$V$4:$V$64,6)=0,"",SUMIFS(Data!$W$4:$W$64,Data!$U$4:$U$64,2021,Data!$V$4:$V$64,6)) | H59: =IF(COUNTIFS(Data!$U$4:$U$64,2021,Data!$V$4:$V$64,7)=0,"",SUMIFS(Data!$W$4:$W$64,Data!$U$4:$U$64,2021,Data!$V$4:$V$64,7)) | I59: =IF(COUNTIFS(Data!$U$4:$U$64,2021,Data!$V$4:$V$64,8)=0,"",SUMIFS(Data!$W$4:$W$64,Data!$U$4:$U$64,2021,Data!$V$4:$V$64,8)) -> 0.017963758 | J59: =IF(COUNTIFS(Data!$U$4:$U$64,2021,Data!$V$4:$V$64,9)=0,"",SUMIFS(Data!$W$4:$W$64,Data!$U$4:$U$64,2021,Data!$V$4:$V$64,9)) -> 0.0078607844 | K59: =IF(COUNTIFS(Data!$U$4:$U$64,2021,Data!$V$4:$V$64,10)=0,"",SUMIFS(Data!$W$4:$W$64,Data!$U$4:$U$64,2021,Data!$V$4:$V$64,10)) -> -0.024465098 | L59: =IF(COUNTIFS(Data!$U$4:$U$64,2021,Data!$V$4:$V$64,11)=0,"",SUMIFS(Data!$W$4:$W$64,Data!$U$4:$U$64,2021,Data!$V$4:$V$64,11)) -> 0.033369901 | M59: =IF(COUNTIFS(Data!$U$4:$U$64,2021,Data!$V$4:$V$64,12)=0,"",SUMIFS(Data!$W$4:$W$64,Data!$U$4:$U$64,2021,Data!$V$4:$V$64,12)) -> 0.036147431 | N59: =INDEX(Data!$AC$4:$AC$9,MATCH(2021,Data!$AA$4:$AA$9,0)) -> 0.071650172 | O59: =INDEX(Data!$AD$4:$AD$9,MATCH(2021,Data!$AA$4:$AA$9,0)) -> 0.080686482 | P59: =INDEX(Data!$AE$4:$AE$9,MATCH(2021,Data!$AA$4:$AA$9,0)) -> -0.0090363098
A60: 2022 | B60: =IF(COUNTIFS(Data!$U$4:$U$64,2022,Data!$V$4:$V$64,1)=0,"",SUMIFS(Data!$W$4:$W$64,Data!$U$4:$U$64,2022,Data!$V$4:$V$64,1)) -> 0.0014163193 | C60: =IF(COUNTIFS(Data!$U$4:$U$64,2022,Data!$V$4:$V$64,2)=0,"",SUMIFS(Data!$W$4:$W$64,Data!$U$4:$U$64,2022,Data!$V$4:$V$64,2)) -> -0.029532354 | D60: =IF(COUNTIFS(Data!$U$4:$U$64,2022,Data!$V$4:$V$64,3)=0,"",SUMIFS(Data!$W$4:$W$64,Data!$U$4:$U$64,2022,Data!$V$4:$V$64,3)) -> 0.10884152 | E60: =IF(COUNTIFS(Data!$U$4:$U$64,2022,Data!$V$4:$V$64,4)=0,"",SUMIFS(Data!$W$4:$W$64,Data!$U$4:$U$64,2022,Data!$V$4:$V$64,4)) -> -0.021167155 | F60: =IF(COUNTIFS(Data!$U$4:$U$64,2022,Data!$V$4:$V$64,5)=0,"",SUMIFS(Data!$W$4:$W$64,Data!$U$4:$U$64,2022,Data!$V$4:$V$64,5)) -> -0.046541425 | G60: =IF(COUNTIFS(Data!$U$4:$U$64,2022,Data!$V$4:$V$64,6)=0,"",SUMIFS(Data!$W$4:$W$64,Data!$U$4:$U$64,2022,Data!$V$4:$V$64,6)) -> -0.065401015 | H60: =IF(COUNTIFS(Data!$U$4:$U$64,2022,Data!$V$4:$V$64,7)=0,"",SUMIFS(Data!$W$4:$W$64,Data!$U$4:$U$64,2022,Data!$V$4:$V$64,7)) -> 0.071264272 | I60: =IF(COUNTIFS(Data!$U$4:$U$64,2022,Data!$V$4:$V$64,8)=0,"",SUMIFS(Data!$W$4:$W$64,Data!$U$4:$U$64,2022,Data!$V$4:$V$64,8)) -> 0.067299623 | J60: =IF(COUNTIFS(Data!$U$4:$U$64,2022,Data!$V$4:$V$64,9)=0,"",SUMIFS(Data!$W$4:$W$64,Data!$U$4:$U$64,2022,Data!$V$4:$V$64,9)) -> 0.014397621 | K60: =IF(COUNTIFS(Data!$U$4:$U$64,2022,Data!$V$4:$V$64,10)=0,"",SUMIFS(Data!$W$4:$W$64,Data!$U$4:$U$64,2022,Data!$V$4:$V$64,10)) -> 0.012722327 | L60: =IF(COUNTIFS(Data!$U$4:$U$64,2022,Data!$V$4:$V$64,11)=0,"",SUMIFS(Data!$W$4:$W$64,Data!$U$4:$U$64,2022,Data!$V$4:$V$64,11)) -> 0.0046022394 | M60: =IF(COUNTIFS(Data!$U$4:$U$64,2022,Data!$V$4:$V$64,12)=0,"",SUMIFS(Data!$W$4:$W$64,Data!$U$4:$U$64,2022,Data!$V$4:$V$64,12)) -> -0.042758798 | N60: =INDEX(Data!$AC$4:$AC$9,MATCH(2022,Data!$AA$4:$AA$9,0)) -> 0.06169062 | O60: =INDEX(Data!$AD$4:$AD$9,MATCH(2022,Data!$AA$4:$AA$9,0)) -> 0.030184313 | P60: =INDEX(Data!$AE$4:$AE$9,MATCH(2022,Data!$AA$4:$AA$9,0)) -> 0.031506306
A61: 2023 | B61: =IF(COUNTIFS(Data!$U$4:$U$64,2023,Data!$V$4:$V$64,1)=0,"",SUMIFS(Data!$W$4:$W$64,Data!$U$4:$U$64,2023,Data!$V$4:$V$64,1)) -> -0.024490579 | C61: =IF(COUNTIFS(Data!$U$4:$U$64,2023,Data!$V$4:$V$64,2)=0,"",SUMIFS(Data!$W$4:$W$64,Data!$U$4:$U$64,2023,Data!$V$4:$V$64,2)) -> -0.0050317282 | D61: =IF(COUNTIFS(Data!$U$4:$U$64,2023,Data!$V$4:$V$64,3)=0,"",SUMIFS(Data!$W$4:$W$64,Data!$U$4:$U$64,2023,Data!$V$4:$V$64,3)) -> -0.011204118 | E61: =IF(COUNTIFS(Data!$U$4:$U$64,2023,Data!$V$4:$V$64,4)=0,"",SUMIFS(Data!$W$4:$W$64,Data!$U$4:$U$64,2023,Data!$V$4:$V$64,4)) -> 0.045855692 | F61: =IF(COUNTIFS(Data!$U$4:$U$64,2023,Data!$V$4:$V$64,5)=0,"",SUMIFS(Data!$W$4:$W$64,Data!$U$4:$U$64,2023,Data!$V$4:$V$64,5)) -> 0.034457254 | G61: =IF(COUNTIFS(Data!$U$4:$U$64,2023,Data!$V$4:$V$64,6)=0,"",SUMIFS(Data!$W$4:$W$64,Data!$U$4:$U$64,2023,Data!$V$4:$V$64,6)) -> 0.04995296 | H61: =IF(COUNTIFS(Data!$U$4:$U$64,2023,Data!$V$4:$V$64,7)=0,"",SUMIFS(Data!$W$4:$W$64,Data!$U$4:$U$64,2023,Data!$V$4:$V$64,7)) -> 0.087975714 | I61: =IF(COUNTIFS(Data!$U$4:$U$64,2023,Data!$V$4:$V$64,8)=0,"",SUMIFS(Data!$W$4:$W$64,Data!$U$4:$U$64,2023,Data!$V$4:$V$64,8)) -> 0.021907845 | J61: =IF(COUNTIFS(Data!$U$4:$U$64,2023,Data!$V$4:$V$64,9)=0,"",SUMIFS(Data!$W$4:$W$64,Data!$U$4:$U$64,2023,Data!$V$4:$V$64,9)) -> -0.0066212008 | K61: =IF(COUNTIFS(Data!$U$4:$U$64,2023,Data!$V$4:$V$64,10)=0,"",SUMIFS(Data!$W$4:$W$64,Data!$U$4:$U$64,2023,Data!$V$4:$V$64,10)) -> -0.0095014938 | L61: =IF(COUNTIFS(Data!$U$4:$U$64,2023,Data!$V$4:$V$64,11)=0,"",SUMIFS(Data!$W$4:$W$64,Data!$U$4:$U$64,2023,Data!$V$4:$V$64,11)) -> 0.11268064 | M61: =IF(COUNTIFS(Data!$U$4:$U$64,2023,Data!$V$4:$V$64,12)=0,"",SUMIFS(Data!$W$4:$W$64,Data!$U$4:$U$64,2023,Data!$V$4:$V$64,12)) -> 0.060353799 | N61: =INDEX(Data!$AC$4:$AC$9,MATCH(2023,Data!$AA$4:$AA$9,0)) -> 0.40709195 | O61: =INDEX(Data!$AD$4:$AD$9,MATCH(2023,Data!$AA$4:$AA$9,0)) -> 0.25764377 | P61: =INDEX(Data!$AE$4:$AE$9,MATCH(2023,Data!$AA$4:$AA$9,0)) -> 0.14944818
A62: 2024 | B62: =IF(COUNTIFS(Data!$U$4:$U$64,2024,Data!$V$4:$V$64,1)=0,"",SUMIFS(Data!$W$4:$W$64,Data!$U$4:$U$64,2024,Data!$V$4:$V$64,1)) -> 0.047025805 | C62: =IF(COUNTIFS(Data!$U$4:$U$64,2024,Data!$V$4:$V$64,2)=0,"",SUMIFS(Data!$W$4:$W$64,Data!$U$4:$U$64,2024,Data!$V$4:$V$64,2)) -> 0.018870931 | D62: =IF(COUNTIFS(Data!$U$4:$U$64,2024,Data!$V$4:$V$64,3)=0,"",SUMIFS(Data!$W$4:$W$64,Data!$U$4:$U$64,2024,Data!$V$4:$V$64,3)) -> 0.0065503435 | E62: =IF(COUNTIFS(Data!$U$4:$U$64,2024,Data!$V$4:$V$64,4)=0,"",SUMIFS(Data!$W$4:$W$64,Data!$U$4:$U$64,2024,Data!$V$4:$V$64,4)) -> 0.041310772 | F62: =IF(COUNTIFS(Data!$U$4:$U$64,2024,Data!$V$4:$V$64,5)=0,"",SUMIFS(Data!$W$4:$W$64,Data!$U$4:$U$64,2024,Data!$V$4:$V$64,5)) -> 0.04875291 | G62: =IF(COUNTIFS(Data!$U$4:$U$64,2024,Data!$V$4:$V$64,6)=0,"",SUMIFS(Data!$W$4:$W$64,Data!$U$4:$U$64,2024,Data!$V$4:$V$64,6)) -> 0.086965371 | H62: =IF(COUNTIFS(Data!$U$4:$U$64,2024,Data!$V$4:$V$64,7)=0,"",SUMIFS(Data!$W$4:$W$64,Data!$U$4:$U$64,2024,Data!$V$4:$V$64,7)) -> 0.060782482 | I62: =IF(COUNTIFS(Data!$U$4:$U$64,2024,Data!$V$4:$V$64,8)=0,"",SUMIFS(Data!$W$4:$W$64,Data!$U$4:$U$64,2024,Data!$V$4:$V$64,8)) -> -0.0096241418 | J62: =IF(COUNTIFS(Data!$U$4:$U$64,2024,Data!$V$4:$V$64,9)=0,"",SUMIFS(Data!$W$4:$W$64,Data!$U$4:$U$64,2024,Data!$V$4:$V$64,9)) -> 0.0014984637 | K62: =IF(COUNTIFS(Data!$U$4:$U$64,2024,Data!$V$4:$V$64,10)=0,"",SUMIFS(Data!$W$4:$W$64,Data!$U$4:$U$64,2024,Data!$V$4:$V$64,10)) -> -0.041877595 | L62: =IF(COUNTIFS(Data!$U$4:$U$64,2024,Data!$V$4:$V$64,11)=0,"",SUMIFS(Data!$W$4:$W$64,Data!$U$4:$U$64,2024,Data!$V$4:$V$64,11)) -> 0.010715634 | M62: =IF(COUNTIFS(Data!$U$4:$U$64,2024,Data!$V$4:$V$64,12)=0,"",SUMIFS(Data!$W$4:$W$64,Data!$U$4:$U$64,2024,Data!$V$4:$V$64,12)) -> -0.012120748 | N62: =INDEX(Data!$AC$4:$AC$9,MATCH(2024,Data!$AA$4:$AA$9,0)) -> 0.28295618 | O62: =INDEX(Data!$AD$4:$AD$9,MATCH(2024,Data!$AA$4:$AA$9,0)) -> 0.1516407 | P62: =INDEX(Data!$AE$4:$AE$9,MATCH(2024,Data!$AA$4:$AA$9,0)) -> 0.13131547
A63: 2025 | B63: =IF(COUNTIFS(Data!$U$4:$U$64,2025,Data!$V$4:$V$64,1)=0,"",SUMIFS(Data!$W$4:$W$64,Data!$U$4:$U$64,2025,Data!$V$4:$V$64,1)) -> -0.080404479 | C63: =IF(COUNTIFS(Data!$U$4:$U$64,2025,Data!$V$4:$V$64,2)=0,"",SUMIFS(Data!$W$4:$W$64,Data!$U$4:$U$64,2025,Data!$V$4:$V$64,2)) -> -0.11975303 | D63: =IF(COUNTIFS(Data!$U$4:$U$64,2025,Data!$V$4:$V$64,3)=0,"",SUMIFS(Data!$W$4:$W$64,Data!$U$4:$U$64,2025,Data!$V$4:$V$64,3)) -> 0.082520934 | E63: =IF(COUNTIFS(Data!$U$4:$U$64,2025,Data!$V$4:$V$64,4)=0,"",SUMIFS(Data!$W$4:$W$64,Data!$U$4:$U$64,2025,Data!$V$4:$V$64,4)) -> 0.020443284 | F63: =IF(COUNTIFS(Data!$U$4:$U$64,2025,Data!$V$4:$V$64,5)=0,"",SUMIFS(Data!$W$4:$W$64,Data!$U$4:$U$64,2025,Data!$V$4:$V$64,5)) -> 0.035162618 | G63: =IF(COUNTIFS(Data!$U$4:$U$64,2025,Data!$V$4:$V$64,6)=0,"",SUMIFS(Data!$W$4:$W$64,Data!$U$4:$U$64,2025,Data!$V$4:$V$64,6)) -> 0.034072807 | H63: =IF(COUNTIFS(Data!$U$4:$U$64,2025,Data!$V$4:$V$64,7)=0,"",SUMIFS(Data!$W$4:$W$64,Data!$U$4:$U$64,2025,Data!$V$4:$V$64,7)) -> 0.0014951721 | I63: =IF(COUNTIFS(Data!$U$4:$U$64,2025,Data!$V$4:$V$64,8)=0,"",SUMIFS(Data!$W$4:$W$64,Data!$U$4:$U$64,2025,Data!$V$4:$V$64,8)) -> 0.00038051484 | J63: =IF(COUNTIFS(Data!$U$4:$U$64,2025,Data!$V$4:$V$64,9)=0,"",SUMIFS(Data!$W$4:$W$64,Data!$U$4:$U$64,2025,Data!$V$4:$V$64,9)) -> -0.0095487009 | K63: =IF(COUNTIFS(Data!$U$4:$U$64,2025,Data!$V$4:$V$64,10)=0,"",SUMIFS(Data!$W$4:$W$64,Data!$U$4:$U$64,2025,Data!$V$4:$V$64,10)) -> 0.038607839 | L63: =IF(COUNTIFS(Data!$U$4:$U$64,2025,Data!$V$4:$V$64,11)=0,"",SUMIFS(Data!$W$4:$W$64,Data!$U$4:$U$64,2025,Data!$V$4:$V$64,11)) -> -0.03867425 | M63: =IF(COUNTIFS(Data!$U$4:$U$64,2025,Data!$V$4:$V$64,12)=0,"",SUMIFS(Data!$W$4:$W$64,Data!$U$4:$U$64,2025,Data!$V$4:$V$64,12)) -> 0.022677067 | N63: =INDEX(Data!$AC$4:$AC$9,MATCH(2025,Data!$AA$4:$AA$9,0)) -> -0.030173256 | O63: =INDEX(Data!$AD$4:$AD$9,MATCH(2025,Data!$AA$4:$AA$9,0)) -> 0.066865844 | P63: =INDEX(Data!$AE$4:$AE$9,MATCH(2025,Data!$AA$4:$AA$9,0)) -> -0.0970391
A64: 2026 | B64: =IF(COUNTIFS(Data!$U$4:$U$64,2026,Data!$V$4:$V$64,1)=0,"",SUMIFS(Data!$W$4:$W$64,Data!$U$4:$U$64,2026,Data!$V$4:$V$64,1)) -> -0.012001884 | C64: =IF(COUNTIFS(Data!$U$4:$U$64,2026,Data!$V$4:$V$64,2)=0,"",SUMIFS(Data!$W$4:$W$64,Data!$U$4:$U$64,2026,Data!$V$4:$V$64,2)) -> -0.015040304 | D64: =IF(COUNTIFS(Data!$U$4:$U$64,2026,Data!$V$4:$V$64,3)=0,"",SUMIFS(Data!$W$4:$W$64,Data!$U$4:$U$64,2026,Data!$V$4:$V$64,3)) -> -0.095831925 | E64: =IF(COUNTIFS(Data!$U$4:$U$64,2026,Data!$V$4:$V$64,4)=0,"",SUMIFS(Data!$W$4:$W$64,Data!$U$4:$U$64,2026,Data!$V$4:$V$64,4)) -> 0.13566435 | F64: =IF(COUNTIFS(Data!$U$4:$U$64,2026,Data!$V$4:$V$64,5)=0,"",SUMIFS(Data!$W$4:$W$64,Data!$U$4:$U$64,2026,Data!$V$4:$V$64,5)) -> 0.052378408 | G64: =IF(COUNTIFS(Data!$U$4:$U$64,2026,Data!$V$4:$V$64,6)=0,"",SUMIFS(Data!$W$4:$W$64,Data!$U$4:$U$64,2026,Data!$V$4:$V$64,6)) -> 0.022839787 | H64: =IF(COUNTIFS(Data!$U$4:$U$64,2026,Data!$V$4:$V$64,7)=0,"",SUMIFS(Data!$W$4:$W$64,Data!$U$4:$U$64,2026,Data!$V$4:$V$64,7)) -> 0.024671045 | I64: =IF(COUNTIFS(Data!$U$4:$U$64,2026,Data!$V$4:$V$64,8)=0,"",SUMIFS(Data!$W$4:$W$64,Data!$U$4:$U$64,2026,Data!$V$4:$V$64,8)) -> 0.0051722537 | J64: =IF(COUNTIFS(Data!$U$4:$U$64,2026,Data!$V$4:$V$64,9)=0,"",SUMIFS(Data!$W$4:$W$64,Data!$U$4:$U$64,2026,Data!$V$4:$V$64,9)) | K64: =IF(COUNTIFS(Data!$U$4:$U$64,2026,Data!$V$4:$V$64,10)=0,"",SUMIFS(Data!$W$4:$W$64,Data!$U$4:$U$64,2026,Data!$V$4:$V$64,10)) | L64: =IF(COUNTIFS(Data!$U$4:$U$64,2026,Data!$V$4:$V$64,11)=0,"",SUMIFS(Data!$W$4:$W$64,Data!$U$4:$U$64,2026,Data!$V$4:$V$64,11)) | M64: =IF(COUNTIFS(Data!$U$4:$U$64,2026,Data!$V$4:$V$64,12)=0,"",SUMIFS(Data!$W$4:$W$64,Data!$U$4:$U$64,2026,Data!$V$4:$V$64,12)) | N64: =INDEX(Data!$AC$4:$AC$9,MATCH(2026,Data!$AA$4:$AA$9,0)) -> 0.10784304 | O64: =INDEX(Data!$AD$4:$AD$9,MATCH(2026,Data!$AA$4:$AA$9,0)) -> -0.0079760217 | P64: =INDEX(Data!$AE$4:$AE$9,MATCH(2026,Data!$AA$4:$AA$9,0)) -> 0.11581907
A65: Month avg | B65: =IFERROR(AVERAGE(B59:B64),"") -> -0.013690964 | C65: =IFERROR(AVERAGE(C59:C64),"") -> -0.030097298 | D65: =IFERROR(AVERAGE(D59:D64),"") -> 0.01817535 | E65: =IFERROR(AVERAGE(E59:E64),"") -> 0.044421388 | F65: =IFERROR(AVERAGE(F59:F64),"") -> 0.024841953 | G65: =IFERROR(AVERAGE(G59:G64),"") -> 0.025685982 | H65: =IFERROR(AVERAGE(H59:H64),"") -> 0.049237737 | I65: =IFERROR(AVERAGE(I59:I64),"") -> 0.017183309 | ... M65: =IFERROR(AVERAGE(M59:M64),"") -> 0.01285975
A66: % positive | B66: =IFERROR(COUNTIF(B59:B64,">0")/COUNT(B59:B64),"") -> 0.4 | C66: =IFERROR(COUNTIF(C59:C64,">0")/COUNT(C59:C64),"") -> 0.2 | D66: =IFERROR(COUNTIF(D59:D64,">0")/COUNT(D59:D64),"") -> 0.6 | E66: =IFERROR(COUNTIF(E59:E64,">0")/COUNT(E59:E64),"") -> 0.8 | F66: =IFERROR(COUNTIF(F59:F64,">0")/COUNT(F59:F64),"") -> 0.8 | G66: =IFERROR(COUNTIF(G59:G64,">0")/COUNT(G59:G64),"") -> 0.8 | H66: =IFERROR(COUNTIF(H59:H64,">0")/COUNT(H59:H64),"") -> 1 | I66: =IFERROR(COUNTIF(I59:I64,">0")/COUNT(I59:I64),"") -> 0.83333333 | ... M66: =IFERROR(COUNTIF(M59:M64,">0")/COUNT(M59:M64),"") -> 0.6
A68: Monthly excess vs NIFTY 500 price index (YTD / Annual column = calendar-year excess)
A69: Year | B69: Jan | C69: Feb | D69: Mar | E69: Apr | F69: May | G69: Jun | H69: Jul | I69: Aug | J69: Sep | K69: Oct | L69: Nov | M69: Dec | N69: YTD / Annual | O69: NIFTY 500 | P69: Excess
A70: 2021 | B70: =IF(COUNTIFS(Data!$U$4:$U$64,2021,Data!$V$4:$V$64,1)=0,"",SUMIFS(Data!$Y$4:$Y$64,Data!$U$4:$U$64,2021,Data!$V$4:$V$64,1)) | C70: =IF(COUNTIFS(Data!$U$4:$U$64,2021,Data!$V$4:$V$64,2)=0,"",SUMIFS(Data!$Y$4:$Y$64,Data!$U$4:$U$64,2021,Data!$V$4:$V$64,2)) | D70: =IF(COUNTIFS(Data!$U$4:$U$64,2021,Data!$V$4:$V$64,3)=0,"",SUMIFS(Data!$Y$4:$Y$64,Data!$U$4:$U$64,2021,Data!$V$4:$V$64,3)) | E70: =IF(COUNTIFS(Data!$U$4:$U$64,2021,Data!$V$4:$V$64,4)=0,"",SUMIFS(Data!$Y$4:$Y$64,Data!$U$4:$U$64,2021,Data!$V$4:$V$64,4)) | F70: =IF(COUNTIFS(Data!$U$4:$U$64,2021,Data!$V$4:$V$64,5)=0,"",SUMIFS(Data!$Y$4:$Y$64,Data!$U$4:$U$64,2021,Data!$V$4:$V$64,5)) | G70: =IF(COUNTIFS(Data!$U$4:$U$64,2021,Data!$V$4:$V$64,6)=0,"",SUMIFS(Data!$Y$4:$Y$64,Data!$U$4:$U$64,2021,Data!$V$4:$V$64,6)) | H70: =IF(COUNTIFS(Data!$U$4:$U$64,2021,Data!$V$4:$V$64,7)=0,"",SUMIFS(Data!$Y$4:$Y$64,Data!$U$4:$U$64,2021,Data!$V$4:$V$64,7)) | I70: =IF(COUNTIFS(Data!$U$4:$U$64,2021,Data!$V$4:$V$64,8)=0,"",SUMIFS(Data!$Y$4:$Y$64,Data!$U$4:$U$64,2021,Data!$V$4:$V$64,8)) -> -0.030992935 | J70: =IF(COUNTIFS(Data!$U$4:$U$64,2021,Data!$V$4:$V$64,9)=0,"",SUMIFS(Data!$Y$4:$Y$64,Data!$U$4:$U$64,2021,Data!$V$4:$V$64,9)) -> -0.026266271 | K70: =IF(COUNTIFS(Data!$U$4:$U$64,2021,Data!$V$4:$V$64,10)=0,"",SUMIFS(Data!$Y$4:$Y$64,Data!$U$4:$U$64,2021,Data!$V$4:$V$64,10)) -> -0.026740445 | L70: =IF(COUNTIFS(Data!$U$4:$U$64,2021,Data!$V$4:$V$64,11)=0,"",SUMIFS(Data!$Y$4:$Y$64,Data!$U$4:$U$64,2021,Data!$V$4:$V$64,11)) -> 0.062438165 | M70: =IF(COUNTIFS(Data!$U$4:$U$64,2021,Data!$V$4:$V$64,12)=0,"",SUMIFS(Data!$Y$4:$Y$64,Data!$U$4:$U$64,2021,Data!$V$4:$V$64,12)) -> 0.012400729 | N70: =INDEX(Data!$AE$4:$AE$9,MATCH(2021,Data!$AA$4:$AA$9,0)) -> -0.0090363098 | O70: =INDEX(Data!$AD$4:$AD$9,MATCH(2021,Data!$AA$4:$AA$9,0)) -> 0.080686482 | P70: =INDEX(Data!$AE$4:$AE$9,MATCH(2021,Data!$AA$4:$AA$9,0)) -> -0.0090363098
A71: 2022 | B71: =IF(COUNTIFS(Data!$U$4:$U$64,2022,Data!$V$4:$V$64,1)=0,"",SUMIFS(Data!$Y$4:$Y$64,Data!$U$4:$U$64,2022,Data!$V$4:$V$64,1)) -> 0.0064009154 | C71: =IF(COUNTIFS(Data!$U$4:$U$64,2022,Data!$V$4:$V$64,2)=0,"",SUMIFS(Data!$Y$4:$Y$64,Data!$U$4:$U$64,2022,Data!$V$4:$V$64,2)) -> 0.011582953 | D71: =IF(COUNTIFS(Data!$U$4:$U$64,2022,Data!$V$4:$V$64,3)=0,"",SUMIFS(Data!$Y$4:$Y$64,Data!$U$4:$U$64,2022,Data!$V$4:$V$64,3)) -> 0.067846823 | E71: =IF(COUNTIFS(Data!$U$4:$U$64,2022,Data!$V$4:$V$64,4)=0,"",SUMIFS(Data!$Y$4:$Y$64,Data!$U$4:$U$64,2022,Data!$V$4:$V$64,4)) -> -0.013704669 | F71: =IF(COUNTIFS(Data!$U$4:$U$64,2022,Data!$V$4:$V$64,5)=0,"",SUMIFS(Data!$Y$4:$Y$64,Data!$U$4:$U$64,2022,Data!$V$4:$V$64,5)) -> -0.0016429408 | G71: =IF(COUNTIFS(Data!$U$4:$U$64,2022,Data!$V$4:$V$64,6)=0,"",SUMIFS(Data!$Y$4:$Y$64,Data!$U$4:$U$64,2022,Data!$V$4:$V$64,6)) -> -0.013554645 | H71: =IF(COUNTIFS(Data!$U$4:$U$64,2022,Data!$V$4:$V$64,7)=0,"",SUMIFS(Data!$Y$4:$Y$64,Data!$U$4:$U$64,2022,Data!$V$4:$V$64,7)) -> -0.024205026 | I71: =IF(COUNTIFS(Data!$U$4:$U$64,2022,Data!$V$4:$V$64,8)=0,"",SUMIFS(Data!$Y$4:$Y$64,Data!$U$4:$U$64,2022,Data!$V$4:$V$64,8)) -> 0.022337415 | J71: =IF(COUNTIFS(Data!$U$4:$U$64,2022,Data!$V$4:$V$64,9)=0,"",SUMIFS(Data!$Y$4:$Y$64,Data!$U$4:$U$64,2022,Data!$V$4:$V$64,9)) -> 0.046743356 | K71: =IF(COUNTIFS(Data!$U$4:$U$64,2022,Data!$V$4:$V$64,10)=0,"",SUMIFS(Data!$Y$4:$Y$64,Data!$U$4:$U$64,2022,Data!$V$4:$V$64,10)) -> -0.027377205 | L71: =IF(COUNTIFS(Data!$U$4:$U$64,2022,Data!$V$4:$V$64,11)=0,"",SUMIFS(Data!$Y$4:$Y$64,Data!$U$4:$U$64,2022,Data!$V$4:$V$64,11)) -> -0.029250847 | M71: =IF(COUNTIFS(Data!$U$4:$U$64,2022,Data!$V$4:$V$64,12)=0,"",SUMIFS(Data!$Y$4:$Y$64,Data!$U$4:$U$64,2022,Data!$V$4:$V$64,12)) -> -0.011572587 | N71: =INDEX(Data!$AE$4:$AE$9,MATCH(2022,Data!$AA$4:$AA$9,0)) -> 0.031506306 | O71: =INDEX(Data!$AD$4:$AD$9,MATCH(2022,Data!$AA$4:$AA$9,0)) -> 0.030184313 | P71: =INDEX(Data!$AE$4:$AE$9,MATCH(2022,Data!$AA$4:$AA$9,0)) -> 0.031506306
A72: 2023 | B72: =IF(COUNTIFS(Data!$U$4:$U$64,2023,Data!$V$4:$V$64,1)=0,"",SUMIFS(Data!$Y$4:$Y$64,Data!$U$4:$U$64,2023,Data!$V$4:$V$64,1)) -> 0.0087384317 | C72: =IF(COUNTIFS(Data!$U$4:$U$64,2023,Data!$V$4:$V$64,2)=0,"",SUMIFS(Data!$Y$4:$Y$64,Data!$U$4:$U$64,2023,Data!$V$4:$V$64,2)) -> 0.022871589 | D72: =IF(COUNTIFS(Data!$U$4:$U$64,2023,Data!$V$4:$V$64,3)=0,"",SUMIFS(Data!$Y$4:$Y$64,Data!$U$4:$U$64,2023,Data!$V$4:$V$64,3)) -> -0.013897188 | E72: =IF(COUNTIFS(Data!$U$4:$U$64,2023,Data!$V$4:$V$64,4)=0,"",SUMIFS(Data!$Y$4:$Y$64,Data!$U$4:$U$64,2023,Data!$V$4:$V$64,4)) -> 0.0004025516 | F72: =IF(COUNTIFS(Data!$U$4:$U$64,2023,Data!$V$4:$V$64,5)=0,"",SUMIFS(Data!$Y$4:$Y$64,Data!$U$4:$U$64,2023,Data!$V$4:$V$64,5)) -> -0.0014735056 | G72: =IF(COUNTIFS(Data!$U$4:$U$64,2023,Data!$V$4:$V$64,6)=0,"",SUMIFS(Data!$Y$4:$Y$64,Data!$U$4:$U$64,2023,Data!$V$4:$V$64,6)) -> 0.0078634533 | H72: =IF(COUNTIFS(Data!$U$4:$U$64,2023,Data!$V$4:$V$64,7)=0,"",SUMIFS(Data!$Y$4:$Y$64,Data!$U$4:$U$64,2023,Data!$V$4:$V$64,7)) -> 0.049692086 | I72: =IF(COUNTIFS(Data!$U$4:$U$64,2023,Data!$V$4:$V$64,8)=0,"",SUMIFS(Data!$Y$4:$Y$64,Data!$U$4:$U$64,2023,Data!$V$4:$V$64,8)) -> 0.02980397 | J72: =IF(COUNTIFS(Data!$U$4:$U$64,2023,Data!$V$4:$V$64,9)=0,"",SUMIFS(Data!$Y$4:$Y$64,Data!$U$4:$U$64,2023,Data!$V$4:$V$64,9)) -> -0.02838281 | K72: =IF(COUNTIFS(Data!$U$4:$U$64,2023,Data!$V$4:$V$64,10)=0,"",SUMIFS(Data!$Y$4:$Y$64,Data!$U$4:$U$64,2023,Data!$V$4:$V$64,10)) -> 0.018921068 | L72: =IF(COUNTIFS(Data!$U$4:$U$64,2023,Data!$V$4:$V$64,11)=0,"",SUMIFS(Data!$Y$4:$Y$64,Data!$U$4:$U$64,2023,Data!$V$4:$V$64,11)) -> 0.042039434 | M72: =IF(COUNTIFS(Data!$U$4:$U$64,2023,Data!$V$4:$V$64,12)=0,"",SUMIFS(Data!$Y$4:$Y$64,Data!$U$4:$U$64,2023,Data!$V$4:$V$64,12)) -> -0.019766504 | N72: =INDEX(Data!$AE$4:$AE$9,MATCH(2023,Data!$AA$4:$AA$9,0)) -> 0.14944818 | O72: =INDEX(Data!$AD$4:$AD$9,MATCH(2023,Data!$AA$4:$AA$9,0)) -> 0.25764377 | P72: =INDEX(Data!$AE$4:$AE$9,MATCH(2023,Data!$AA$4:$AA$9,0)) -> 0.14944818
A73: 2024 | B73: =IF(COUNTIFS(Data!$U$4:$U$64,2024,Data!$V$4:$V$64,1)=0,"",SUMIFS(Data!$Y$4:$Y$64,Data!$U$4:$U$64,2024,Data!$V$4:$V$64,1)) -> 0.027830421 | C73: =IF(COUNTIFS(Data!$U$4:$U$64,2024,Data!$V$4:$V$64,2)=0,"",SUMIFS(Data!$Y$4:$Y$64,Data!$U$4:$U$64,2024,Data!$V$4:$V$64,2)) -> 0.0043295443 | D73: =IF(COUNTIFS(Data!$U$4:$U$64,2024,Data!$V$4:$V$64,3)=0,"",SUMIFS(Data!$Y$4:$Y$64,Data!$U$4:$U$64,2024,Data!$V$4:$V$64,3)) -> -0.0016676549 | E73: =IF(COUNTIFS(Data!$U$4:$U$64,2024,Data!$V$4:$V$64,4)=0,"",SUMIFS(Data!$Y$4:$Y$64,Data!$U$4:$U$64,2024,Data!$V$4:$V$64,4)) -> 0.0046756444 | F73: =IF(COUNTIFS(Data!$U$4:$U$64,2024,Data!$V$4:$V$64,5)=0,"",SUMIFS(Data!$Y$4:$Y$64,Data!$U$4:$U$64,2024,Data!$V$4:$V$64,5)) -> 0.043699855 | G73: =IF(COUNTIFS(Data!$U$4:$U$64,2024,Data!$V$4:$V$64,6)=0,"",SUMIFS(Data!$Y$4:$Y$64,Data!$U$4:$U$64,2024,Data!$V$4:$V$64,6)) -> 0.017952468 | H73: =IF(COUNTIFS(Data!$U$4:$U$64,2024,Data!$V$4:$V$64,7)=0,"",SUMIFS(Data!$Y$4:$Y$64,Data!$U$4:$U$64,2024,Data!$V$4:$V$64,7)) -> 0.017736697 | I73: =IF(COUNTIFS(Data!$U$4:$U$64,2024,Data!$V$4:$V$64,8)=0,"",SUMIFS(Data!$Y$4:$Y$64,Data!$U$4:$U$64,2024,Data!$V$4:$V$64,8)) -> -0.018283006 | J73: =IF(COUNTIFS(Data!$U$4:$U$64,2024,Data!$V$4:$V$64,9)=0,"",SUMIFS(Data!$Y$4:$Y$64,Data!$U$4:$U$64,2024,Data!$V$4:$V$64,9)) -> -0.020016585 | K73: =IF(COUNTIFS(Data!$U$4:$U$64,2024,Data!$V$4:$V$64,10)=0,"",SUMIFS(Data!$Y$4:$Y$64,Data!$U$4:$U$64,2024,Data!$V$4:$V$64,10)) -> 0.02229387 | L73: =IF(COUNTIFS(Data!$U$4:$U$64,2024,Data!$V$4:$V$64,11)=0,"",SUMIFS(Data!$Y$4:$Y$64,Data!$U$4:$U$64,2024,Data!$V$4:$V$64,11)) -> 0.010819207 | M73: =IF(COUNTIFS(Data!$U$4:$U$64,2024,Data!$V$4:$V$64,12)=0,"",SUMIFS(Data!$Y$4:$Y$64,Data!$U$4:$U$64,2024,Data!$V$4:$V$64,12)) -> 0.0016139898 | N73: =INDEX(Data!$AE$4:$AE$9,MATCH(2024,Data!$AA$4:$AA$9,0)) -> 0.13131547 | O73: =INDEX(Data!$AD$4:$AD$9,MATCH(2024,Data!$AA$4:$AA$9,0)) -> 0.1516407 | P73: =INDEX(Data!$AE$4:$AE$9,MATCH(2024,Data!$AA$4:$AA$9,0)) -> 0.13131547
A74: 2025 | B74: =IF(COUNTIFS(Data!$U$4:$U$64,2025,Data!$V$4:$V$64,1)=0,"",SUMIFS(Data!$Y$4:$Y$64,Data!$U$4:$U$64,2025,Data!$V$4:$V$64,1)) -> -0.044896734 | C74: =IF(COUNTIFS(Data!$U$4:$U$64,2025,Data!$V$4:$V$64,2)=0,"",SUMIFS(Data!$Y$4:$Y$64,Data!$U$4:$U$64,2025,Data!$V$4:$V$64,2)) -> -0.040979675 | D74: =IF(COUNTIFS(Data!$U$4:$U$64,2025,Data!$V$4:$V$64,3)=0,"",SUMIFS(Data!$Y$4:$Y$64,Data!$U$4:$U$64,2025,Data!$V$4:$V$64,3)) -> 0.0091515191 | E74: =IF(COUNTIFS(Data!$U$4:$U$64,2025,Data!$V$4:$V$64,4)=0,"",SUMIFS(Data!$Y$4:$Y$64,Data!$U$4:$U$64,2025,Data!$V$4:$V$64,4)) -> -0.011914474 | F74: =IF(COUNTIFS(Data!$U$4:$U$64,2025,Data!$V$4:$V$64,5)=0,"",SUMIFS(Data!$Y$4:$Y$64,Data!$U$4:$U$64,2025,Data!$V$4:$V$64,5)) -> 0.00012411407 | G74: =IF(COUNTIFS(Data!$U$4:$U$64,2025,Data!$V$4:$V$64,6)=0,"",SUMIFS(Data!$Y$4:$Y$64,Data!$U$4:$U$64,2025,Data!$V$4:$V$64,6)) -> -0.0016807137 | H74: =IF(COUNTIFS(Data!$U$4:$U$64,2025,Data!$V$4:$V$64,7)=0,"",SUMIFS(Data!$Y$4:$Y$64,Data!$U$4:$U$64,2025,Data!$V$4:$V$64,7)) -> 0.031229857 | I74: =IF(COUNTIFS(Data!$U$4:$U$64,2025,Data!$V$4:$V$64,8)=0,"",SUMIFS(Data!$Y$4:$Y$64,Data!$U$4:$U$64,2025,Data!$V$4:$V$64,8)) -> 0.020105629 | J74: =IF(COUNTIFS(Data!$U$4:$U$64,2025,Data!$V$4:$V$64,9)=0,"",SUMIFS(Data!$Y$4:$Y$64,Data!$U$4:$U$64,2025,Data!$V$4:$V$64,9)) -> -0.021619689 | K74: =IF(COUNTIFS(Data!$U$4:$U$64,2025,Data!$V$4:$V$64,10)=0,"",SUMIFS(Data!$Y$4:$Y$64,Data!$U$4:$U$64,2025,Data!$V$4:$V$64,10)) -> -0.0043364605 | L74: =IF(COUNTIFS(Data!$U$4:$U$64,2025,Data!$V$4:$V$64,11)=0,"",SUMIFS(Data!$Y$4:$Y$64,Data!$U$4:$U$64,2025,Data!$V$4:$V$64,11)) -> -0.04807097 | M74: =IF(COUNTIFS(Data!$U$4:$U$64,2025,Data!$V$4:$V$64,12)=0,"",SUMIFS(Data!$Y$4:$Y$64,Data!$U$4:$U$64,2025,Data!$V$4:$V$64,12)) -> 0.025252986 | N74: =INDEX(Data!$AE$4:$AE$9,MATCH(2025,Data!$AA$4:$AA$9,0)) -> -0.0970391 | O74: =INDEX(Data!$AD$4:$AD$9,MATCH(2025,Data!$AA$4:$AA$9,0)) -> 0.066865844 | P74: =INDEX(Data!$AE$4:$AE$9,MATCH(2025,Data!$AA$4:$AA$9,0)) -> -0.0970391
A75: 2026 | B75: =IF(COUNTIFS(Data!$U$4:$U$64,2026,Data!$V$4:$V$64,1)=0,"",SUMIFS(Data!$Y$4:$Y$64,Data!$U$4:$U$64,2026,Data!$V$4:$V$64,1)) -> 0.02117778 | C75: =IF(COUNTIFS(Data!$U$4:$U$64,2026,Data!$V$4:$V$64,2)=0,"",SUMIFS(Data!$Y$4:$Y$64,Data!$U$4:$U$64,2026,Data!$V$4:$V$64,2)) -> -0.018825048 | D75: =IF(COUNTIFS(Data!$U$4:$U$64,2026,Data!$V$4:$V$64,3)=0,"",SUMIFS(Data!$Y$4:$Y$64,Data!$U$4:$U$64,2026,Data!$V$4:$V$64,3)) -> 0.018072209 | E75: =IF(COUNTIFS(Data!$U$4:$U$64,2026,Data!$V$4:$V$64,4)=0,"",SUMIFS(Data!$Y$4:$Y$64,Data!$U$4:$U$64,2026,Data!$V$4:$V$64,4)) -> 0.030661682 | F75: =IF(COUNTIFS(Data!$U$4:$U$64,2026,Data!$V$4:$V$64,5)=0,"",SUMIFS(Data!$Y$4:$Y$64,Data!$U$4:$U$64,2026,Data!$V$4:$V$64,5)) -> 0.053548859 | G75: =IF(COUNTIFS(Data!$U$4:$U$64,2026,Data!$V$4:$V$64,6)=0,"",SUMIFS(Data!$Y$4:$Y$64,Data!$U$4:$U$64,2026,Data!$V$4:$V$64,6)) -> 0.007892971 | H75: =IF(COUNTIFS(Data!$U$4:$U$64,2026,Data!$V$4:$V$64,7)=0,"",SUMIFS(Data!$Y$4:$Y$64,Data!$U$4:$U$64,2026,Data!$V$4:$V$64,7)) -> 0.0044476546 | I75: =IF(COUNTIFS(Data!$U$4:$U$64,2026,Data!$V$4:$V$64,8)=0,"",SUMIFS(Data!$Y$4:$Y$64,Data!$U$4:$U$64,2026,Data!$V$4:$V$64,8)) -> -0.0042243117 | J75: =IF(COUNTIFS(Data!$U$4:$U$64,2026,Data!$V$4:$V$64,9)=0,"",SUMIFS(Data!$Y$4:$Y$64,Data!$U$4:$U$64,2026,Data!$V$4:$V$64,9)) | K75: =IF(COUNTIFS(Data!$U$4:$U$64,2026,Data!$V$4:$V$64,10)=0,"",SUMIFS(Data!$Y$4:$Y$64,Data!$U$4:$U$64,2026,Data!$V$4:$V$64,10)) | L75: =IF(COUNTIFS(Data!$U$4:$U$64,2026,Data!$V$4:$V$64,11)=0,"",SUMIFS(Data!$Y$4:$Y$64,Data!$U$4:$U$64,2026,Data!$V$4:$V$64,11)) | M75: =IF(COUNTIFS(Data!$U$4:$U$64,2026,Data!$V$4:$V$64,12)=0,"",SUMIFS(Data!$Y$4:$Y$64,Data!$U$4:$U$64,2026,Data!$V$4:$V$64,12)) | N75: =INDEX(Data!$AE$4:$AE$9,MATCH(2026,Data!$AA$4:$AA$9,0)) -> 0.11581907 | O75: =INDEX(Data!$AD$4:$AD$9,MATCH(2026,Data!$AA$4:$AA$9,0)) -> -0.0079760217 | P75: =INDEX(Data!$AE$4:$AE$9,MATCH(2026,Data!$AA$4:$AA$9,0)) -> 0.11581907
A76: Month avg | B76: =IFERROR(AVERAGE(B70:B75),"") -> 0.0038501627 | C76: =IFERROR(AVERAGE(C70:C75),"") -> -0.0042041273 | D76: =IFERROR(AVERAGE(D70:D75),"") -> 0.015901142 | E76: =IFERROR(AVERAGE(E70:E75),"") -> 0.0020241469 | F76: =IFERROR(AVERAGE(F70:F75),"") -> 0.018851276 | G76: =IFERROR(AVERAGE(G70:G75),"") -> 0.0036947067 | H76: =IFERROR(AVERAGE(H70:H75),"") -> 0.015780254 | I76: =IFERROR(AVERAGE(I70:I75),"") -> 0.0031244602 | ... M76: =IFERROR(AVERAGE(M70:M75),"") -> 0.0015857229
A77: % positive | B77: =IFERROR(COUNTIF(B70:B75,">0")/COUNT(B70:B75),"") -> 0.8 | C77: =IFERROR(COUNTIF(C70:C75,">0")/COUNT(C70:C75),"") -> 0.6 | D77: =IFERROR(COUNTIF(D70:D75,">0")/COUNT(D70:D75),"") -> 0.6 | E77: =IFERROR(COUNTIF(E70:E75,">0")/COUNT(E70:E75),"") -> 0.6 | F77: =IFERROR(COUNTIF(F70:F75,">0")/COUNT(F70:F75),"") -> 0.6 | G77: =IFERROR(COUNTIF(G70:G75,">0")/COUNT(G70:G75),"") -> 0.6 | H77: =IFERROR(COUNTIF(H70:H75,">0")/COUNT(H70:H75),"") -> 0.8 | I77: =IFERROR(COUNTIF(I70:I75,">0")/COUNT(I70:I75),"") -> 0.5 | ... M77: =IFERROR(COUNTIF(M70:M75,">0")/COUNT(M70:M75),"") -> 0.6
A80: 5 · Trade-level net return distribution — strategy vs placebo (random books, same mechanics)
A81: Bin (net return) | B81: Lower | C81: Upper | D81: Strategy (% of trades) | E81: Placebo (% of trades)
A82: < -40% | B82: -9.99 | C82: -0.4 | D82: =COUNTIFS('Trade Log'!$O$5:$O$571,">="&B82,'Trade Log'!$O$5:$O$571,"<"&C82)/COUNT('Trade Log'!$O$5:$O$571) -> 0.0035273369 | E82: =COUNTIFS(Data!$BI$4:$BI$23245,">="&B82,Data!$BI$4:$BI$23245,"<"&C82)/COUNT(Data!$BI$4:$BI$23245) -> 0.0027106101
A83: -40% to -35% | B83: -0.4 | C83: -0.35 | D83: =COUNTIFS('Trade Log'!$O$5:$O$571,">="&B83,'Trade Log'!$O$5:$O$571,"<"&C83)/COUNT('Trade Log'!$O$5:$O$571) -> 0.0017636684 | E83: =COUNTIFS(Data!$BI$4:$BI$23245,">="&B83,Data!$BI$4:$BI$23245,"<"&C83)/COUNT(Data!$BI$4:$BI$23245) -> 0.0011186645
A84: -35% to -30% | B84: -0.35 | C84: -0.3 | D84: =COUNTIFS('Trade Log'!$O$5:$O$571,">="&B84,'Trade Log'!$O$5:$O$571,"<"&C84)/COUNT('Trade Log'!$O$5:$O$571) -> 0.0035273369 | E84: =COUNTIFS(Data!$BI$4:$BI$23245,">="&B84,Data!$BI$4:$BI$23245,"<"&C84)/COUNT(Data!$BI$4:$BI$23245) -> 0.0061526547
A85: -30% to -25% | B85: -0.3 | C85: -0.25 | D85: =COUNTIFS('Trade Log'!$O$5:$O$571,">="&B85,'Trade Log'!$O$5:$O$571,"<"&C85)/COUNT('Trade Log'!$O$5:$O$571) -> 0.010582011 | E85: =COUNTIFS(Data!$BI$4:$BI$23245,">="&B85,Data!$BI$4:$BI$23245,"<"&C85)/COUNT(Data!$BI$4:$BI$23245) -> 0.0092074692
A86: -25% to -20% | B86: -0.25 | C86: -0.2 | D86: =COUNTIFS('Trade Log'!$O$5:$O$571,">="&B86,'Trade Log'!$O$5:$O$571,"<"&C86)/COUNT('Trade Log'!$O$5:$O$571) -> 0.0335097 | E86: =COUNTIFS(Data!$BI$4:$BI$23245,">="&B86,Data!$BI$4:$BI$23245,"<"&C86)/COUNT(Data!$BI$4:$BI$23245) -> 0.025987437
A87: -20% to -15% | B87: -0.2 | C87: -0.15 | D87: =COUNTIFS('Trade Log'!$O$5:$O$571,">="&B87,'Trade Log'!$O$5:$O$571,"<"&C87)/COUNT('Trade Log'!$O$5:$O$571) -> 0.044091711 | E87: =COUNTIFS(Data!$BI$4:$BI$23245,">="&B87,Data!$BI$4:$BI$23245,"<"&C87)/COUNT(Data!$BI$4:$BI$23245) -> 0.059332243
A88: -15% to -10% | B88: -0.15 | C88: -0.1 | D88: =COUNTIFS('Trade Log'!$O$5:$O$571,">="&B88,'Trade Log'!$O$5:$O$571,"<"&C88)/COUNT('Trade Log'!$O$5:$O$571) -> 0.065255732 | E88: =COUNTIFS(Data!$BI$4:$BI$23245,">="&B88,Data!$BI$4:$BI$23245,"<"&C88)/COUNT(Data!$BI$4:$BI$23245) -> 0.089105929
A89: -10% to -5% | B89: -0.1 | C89: -0.05 | D89: =COUNTIFS('Trade Log'!$O$5:$O$571,">="&B89,'Trade Log'!$O$5:$O$571,"<"&C89)/COUNT('Trade Log'!$O$5:$O$571) -> 0.1340388 | E89: =COUNTIFS(Data!$BI$4:$BI$23245,">="&B89,Data!$BI$4:$BI$23245,"<"&C89)/COUNT(Data!$BI$4:$BI$23245) -> 0.13604681
A90: -5% to 0% | B90: -0.05 | C90: 0 | D90: =COUNTIFS('Trade Log'!$O$5:$O$571,">="&B90,'Trade Log'!$O$5:$O$571,"<"&C90)/COUNT('Trade Log'!$O$5:$O$571) -> 0.11992945 | E90: =COUNTIFS(Data!$BI$4:$BI$23245,">="&B90,Data!$BI$4:$BI$23245,"<"&C90)/COUNT(Data!$BI$4:$BI$23245) -> 0.14219947
A91: 0% to 5% | B91: 0 | C91: 0.05 | D91: =COUNTIFS('Trade Log'!$O$5:$O$571,">="&B91,'Trade Log'!$O$5:$O$571,"<"&C91)/COUNT('Trade Log'!$O$5:$O$571) -> 0.13051146 | E91: =COUNTIFS(Data!$BI$4:$BI$23245,">="&B91,Data!$BI$4:$BI$23245,"<"&C91)/COUNT(Data!$BI$4:$BI$23245) -> 0.13639102
A92: 5% to 10% | B92: 0.05 | C92: 0.1 | D92: =COUNTIFS('Trade Log'!$O$5:$O$571,">="&B92,'Trade Log'!$O$5:$O$571,"<"&C92)/COUNT('Trade Log'!$O$5:$O$571) -> 0.13756614 | E92: =COUNTIFS(Data!$BI$4:$BI$23245,">="&B92,Data!$BI$4:$BI$23245,"<"&C92)/COUNT(Data!$BI$4:$BI$23245) -> 0.11982618
A93: 10% to 15% | B93: 0.1 | C93: 0.15 | D93: =COUNTIFS('Trade Log'!$O$5:$O$571,">="&B93,'Trade Log'!$O$5:$O$571,"<"&C93)/COUNT('Trade Log'!$O$5:$O$571) -> 0.10758377 | E93: =COUNTIFS(Data!$BI$4:$BI$23245,">="&B93,Data!$BI$4:$BI$23245,"<"&C93)/COUNT(Data!$BI$4:$BI$23245) -> 0.094441098
... A103: ≥ 60% | B103: 0.6 | C103: 9.99 | D103: =COUNTIFS('Trade Log'!$O$5:$O$571,">="&B103,'Trade Log'!$O$5:$O$571,"<"&C103)/COUNT('Trade Log'!$O$5:$O$571) -> 0.0088183422 | E103: =COUNTIFS(Data!$BI$4:$BI$23245,">="&B103,Data!$BI$4:$BI$23245,"<"&C103)/COUNT(Data!$BI$4:$BI$23245) -> 0.0067119869
A107: 6 · Fold-by-fold robustness — quarterly bars, green = positive, red = negative
A124: Source: corrected/nav_daily_corrected.csv, rolling_12m, monthly_returns, yearly_returns, trade_ledger, placebo_trade_returns, signal_folds_60d, quarterly_portfolio_excess · Built from CORRECTED_REPORT.md (revision 2) outputs · Workbook generated 2026-09-23

Sheet Trade Log
A1: Trade Log — every trade of the frozen configuration, A to Z (chronological)
A2: Forward-test candidate — not validated. Net return = gross − 0.585% round trip. Excess vs benchmark = gross return − NIFTY 500 price-index return between entry and exit dates. Price path = daily Close ÷ entry Open, entry to exit.
A4: Entry date | B4: Symbol | C4: Company | D4: Sector | E4: Filing timestamp (IST) | F4: Event day | G4: Entry price (Open) | H4: Exit date | I4: Exit price (Close) | J4: Holding days (sessions) | K4: SUE | L4: SUE quintile | M4: Gross return | N4: Cost | O4: Net return | P4: Excess vs NIFTY 500 | Q4: Period | R4: Result | S4: Price path
A5: 44419 | B5: SHREECEM | C5: SHREE CEMENT LIMITED | D5: Cement & Cement Products | E5: 44417.767 | F5: 44418 | G5: 26650.973 | H5: 44509 | I5: 28623.867 | J5: 60 | K5: 2.0311596 | L5: 5 | M5: 0.074027106 | N5: 0.00585 | O5: 0.068177106 | P5: -0.045988315 | Q5: Discovery | R5: Win
A6: 44421 | B6: POWERGRID | C6: Power Grid Corporation of India Limited | D6: Power | E6: 44419.679 | F6: 44420 | G6: 106.78037 | H6: 44511 | I6: 107.45535 | J6: 60 | K6: 10.013007 | L6: 5 | M6: 0.0063211876 | N6: 0.00585 | O6: 0.0004711876 | P6: -0.089361094 | Q6: Discovery | R6: Win
A7: 44421 | B7: HINDALCO | C7: Hindalco Industries Limited | D7: Metals | E7: 44419.725 | F7: 44420 | G7: 422.83556 | H7: 44511 | I7: 438.8345 | J7: 60 | K7: 3.0824236 | L7: 5 | M7: 0.037837271 | N7: 0.00585 | O7: 0.031987271 | P7: -0.057845011 | Q7: Discovery | R7: Win
A8: 44421 | B8: ASTERDM | C8: Aster DM Quality Care Limited | D8: Healthcare Services | E8: 44420.552 | F8: 44420 | G8: 125.29557 | H8: 44511 | I8: 153.65512 | J8: 60 | K8: 2.6427573 | L8: 5 | M8: 0.22634116 | N8: 0.00585 | O8: 0.22049116 | P8: 0.13065888 | Q8: Discovery | R8: Win
A9: 44421 | B9: SUPRAJIT | C9: Suprajit Engineering Limited | D9: Automobile | E9: 44420.394 | F9: 44420 | G9: 308.38685 | H9: 44511 | I9: 351.39987 | J9: 60 | K9: 1.8476518 | L9: 5 | M9: 0.13947749 | N9: 0.00585 | O9: 0.13362749 | P9: 0.043795207 | Q9: Discovery | R9: Win
A10: 44421 | B10: PTC | C10: PTC India Limited | D10: Power | E10: 44420.497 | F10: 44420 | G10: 65.20744 | H10: 44511 | I10: 84.215179 | J10: 60 | K10: 1.6833341 | L10: 5 | M10: 0.29149648 | N10: 0.00585 | O10: 0.28564648 | P10: 0.1958142 | Q10: Discovery | R10: Win
A11: 44424 | B11: CUMMINSIND | C11: Cummins India Limited | D11: Industrial Manufacturing | E11: 44420.693 | F11: 44421 | G11: 914.80906 | H11: 44512 | I11: 858.83167 | J11: 60 | K11: 3.8741236 | L11: 5 | M11: -0.061190245 | N11: 0.00585 | O11: -0.067040245 | P11: -0.16837676 | Q11: Discovery | R11: Loss
A12: 44424 | B12: TATASTEEL | C12: Tata Steel Limited | D12: Metals | E12: 44420.791 | F12: 44421 | G12: 127.97396 | H12: 44512 | I12: 111.00708 | J12: 60 | K12: 2.5486866 | L12: 5 | M12: -0.13258074 | N12: 0.00585 | O12: -0.13843074 | P12: -0.23976725 | Q12: Discovery | R12: Loss
A13: 44424 | B13: GRASIM | C13: Grasim Industries Limited | D13: Cement & Cement Products | E13: 44421.628 | F13: 44421 | G13: 1460.0643 | H13: 44512 | I13: 1810.2985 | J13: 60 | K13: 2.3036121 | L13: 5 | M13: 0.23987587 | N13: 0.00585 | O13: 0.23402587 | P13: 0.13268935 | Q13: Discovery | R13: Win
A14: 44424 | B14: KNRCON | C14: KNR Constructions Limited | D14: Construction | E14: 44420.698 | F14: 44421 | G14: 285.10595 | H14: 44512 | I14: 283.06369 | J14: 60 | K14: 2.0313248 | L14: 5 | M14: -0.0071631521 | N14: 0.00585 | O14: -0.013013152 | P14: -0.11434967 | Q14: Discovery | R14: Loss
A15: 44424 | B15: SUNDRMFAST | C15: Sundram Fasteners Limited | D15: Automobile | E15: 44420.699 | F15: 44421 | G15: 753.74181 | H15: 44512 | I15: 793.16162 | J15: 60 | K15: 1.9948311 | L15: 5 | M15: 0.052298826 | N15: 0.00585 | O15: 0.046448826 | P15: -0.054887688 | Q15: Discovery | R15: Win
A16: 44424 | B16: REDINGTON | C16: Redington Limited | D16: Services | E16: 44421.547 | F16: 44421 | G16: 150.95597 | H16: 44512 | I16: 127.36713 | J16: 60 | K16: 1.8469303 | L16: 5 | M16: -0.15626307 | N16: 0.00585 | O16: -0.16211307 | P16: -0.26344959 | Q16: Discovery | R16: Loss
... A571: 46157 | B571: ECLERX | C571: eClerx Services Limited | D571: IT | E571: 46155.822 | F571: 46156 | G571: 1535.1489 | H571: 46245 | I571: 1794.6051 | J571: 60 | K571: 1.7003528 | L571: 5 | M571: 0.16901044 | N571: 0.00585 | O571: 0.16316044 | P571: 0.11796999 | Q571: Holdout | R571: Win
A572: TOTALS | B572: =COUNTA(B5:B571) -> 567 | M572: =AVERAGE(M5:M571) -> 0.051934937 | N572: avg net → | O572: =AVERAGE(O5:O571) -> 0.046084937 | P572: =AVERAGE(P5:P571) -> 0.022942353 | Q572: win rate → | R572: =COUNTIF(R5:R571,"Win")/COUNTA(R5:R571) -> 0.58377425
A574: Source: corrected/trade_ledger_corrected.csv; price paths from pead/cache/px (NSE-calendar filtered) · Built from CORRECTED_REPORT.md (revision 2) outputs · Workbook generated 2026-09-23

Sheet Risk Diagnostics
A1: Risk & Robustness Diagnostics
A2: Forward-test candidate — not validated. Signal tests use the cross-sectional event sample; KT5 is the only portfolio-level kill test.
A4: Tail risk (daily NAV returns)
A5: Metric | B5: Full Period | C5: Discovery | D5: Holdout
A6: VaR 95% (1-day) | B6: =Data!C27 -> 0.016145473 | C6: =Data!D27 -> 0.014830713 | D6: =Data!E27 -> 0.016855544
A7: CVaR 95% (1-day) | B7: =Data!C28 -> 0.025294984 | C7: =Data!D28 -> 0.023651239 | D7: =Data!E28 -> 0.02599451
A8: Skewness (daily) | B8: =Data!C29 -> -0.84651235 | C8: =Data!D29 -> -0.86821847 | D8: =Data!E29 -> -0.80798231
A9: Excess kurtosis (daily) | B9: =Data!C30 -> 4.3629052 | C9: =Data!D30 -> 3.9249457 | D9: =Data!E30 -> 4.5016245
A10: Annualised volatility | B10: =Data!C14 -> 0.16071962 | C10: =Data!D14 -> 0.14845989 | D10: =Data!E14 -> 0.16698793
A11: Maximum drawdown | B11: =Data!C22 -> -0.23675278 | C11: =Data!D22 -> -0.19281551 | D11: =Data!E22 -> -0.24950465
A13: Signal breakdown — Q5 minus Q1, 60 trading days, excess vs event universe
A14: Cut | B14: Q5 n | C14: Q1 n | D14: Q5 | E14: Q1 | F14: Spread | G14: p-value | H14: Folds + | I14: Folds | J14: Ex-best fold
A15: All events | B15: =Data!BY4 -> 1427 | C15: =Data!BZ4 -> 1503 | D15: =Data!CA4 -> 0.014148459 | E15: =Data!CB4 -> -0.015953365 | F15: =Data!CC4 -> 0.030101824 | G15: =Data!CD4 -> 1.2828659e-07 | H15: =Data!CE4 -> 17 | I15: =Data!CF4 -> 20 | J15: =Data!CG4 -> 0.030570657
A16: Discovery (≤ 2023) | B16: =Data!BY5 -> 635 | C16: =Data!BZ5 -> 709 | D16: =Data!CA5 -> 0.017005464 | E16: =Data!CB5 -> -0.017284883 | F16: =Data!CC5 -> 0.034290347 | G16: =Data!CD5 -> 0.00013057945 | H16: =Data!CE5 -> 8 | I16: =Data!CF5 -> 10 | J16: =Data!CG5 -> 0.034967031
A17: Holdout (≥ 2024) | B17: =Data!BY6 -> 792 | C17: =Data!BZ6 -> 794 | D17: =Data!CA6 -> 0.011857805 | E17: =Data!CB6 -> -0.01476439 | F17: =Data!CC6 -> 0.026622195 | G17: =Data!CD6 -> 0.00030198287 | H17: =Data!CE6 -> 9 | I17: =Data!CF6 -> 10 | J17: =Data!CG6 -> 0.021958328
A18: Size: Small (turnover tercile) | B18: =Data!BY16 -> 358 | C18: =Data!BZ16 -> 595 | D18: =Data!CA16 -> 0.013769867 | E18: =Data!CB16 -> -0.028702101 | F18: =Data!CC16 -> 0.042471968 | G18: =Data!CD16 -> 2.7411364e-05 | H18: =Data!CE16 -> 19 | I18: =Data!CF16 -> 20 | J18: =Data!CG16 -> 0.040572279
A19: Size: Mid | B19: =Data!BY17 -> 483 | C19: =Data!BZ17 -> 504 | D19: =Data!CA17 -> 0.017130432 | E19: =Data!CB17 -> -0.0051172498 | F19: =Data!CC17 -> 0.022247681 | G19: =Data!CD17 -> 0.037625719 | H19: =Data!CE17 -> 13 | I19: =Data!CF17 -> 20 | J19: =Data!CG17 -> 0.0177489
A20: Size: Large | B20: =Data!BY18 -> 586 | C20: =Data!BZ18 -> 404 | D20: =Data!CA18 -> 0.011921912 | E20: =Data!CB18 -> -0.010695701 | F20: =Data!CC18 -> 0.022617613 | G20: =Data!CD18 -> 0.012214283 | H20: =Data!CE18 -> 14 | I20: =Data!CF18 -> 19 | J20: =Data!CG18 -> 0.022999998
A21: Non-Financials (traded universe) | B21: =Data!BY14 -> 1114 | C21: =Data!BZ14 -> 1403 | D21: =Data!CA14 -> 0.014836427 | E21: =Data!CB14 -> -0.019594424 | F21: =Data!CC14 -> 0.034430851 | G21: =Data!CD14 -> 3.6533215e-08 | H21: =Data!CE14 -> 17 | I21: =Data!CF14 -> 20 | J21: =Data!CG14 -> 0.035126845
A22: Financials (EXCLUDED) | B22: =Data!BY15 -> 313 | C22: =Data!BZ15 -> 100 | D22: =Data!CA15 -> 0.011699911 | E22: =Data!CB15 -> 0.035130698 | F22: =Data!CC15 -> -0.023430787 | G22: =Data!CD15 -> 0.19359791 | H22: =Data!CE15 -> 9 | I22: =Data!CF15 -> 17 | J22: =Data!CG15 -> -0.024415901
A23: Financials excluded: banks, NBFCs, housing finance, insurers, AMCs, exchanges/market infrastructure and rating agencies, identified by the XBRL pipeline 'fin' flag (taxonomy BANKING/NBFC or industry = FINANCIAL SERVICES). Provision-driven profits make a seasonal-random-walk SUE a poor surprise proxy; the financials spread is negative and not significant.
A26: Kill tests (corrected)
A27: Test | B27: Perturbation | E27: Result | J27: Pass?
A28: =Data!CJ4 -> KT1 | B28: =Data!CK4 -> Drop top-2 quarterly folds (2021Q3 & 2022Q1) | E28: =Data!CL4 -> fold-mean +3.45% -> +2.75%, folds+ 83.3%; event-level spread +2.62% | J28: =IF(Data!CM4,"PASS","FAIL") -> PASS
A29: =Data!CJ5 -> KT2 | B29: =Data!CK5 -> Drop 2021 | E29: =Data!CL5 -> spread +2.88%, p=7.9e-07 | J29: =IF(Data!CM5,"PASS","FAIL") -> PASS
A30: =Data!CJ6 -> KT3 | B30: =Data!CK6 -> Mid + Large caps only | E30: =Data!CL6 -> spread +2.19%, p=0.0017 | J30: =IF(Data!CM6,"PASS","FAIL") -> PASS
A31: =Data!CJ7 -> KT4 | B31: =Data!CK7 -> Exclude Layer-4-seen events | E31: =Data!CL7 -> spread +3.05%, folds+ 85.0% | J31: =IF(Data!CM7,"PASS","FAIL") -> PASS
A32: =Data!CJ8 -> KT5 | B32: =Data!CK8 -> 1.000% round-trip cost (portfolio) | E32: =Data!CL8 -> full excess +4.06%, HOLDOUT excess -0.88% | J32: =IF(Data!CM8,"PASS","FAIL") -> FAIL
A33: =Data!CJ9 -> KT6 | B33: =Data!CK9 -> 8Q / expanding threshold windows | E33: =Data!CL9 -> 8Q +2.91%, expanding +2.83% | J33: =IF(Data!CM9,"PASS","FAIL") -> PASS
A34: =Data!CJ10 -> KT7 | B34: =Data!CK10 -> Horizon jitter 40d / 90d | E34: =Data!CL10 -> 40d +1.82%, 90d +3.92% | J34: =IF(Data!CM10,"PASS","FAIL") -> PASS
A35: Reading: every signal-level test passes; the portfolio-level cost test (KT5) fails because at 1.0% round-trip cost the holdout book trails NIFTY 500. KT1 compares the mean of quarterly fold spreads with and without the two best quarters (2021Q3, 2022Q1).
A38: Cost sensitivity
A39: Round-trip cost | B39: Full CAGR | C39: Full excess* | D39: Full Sharpe (rf 0) | E39: Full max DD | F39: Holdout CAGR | G39: Holdout excess*
A40: =Data!BO4 -> 0.003 | B40: =Data!BP4 -> 0.18416048 | C40: =Data!BQ4 -> 0.071325899 | D40: =Data!BR4 -> 1.1503883 | E40: =Data!BS4 -> -0.2328879 | F40: =Data!BT4 -> 0.098906978 | G40: =Data!BU4 -> 0.019972509
A41: =Data!BO5 -> 0.00585 | B41: =Data!BP5 -> 0.17155034 | C41: =Data!BQ5 -> 0.058715761 | D41: =Data!BR5 -> 1.0827253 | E41: =Data!BS5 -> -0.23675278 | F41: =Data!BT5 -> 0.087085033 | G41: =Data!BU5 -> 0.0081505638
A42: =Data!BO6 -> 0.01 | B42: =Data!BP6 -> 0.15342996 | C42: =Data!BQ6 -> 0.040595379 | D42: =Data!BR6 -> 0.98408992 | E42: =Data!BS6 -> -0.24234357 | F42: =Data!BT6 -> 0.070100271 | G42: =Data!BU6 -> -0.0088341983
A44: Capacity — share of trades that fit within 1% / 5% of 20-day median traded value
A62: Source: corrected/period_metrics_corrected.csv, signal_cells.csv, kill_tests_corrected.csv, cost_sensitivity_corrected.csv, capacity_curve_corrected.csv · Built from CORRECTED_REPORT.md (revision 2) outputs · Workbook generated 2026-09-23

Sheet Methodology
A1: Methodology & Disclaimers
A4: Status
A5: DISCOVERY — NOT VALIDATED. StackFlow PEAD V2 is a FORWARD-TEST CANDIDATE. The cross-sectional signal is confirmed; the long-only trading strategy is not validated. Nothing in this workbook is investment advice or a live-trading recommendation.
A7: Signal — Standardised Unexpected Earnings (SUE)
A8: SUE_q = (PAT_q − PAT of the same fiscal quarter one year earlier) ÷ standard deviation of the YoY PAT changes of the 8 prior quarters (at least 6 required). Seasonal random walk: NO analyst estimates are used. YoY is matched by fiscal quarter-end date (audit fix 5), so gaps in the XBRL series never compare the wrong quarters.
A9: Ex-ante buckets (model M1): for an event on day T, quintile cut-offs are the 20/40/60/80th percentiles of SUE across all qualifying events with event day in [T−365, T), minimum 150 prior events (pre-registration said 200; disclosed deviation; with 200 the spread is unchanged). Events 2021-08-10 → 2022-02-09 use truncated windows because data begins 2021-02-10. The strategy buys Q5 only.
A11: Universe and filters
A12: NSE equities with quarterly XBRL PAT (earliest parseable filing per company-quarter, Consolidated first, Standalone fallback). 20-session average traded value before the event day ≥ INR 1 crore; entry Open > INR 50. Prices restricted to NSE sessions (phantom zero-volume holiday rows removed, audit fix 6). Financial sector excluded by the XBRL pipeline 'fin' flag: taxonomy BANKING/NBFC or industry FINANCIAL SERVICES — banks, NBFCs, housing finance, insurers, AMCs, exchanges, rating agencies (audit fix 4). Universe = 421 symbols with a price history today: survivorship bias is not removed.
A14: Entry / exit timing (reconciled rule, TIMING_RULES.md)
A15: Case A — filing ≤ 15:30 IST on a session day D: event day = D; entry = OPEN of the next session.
A16: Case B — filing > 15:30 IST on a session day D: event day = next session; entry = OPEN of the session after that.
A17: Case C — filing on a weekend/holiday: ≤ 15:30 IST → event day = first session D1, entry = OPEN of D2; > 15:30 IST → event day = D2, entry = OPEN of D3 (as coded; conservative).
... A45: Source: CORRECTED_REPORT.md (rev 2), live_config_pead_v2_corrected.md, TIMING_RULES.md, AUDIT_REPORT.md · Built from CORRECTED_REPORT.md (revision 2) outputs · Workbook generated 2026-09-23

Sheet Data
A1: Period metrics (corrected/period_metrics_corrected.csv) | I1: Daily NAV, rebased to 100 (corrected/nav_daily_corrected.csv) | T1: Monthly returns (corrected/monthly_returns_corrected.csv) | AA1: Calendar-year returns (corrected/yearly_returns_corrected.csv) | AH1: Rolling 12-month (252-session) returns (corrected/rolling_12m_corrected.csv) | AM1: Signal: quarterly Q5-Q1 spread, 60d, xs event universe (corrected/signal_folds_60d.csv) | AU1: Portfolio: quarterly return vs NIFTY 500 (corrected/quarterly_portfolio_excess_corrected.csv) | BB1: Placebo: 40 random books, same mechanics (corrected/placebo_random_books.csv) | BI1: Placebo trade-level net returns (corrected/placebo_trade_returns.csv) | BK1: Capacity curve (corrected/capacity_curve_corrected.csv) | BO1: Cost sensitivity (corrected/cost_sensitivity_corrected.csv) | BX1: Signal cells, 60d unless stated (corrected/signal_cells.csv) | CJ1: Kill tests (corrected/kill_tests_corrected.csv) | CP1: Per-trade price path: Close / entry Open, entry day to exit day (calendar-filtered pead/cache/px)
P2: band height = | Q2: 225
A3: key | B3: metric | C3: Full Period | D3: Discovery | E3: Holdout | F3: Discovery (calendar split of full book) | G3: Holdout (calendar split of full book) | I3: date | J3: strategy_nav | K3: nifty500 | L3: strategy_dd | M3: nifty500_dd | N3: positions_held | O3: period | P3: band_discovery | Q3: band_holdout | T3: month_end | U3: year | V3: month | W3: strategy | X3: nifty500 | Y3: excess | AA3: year | AB3: window | AC3: strategy | AD3: nifty500 | AE3: excess | AF3: trades_entered | AH3: date | AI3: strategy_12m | AJ3: nifty500_12m | AK3: excess_12m | AM3: qtr | AN3: period | AO3: n_hi | AP3: n_lo | AQ3: spread | AR3: positive | AS3: negative | AU3: quarter | AV3: strategy | AW3: nifty500 | AX3: excess | AY3: positive | AZ3: negative | BB3: draw | BC3: trades | BD3: cagr | BE3: excess_cagr | BF3: sharpe_rf0 | BG3: holdout_excess_cagr | BI3: net_return | BK3: aum_cr | BL3: pct_trades_within_1pct_adv | BM3: pct_trades_within_5pct_adv | BO3: round_trip_cost | BP3: full_cagr | BQ3: full_excess | BR3: full_sharpe_rf0 | BS3: full_max_dd | BT3: holdout_cagr | BU3: holdout_excess | BX3: label | BY3: n_q5 | BZ3: n_q1 | CA3: q5_pct | CB3: q1_pct | CC3: spread_pct | CD3: p_val | CE3: folds_pos | CF3: folds_total | CG3: spread_ex_best_pct | CH3: inversions | CJ3: test | CK3: perturbation | CL3: result | CM3: passed | CP3: trade_id | CQ3: s0 | CR3: s1 | CS3: s2 | CT3: s3 | CU3: s4 | CV3: s5 | CW3: s6 | CX3: s7 | CY3: s8 | CZ3: s9 | DA3: s10 | DB3: s11 | DC3: s12 | DD3: s13 | DE3: s14 | DF3: s15 | DG3: s16 | DH3: s17 | DI3: s18 | DJ3: s19 | DK3: s20 | DL3: s21 | DM3: s22 | DN3: s23 | DO3: s24 | DP3: s25 | DQ3: s26 | DR3: s27 | DS3: s28 | DT3: s29 | DU3: s30 | DV3: s31 | DW3: s32 | DX3: s33 | DY3: s34 | DZ3: s35 | EA3: s36 | EB3: s37 | EC3: s38 | ED3: s39 | EE3: s40 | EF3: s41 | EG3: s42 | EH3: s43 | EI3: s44 | EJ3: s45 | EK3: s46 | EL3: s47 | EM3: s48 | EN3: s49 | EO3: s50 | EP3: s51 | EQ3: s52 | ER3: s53 | ES3: s54 | ET3: s55 | EU3: s56 | EV3: s57 | EW3: s58 | EX3: s59 | EY3: s60
A4: start | B4: Window start | C4: 2021-08-11 | D4: 2021-08-11 | E4: 2024-01-17 | F4: 2021-08-11 | G4: 2023-12-29 | I4: 44419 | J4: 100 | K4: 100 | L4: 0 | M4: 0 | N4: 1 | O4: Discovery | P4: =IF(O4="Discovery",$Q$2,0) -> 225 | Q4: =IF(O4="Holdout",$Q$2,0) -> 0 | T4: 44439 | U4: 2021 | V4: 8 | W4: 0.017963758 | X4: 0.048956693 | Y4: -0.030992935 | AA4: 2021 | AB4: 2021-08-11 to 2021-12-31 | AC4: 0.071650172 | AD4: 0.080686482 | AE4: -0.0090363098 | AF4: 37 | AH4: 44790 | AI4: 0.12626574 | AJ4: 0.10827619 | AK4: 0.017989547 | AM4: 2021Q3 | AN4: Discovery | AO4: 19 | AP4: 14 | AQ4: 0.10896649 | AR4: =MAX(AQ4,0) -> 0.10896649 | AS4: =MIN(AQ4,0) -> 0 | AU4: 2021Q3 | AV4: 0.025965752 | AW4: 0.084754496 | AX4: -0.058788744 | AY4: =MAX(AX4,0) -> 0 | AZ4: =MIN(AX4,0) -> -0.058788744 | BB4: 1 | BC4: 583 | BD4: 0.072191984 | BE4: -0.040295949 | BF4: 0.51430182 | BG4: -0.024128245 | BI4: -0.079794257 | BK4: 0.5 | BL4: 0.98412698 | BM4: 1 | BO4: 0.003 | BP4: 0.18416048 | BQ4: 0.071325899 | BR4: 1.1503883 | BS4: -0.2328879 | BT4: 0.098906978 | BU4: 0.019972509 | BX4: Primary 60d (all) | BY4: 1427 | BZ4: 1503 | CA4: 0.014148459 | CB4: -0.015953365 | CC4: 0.030101824 | CD4: 1.2828659e-07 | CE4: 17 | CF4: 20 | CG4: 0.030570657 | CH4: 0 | CJ4: KT1 | CK4: Drop top-2 quarterly folds (2021Q3 & 2022Q1) | CL4: fold-mean +3.45% -> +2.75%, folds+ 83.3%; event-level spread +2.62% | CM4: TRUE | CP4: T0001 | CQ4: 0.97547308 | CR4: 0.97714487 | CS4: 0.97741683 | CT4: 0.95456742 | CU4: 0.96271352 | CV4: 0.96738187 | CW4: 0.96605365 | CX4: 0.95483909 | CY4: 0.96391496 | CZ4: 0.96594709 | DA4: 0.97578726 | DB4: 0.98834287 | DC4: 0.9979 | DD4: 1.0394231 | DE4: 1.0464174 | DF4: 1.1142108 | DG4: 1.1185302 | DH4: 1.1220117 | DI4: 1.1263494 | DJ4: 1.1315378 | DK4: 1.1270017 | DL4: 1.1267076 | DM4: 1.1265296 | DN4: 1.1405639 | DO4: 1.1266084 | DP4: 1.1228898 | DQ4: 1.1060774 | DR4: 1.1045342 | DS4: 1.0947087 | DT4: 1.0993661 | DU4: 1.0807202 | DV4: 1.0830792 | DW4: 1.0745158 | DX4: 1.07964 | DY4: 1.0619713 | DZ4: 1.0692469 | EA4: 1.0762189 | EB4: 1.057007 | EC4: 1.032877 | ED4: 1.031025 | EE4: 1.019921 | EF4: 1.029669 | EG4: 1.0180342 | EH4: 1.0220723 | EI4: 1.0272442 | EJ4: 1.0358735 | EK4: 1.0177035 | EL4: 1.0089068 | EM4: 1.0148335 | EN4: 1.0192246 | EO4: 1.0022046 | EP4: 1.0206835 | EQ4: 1.0328036 | ER4: 1.0359379 | ES4: 1.0521862 | ET4: 1.0709442 | EU4: 1.0607441 | EV4: 1.0648741 | EW4: 1.0673231 | EX4: 1.0849365 | EY4: 1.0740271
A5: end | B5: Window end | C5: 2026-08-11 | D5: 2024-02-13 | E5: 2026-08-11 | F5: 2023-12-29 | G5: 2026-08-11 | I5: 44420 | J5: 100.00556 | K5: 100.68749 | L5: 0 | M5: 0 | N5: 1 | O5: Discovery | P5: =IF(O5="Discovery",$Q$2,0) -> 225 | Q5: =IF(O5="Holdout",$Q$2,0) -> 0 | T5: 44469 | U5: 2021 | V5: 9 | W5: 0.0078607844 | X5: 0.034127055 | Y5: -0.026266271 | AA5: 2022 | AB5: 2022-01-01 to 2022-12-31 | AC5: 0.06169062 | AD5: 0.030184313 | AE5: 0.031506306 | AF5: 120 | AH5: 44791 | AI5: 0.12996983 | AJ5: 0.10253758 | AK5: 0.027432246 | AM5: 2021Q4 | AN5: Discovery | AO5: 35 | AP5: 90 | AQ5: 0.06636817 | AR5: =MAX(AQ5,0) -> 0.06636817 | AS5: =MIN(AQ5,0) -> 0 | AU5: 2021Q4 | AV5: 0.044528212 | AW5: -0.0037501702 | AX5: 0.048278382 | AY5: =MAX(AX5,0) -> 0.048278382 | AZ5: =MIN(AX5,0) -> 0 | BB5: 2 | BC5: 583 | BD5: 0.11426836 | BE5: 0.0017804305 | BF5: 0.75626648 | BG5: 0.018401911 | BI5: 0.12299976 | BK5: 1 | BL5: 0.95238095 | BM5: 1 | BO5: 0.00585 | BP5: 0.17155034 | BQ5: 0.058715761 | BR5: 1.0827253 | BS5: -0.23675278 | BT5: 0.087085033 | BU5: 0.0081505638 | BX5: Discovery 60d | BY5: 635 | BZ5: 709 | CA5: 0.017005464 | CB5: -0.017284883 | CC5: 0.034290347 | CD5: 0.00013057945 | CE5: 8 | CF5: 10 | CG5: 0.034967031 | CH5: 0 | CJ5: KT2 | CK5: Drop 2021 | CL5: spread +2.88%, p=7.9e-07 | CM5: TRUE | CP5: T0002 | CQ5: 1.0029859 | CR5: 0.98099873 | CS5: 0.99484241 | CT5: 0.98045593 | CU5: 0.96959819 | CV5: 0.95358295 | CW5: 0.95874038 | CX5: 0.95276878 | CY5: 0.9397392 | CZ5: 0.94652539 | DA5: 0.95276878 | DB5: 0.95195426 | DC5: 0.95358295 | DD5: 0.95412575 | DE5: 0.95303993 | DF5: 0.94516814 | DG5: 0.93919647 | DH5: 0.9549417 | DI5: 0.95853275 | DJ5: 0.96074268 | DK5: 0.9618475 | DL5: 0.98284148 | DM5: 0.99140477 | DN5: 0.98781358 | DO5: 0.97786925 | DP5: 0.9717919 | DQ5: 0.97648813 | DR5: 0.98477512 | DS5: 0.97317309 | DT5: 0.97234456 | DU5: 1.0162657 | DV5: 1.0775897 | DW5: 1.0491376 | DX5: 1.0599107 | DY5: 1.0588059 | DZ5: 1.0494138 | EA5: 1.0364308 | EB5: 1.0402983 | EC5: 1.0369832 | ED5: 1.0687501 | EE5: 1.0681977 | EF5: 1.1016222 | EG5: 1.1306267 | EH5: 1.1259308 | EI5: 1.0974784 | EJ5: 1.0737226 | EK5: 1.0720651 | EL5: 1.0742748 | EM5: 1.0643306 | EN5: 1.0519 | EO5: 1.0510713 | EP5: 1.0270388 | EQ5: 1.022343 | ER5: 1.0372595 | ES5: 1.0248289 | ET5: 1.0162657 | EU5: 1.022343 | EV5: 1.0449942 | EW5: 1.0306301 | EX5: 1.0187517 | EY5: 1.0063212
A6: years | B6: Years | C6: 4.9993155 | D6: 2.5078713 | E6: 2.5653662 | F6: 2.3819302 | G6: 2.6173854 | I6: 44421 | J6: 100.04603 | K6: 101.36021 | L6: 0 | M6: 0 | N6: 6 | O6: Discovery | P6: =IF(O6="Discovery",$Q$2,0) -> 225 | Q6: =IF(O6="Holdout",$Q$2,0) -> 0 | T6: 44500 | U6: 2021 | V6: 10 | W6: -0.024465098 | X6: 0.0022753469 | Y6: -0.026740445 | AA6: 2023 | AB6: 2023-01-01 to 2023-12-31 | AC6: 0.40709195 | AD6: 0.25764377 | AE6: 0.14944818 | AF6: 120 | AH6: 44792 | AI6: 0.11216826 | AJ6: 0.083279418 | AK6: 0.028888842 | AM6: 2022Q1 | AN6: Discovery | AO6: 49 | AP6: 105 | AQ6: 0.085200586 | AR6: =MAX(AQ6,0) -> 0.085200586 | AS6: =MIN(AQ6,0) -> 0 | AU6: 2022Q1 | AV6: 0.077618908 | AW6: -0.006781718 | AX6: 0.084400626 | AY6: =MAX(AX6,0) -> 0.084400626 | AZ6: =MIN(AX6,0) -> 0 | BB6: 3 | BC6: 580 | BD6: 0.082590705 | BE6: -0.030097018 | BF6: 0.56887415 | BG6: -0.10473597 | BI6: -0.052447654 | BK6: 2 | BL6: 0.87477954 | BM6: 0.98941799 | BO6: 0.01 | BP6: 0.15342996 | BQ6: 0.040595379 | BR6: 0.98408992 | BS6: -0.24234357 | BT6: 0.070100271 | BU6: -0.0088341983 | BX6: Holdout 60d | BY6: 792 | BZ6: 794 | CA6: 0.011857805 | CB6: -0.01476439 | CC6: 0.026622195 | CD6: 0.00030198287 | CE6: 9 | CF6: 10 | CG6: 0.021958328 | CH6: 1 | CJ6: KT3 | CK6: Mid + Large caps only | CL6: spread +2.19%, p=0.0017 | CM6: TRUE | CP6: T0003 | CQ6: 1.010631 | CR6: 1.009945 | CS6: 0.998171 | CT6: 0.97610882 | CU6: 0.92283941 | CV6: 0.93015537 | CW6: 0.96216271 | CX6: 0.98468219 | CY6: 0.96959306 | CZ6: 1.0011431 | DA6: 1.0243485 | DB6: 1.0706447 | DC6: 1.0473251 | DD6: 1.044696 | DE6: 1.0546411 | DF6: 1.0728166 | DG6: 1.0569273 | DH6: 1.0432099 | DI6: 1.0597851 | DJ6: 1.0936214 | DK6: 1.0927068 | DL6: 1.11294 | DM6: 1.1049383 | DN6: 1.0815043 | DO6: 1.0160037 | DP6: 1.0310927 | DQ6: 1.0585276 | DR6: 1.1048239 | DS6: 1.0945359 | DT6: 1.1005943 | DU6: 1.093164 | DV6: 1.1297439 | DW6: 1.1155693 | DX6: 1.1073388 | DY6: 1.1561499 | DZ6: 1.132373 | EA6: 1.0880201 | EB6: 1.0916781 | EC6: 1.0828761 | ED6: 1.1145404 | EE6: 1.140032 | EF6: 1.1615226 | EG6: 1.1799267 | EH6: 1.2409695 | EI6: 1.2202789 | EJ6: 1.1727252 | EK6: 1.1288294 | EL6: 1.0755601 | EM6: 1.0819616 | EN6: 1.1112254 | EO6: 1.0970508 | EP6: 1.0717877 | EQ6: 1.0512117 | ER6: 1.093164 | ES6: 1.0708733 | ET6: 1.093507 | EU6: 1.0804756 | EV6: 1.0740739 | EW6: 1.0621857 | EX6: 1.0282349 | EY6: 1.0378373
A7: total_return | B7: Total return | C7: 1.2067733 | D7: 0.68598808 | E7: 0.23887988 | F7: 0.60093426 | G7: 0.3784284 | I7: 44424 | J7: 99.966465 | K7: 101.39984 | L7: -0.0007953125 | M7: 0 | N7: 12 | O7: Discovery | P7: =IF(O7="Discovery",$Q$2,0) -> 225 | Q7: =IF(O7="Holdout",$Q$2,0) -> 0 | T7: 44530 | U7: 2021 | V7: 11 | W7: 0.033369901 | X7: -0.029068265 | Y7: 0.062438165 | AA7: 2024 | AB7: 2024-01-01 to 2024-12-31 | AC7: 0.28295618 | AD7: 0.1516407 | AE7: 0.13131547 | AF7: 110 | AH7: 44795 | AI7: 0.10816037 | AJ7: 0.066161839 | AK7: 0.041998531 | AM7: 2022Q2 | AN7: Discovery | AO7: 64 | AP7: 90 | AQ7: -0.018821707 | AR7: =MAX(AQ7,0) -> 0 | AS7: =MIN(AQ7,0) -> -0.018821707 | AU7: 2022Q2 | AV7: -0.12776067 | AW7: -0.10117493 | AX7: -0.026585735 | AY7: =MAX(AX7,0) -> 0 | AZ7: =MIN(AX7,0) -> -0.026585735 | BB7: 4 | BC7: 575 | BD7: 0.063843611 | BE7: -0.046052372 | BF7: 0.46945271 | BG7: -0.060242666 | BI7: 0.094937777 | BK7: 3 | BL7: 0.80599647 | BM7: 0.97707231 | BX7: Horizon 5d | BY7: 1535 | BZ7: 1573 | CA7: 0.0046162536 | CB7: -0.0015235551 | CC7: 0.0061398087 | CD7: 0.0015687377 | CE7: 14 | CF7: 21 | CG7: 0.0052671048 | CH7: 1 | CJ7: KT4 | CK7: Exclude Layer-4-seen events | CL7: spread +3.05%, folds+ 85.0% | CM7: TRUE | CP7: T0004 | CQ7: 0.97950576 | CR7: 0.98523215 | CS7: 1.0635926 | CT7: 1.14346 | CU7: 1.1338157 | CV7: 1.1594335 | CW7: 1.1283906 | CX7: 1.1844486 | CY7: 1.170886 | CZ7: 1.1769138 | DA7: 1.296263 | DB7: 1.2911394 | DC7: 1.3646776 | DD7: 1.3499097 | DE7: 1.3761304 | DF7: 1.3631707 | DG7: 1.3173599 | DH7: 1.3245932 | DI7: 1.3698013 | DJ7: 1.3824596 | DK7: 1.4095844 | DL7: 1.3915012 | DM7: 1.3698013 | DN7: 1.3040989 | DO7: 1.2905367 | DP7: 1.3125377 | DQ7: 1.2610008 | DR7: 1.2655215 | DS7: 1.2866186 | DT7: 1.2763713 | DU7: 1.2839061 | DV7: 1.2691382 | DW7: 1.2510549 | DX7: 1.2769744 | DY7: 1.2685355 | DZ7: 1.2799881 | EA7: 1.2534661 | EB7: 1.2757685 | EC7: 1.2827006 | ED7: 1.2820976 | EE7: 1.2739605 | EF7: 1.2622062 | EG7: 1.2534661 | EH7: 1.2275468 | EI7: 1.1868596 | EJ7: 1.1377337 | EK7: 1.1766126 | EL7: 1.1657626 | EM7: 1.1160339 | EN7: 1.1292949 | EO7: 1.1371308 | EP7: 1.1069922 | EQ7: 1.1320075 | ER7: 1.1094033 | ES7: 1.1341169 | ET7: 1.1208561 | EU7: 1.1678724 | EV7: 1.1573238 | EW7: 1.1723932 | EX7: 1.2377941 | EY7: 1.2263412
A8: cagr | B8: CAGR | C8: 0.17155034 | D8: 0.23156402 | E8: 0.087085033 | F8: 0.21843294 | G8: 0.13045486 | I8: 44425 | J8: 100.34855 | K8: 101.70467 | L8: 0 | M8: 0 | N8: 19 | O8: Discovery | P8: =IF(O8="Discovery",$Q$2,0) -> 225 | Q8: =IF(O8="Holdout",$Q$2,0) -> 0 | T8: 44561 | U8: 2021 | V8: 12 | W8: 0.036147431 | X8: 0.023746702 | Y8: 0.012400729 | AA8: 2025 | AB8: 2025-01-01 to 2025-12-31 | AC8: -0.030173256 | AD8: 0.066865844 | AE8: -0.0970391 | AF8: 120 | AH8: 44796 | AI8: 0.11776907 | AJ8: 0.069254806 | AK8: 0.048514265 | AM8: 2022Q3 | AN8: Discovery | AO8: 83 | AP8: 53 | AQ8: 0.052294923 | AR8: =MAX(AQ8,0) -> 0.052294923 | AS8: =MIN(AQ8,0) -> 0 | AU8: 2022Q3 | AV8: 0.15982162 | AW8: 0.10769708 | AX8: 0.05212454 | AY8: =MAX(AX8,0) -> 0.05212454 | AZ8: =MIN(AX8,0) -> 0 | BB8: 5 | BC8: 579 | BD8: 0.11307035 | BE8: 0.0012413369 | BF8: 0.73726799 | BG8: -0.047206202 | BI8: 0.054640006 | BK8: 5 | BL8: 0.71781305 | BM8: 0.95238095 | BX8: Horizon 10d | BY8: 1535 | BZ8: 1573 | CA8: 0.007178186 | CB8: -0.0029966206 | CC8: 0.010174807 | CD8: 1.9071213e-05 | CE8: 18 | CF8: 21 | CG8: 0.0097822654 | CH8: 0 | CJ8: KT5 | CK8: 1.000% round-trip cost (portfolio) | CL8: full excess +4.06%, HOLDOUT excess -0.88% | CM8: FALSE | CP8: T0005 | CQ8: 1.0574785 | CR8: 1.0864527 | CS8: 1.0859829 | CT8: 1.0935006 | CU8: 1.0415036 | CV8: 0.96131561 | CW8: 1.0391544 | CX8: 1.0100236 | CY8: 1.0210207 | CZ8: 1.0123801 | DA8: 1.0128515 | DB8: 1.0169362 | DC8: 1.010966 | DD8: 1.0134798 | DE8: 1.0078241 | DF8: 1.0064101 | DG8: 0.99588428 | DH8: 0.98237305 | DI8: 0.97404666 | DJ8: 0.96980479 | DK8: 0.99871213 | DL8: 1.0169362 | DM8: 1.0243199 | DN8: 1.0255768 | DO8: 1.0103375 | DP8: 1.0068814 | DQ8: 0.9875573 | DR8: 0.9896 | DS8: 0.98362982 | DT8: 1.0101806 | DU8: 1.0405016 | DV8: 1.042387 | DW8: 1.0104948 | DX8: 1.0178788 | DY8: 1.0161506 | DZ8: 1.0147366 | EA8: 1.0276193 | EB8: 1.0719227 | EC8: 1.0989446 | ED8: 1.1540881 | EE8: 1.1286373 | EF8: 1.1850377 | EG8: 1.1947781 | EH8: 1.2315405 | EI8: 1.1694845 | EJ8: 1.140263 | EK8: 1.1463901 | EL8: 1.0821343 | EM8: 1.0628107 | EN8: 1.1470184 | EO8: 1.1273803 | EP8: 1.1133981 | EQ8: 1.08182 | ER8: 1.1215676 | ES8: 1.1512603 | ET8: 1.1735691 | EU8: 1.1619434 | EV8: 1.1837809 | EW8: 1.1867659 | EX8: 1.1427766 | EY8: 1.1394775
A9: bench_total_return | B9: NIFTY 500 (PR) total return | C9: 0.70655891 | D9: 0.42563533 | E9: 0.21519069 | F9: 0.40014269 | G9: 0.21884642 | I9: 44426 | J9: 100.41514 | K9: 101.5782 | L9: 0 | M9: -0.0012435255 | N9: 19 | O9: Discovery | P9: =IF(O9="Discovery",$Q$2,0) -> 225 | Q9: =IF(O9="Holdout",$Q$2,0) -> 0 | T9: 44592 | U9: 2022 | V9: 1 | W9: 0.0014163193 | X9: -0.0049845961 | Y9: 0.0064009154 | AA9: 2026 | AB9: 2026-01-01 to 2026-08-11 | AC9: 0.10784304 | AD9: -0.0079760217 | AE9: 0.11581907 | AF9: 60 | AH9: 44797 | AI9: 0.128086 | AJ9: 0.074126231 | AK9: 0.053959771 | AM9: 2022Q4 | AN9: Discovery | AO9: 63 | AP9: 91 | AQ9: -0.027667829 | AR9: =MAX(AQ9,0) -> 0 | AS9: =MIN(AQ9,0) -> -0.027667829 | AU9: 2022Q4 | AV9: -0.026118961 | AW9: 0.041775263 | AX9: -0.067894224 | AY9: =MAX(AX9,0) -> 0 | AZ9: =MIN(AX9,0) -> -0.067894224 | BB9: 6 | BC9: 579 | BD9: 0.088425602 | BE9: -0.024062332 | BF9: 0.64452838 | BG9: -0.058507888 | BI9: 0.13362749 | BK9: 7.5 | BL9: 0.62433862 | BM9: 0.92063492 | BX9: Horizon 20d | BY9: 1535 | BZ9: 1573 | CA9: 0.010817846 | CB9: -0.0057550836 | CC9: 0.016572929 | CD9: 2.7144632e-07 | CE9: 18 | CF9: 21 | CG9: 0.015702392 | CH9: 0 | CJ9: KT6 | CK9: 8Q / expanding threshold windows | CL9: 8Q +2.91%, expanding +2.83% | CM9: TRUE | CP9: T0006 | CQ9: 0.97592784 | CR9: 0.97693084 | CS9: 0.95185564 | CT9: 0.95285864 | CU9: 0.941324 | CV9: 0.91925786 | CW9: 0.948345 | CX9: 0.94784364 | CY9: 0.95887657 | CZ9: 0.98194595 | DA9: 1.0005014 | DB9: 1.0371114 | DC9: 1.0320964 | DD9: 1.1118355 | DE9: 1.0922768 | DF9: 1.0872619 | DG9: 1.0661986 | DH9: 1.0857667 | DI9: 1.0720162 | DJ9: 1.0513903 | DK9: 1.0376397 | DL9: 1.0587943 | DM9: 1.060381 | DN9: 1.0455726 | DO9: 1.0212449 | DP9: 1.012783 | DQ9: 1.0186003 | DR9: 1.024418 | DS9: 1.0397553 | DT9: 1.0307644 | DU9: 1.0429285 | DV9: 1.1799051 | DW9: 1.225388 | DX9: 1.2169261 | DY9: 1.2132238 | DZ9: 1.221686 | EA9: 1.2550045 | EB9: 1.2354365 | EC9: 1.3264019 | ED9: 1.4152517 | EE9: 1.4178962 | EF9: 1.4506856 | EG9: 1.4110208 | EH9: 1.4210694 | EI9: 1.377173 | EJ9: 1.3427967 | EK9: 1.4141939 | EL9: 1.3660667 | EM9: 1.3496719 | EN9: 1.3983278 | EO9: 1.3623648 | EP9: 1.3301038 | EQ9: 1.3353926 | ER9: 1.3486142 | ES9: 1.3248152 | ET9: 1.3332772 | EU9: 1.3517876 | EV9: 1.3406813 | EW9: 1.3322192 | EX9: 1.3110645 | EY9: 1.2914965
A10: bench_cagr | B10: NIFTY 500 (PR) CAGR | C10: 0.11283458 | D10: 0.1518874 | E10: 0.07893447 | F10: 0.15177371 | G10: 0.078543654 | I10: 44428 | J10: 98.778525 | K10: 100.48571 | L10: -0.016298524 | M10: -0.011985319 | N10: 19 | O10: Discovery | P10: =IF(O10="Discovery",$Q$2,0) -> 225 | Q10: =IF(O10="Holdout",$Q$2,0) -> 0 | T10: 44620 | U10: 2022 | V10: 2 | W10: -0.029532354 | X10: -0.041115307 | Y10: 0.011582953 | AH10: 44798 | AI10: 0.14505362 | AJ10: 0.082953539 | AK10: 0.06210008 | AM10: 2023Q1 | AN10: Discovery | AO10: 74 | AP10: 65 | AQ10: 0.045422821 | AR10: =MAX(AQ10,0) -> 0.045422821 | AS10: =MIN(AQ10,0) -> 0 | AU10: 2023Q1 | AV10: -0.040273805 | AW10: -0.057674196 | AX10: 0.017400391 | AY10: =MAX(AX10,0) -> 0.017400391 | AZ10: =MIN(AX10,0) -> 0 | BB10: 7 | BC10: 582 | BD10: 0.14433214 | BE10: 0.032982282 | BF10: 0.92719936 | BG10: -0.056792986 | BI10: 0.28564648 | BK10: 10 | BL10: 0.58024691 | BM10: 0.87477954 | BX10: Horizon 30d | BY10: 1508 | BZ10: 1543 | CA10: 0.0086077237 | CB10: -0.0060219277 | CC10: 0.014629651 | CD10: 0.00013842795 | CE10: 17 | CF10: 21 | CG10: 0.01249861 | CH10: 0 | CJ10: KT7 | CK10: Horizon jitter 40d / 90d | CL10: 40d +1.82%, 90d +3.92% | CM10: TRUE | CP10: T0007 | CQ10: 1.0010173 | CR10: 1.0373345 | CS10: 1.0478129 | CT10: 1.0092065 | CU10: 0.99237018 | CV10: 1.0134791 | CW10: 1.0068159 | CX10: 0.99806718 | CY10: 0.99694803 | CZ10: 1.0166837 | DA10: 1.0164293 | DB10: 1.023347 | DC10: 1.058291 | DD10: 1.0436926 | DE10: 1.065412 | DF10: 1.0574262 | DG10: 1.0595625 | DH10: 1.0620548 | DI10: 1.0622076 | DJ10: 1.0566124 | DK10: 1.0593082 | DL10: 1.0498982 | DM10: 1.0251271 | DN10: 1.0012207 | DO10: 1.0077822 | DP10: 1.0398778 | DQ10: 1.0455748 | DR10: 1.012004 | DS10: 1.0156664 | DT10: 1.01882 | DU10: 1.0141911 | DV10: 1.0091047 | DW10: 0.93397736 | DX10: 0.90874864 | DY10: 0.9154118 | DZ10: 0.8978637 | EA10: 0.91241091 | EB10: 0.89888089 | EC10: 0.92512715 | ED10: 0.91495417 | EE10: 0.91358076 | EF10: 0.91876903 | EG10: 0.92594099 | EH10: 0.92400808 | EI10: 0.89842314 | EJ10: 0.8963377 | EK10: 0.90055948 | EL10: 0.88357075 | EM10: 0.89048824 | EN10: 0.91007107 | EO10: 0.91037638 | EP10: 0.91119022 | EQ10: 0.92853509 | ER10: 0.92772119 | ES10: 0.91103763 | ET10: 0.91510676 | EU10: 0.92761951 | EV10: 0.93789424 | EW10: 0.94053925 | EX10: 0.93306198 | EY10: 0.93880975
A11: excess_cagr | B11: Excess CAGR vs NIFTY 500 (PR) | C11: 0.058715761 | D11: 0.079676621 | E11: 0.0081505638 | F11: 0.066659229 | G11: 0.051911208 | I11: 44431 | J11: 97.763407 | K11: 100.38915 | L11: -0.026407739 | M11: -0.012934791 | N11: 19 | O11: Discovery | P11: =IF(O11="Discovery",$Q$2,0) -> 225 | Q11: =IF(O11="Holdout",$Q$2,0) -> 0 | T11: 44651 | U11: 2022 | V11: 3 | W11: 0.10884152 | X11: 0.040994692 | Y11: 0.067846823 | AH11: 44799 | AI11: 0.16468663 | AJ11: 0.087361949 | AK11: 0.077324679 | AM11: 2023Q2 | AN11: Discovery | AO11: 82 | AP11: 93 | AQ11: 0.035646893 | AR11: =MAX(AQ11,0) -> 0.035646893 | AS11: =MIN(AQ11,0) -> 0 | AU11: 2023Q2 | AV11: 0.13593677 | AW11: 0.12860072 | AX11: 0.0073360454 | AY11: =MAX(AX11,0) -> 0.0073360454 | AZ11: =MIN(AX11,0) -> 0 | BB11: 8 | BC11: 579 | BD11: 0.11054909 | BE11: -0.0021386328 | BF11: 0.75054225 | BG11: 0.0027255337 | BI11: 0.34070913 | BK11: 15 | BL11: 0.4973545 | BM11: 0.80599647 | BX11: Horizon 40d | BY11: 1450 | BZ11: 1510 | CA11: 0.010678269 | CB11: -0.0075632575 | CC11: 0.018241526 | CD11: 6.8833496e-05 | CE11: 16 | CF11: 21 | CG11: 0.01260746 | CH11: 0 | CP11: T0008 | CQ11: 1.0238545 | CR11: 1.0132749 | CS11: 1.0110851 | CT11: 0.92695412 | CU11: 0.91553244 | CV11: 0.9465297 | CW11: 0.93679256 | CX11: 0.92658366 | CY11: 0.9327156 | CZ11: 0.97075486 | DA11: 0.9772575 | DB11: 0.95094349 | DC11: 0.96030994 | DD11: 0.97281003 | DE11: 0.96832882 | DF11: 0.96273593 | DG11: 0.96351083 | DH11: 0.97506736 | DI11: 0.98615232 | DJ11: 0.97863894 | DK11: 0.98052563 | DL11: 0.9681604 | DM11: 0.93389488 | DN11: 0.84440701 | DO11: 0.87075476 | DP11: 0.87991923 | DQ11: 0.88861183 | DR11: 0.85721031 | DS11: 0.85613214 | DT11: 0.86317395 | DU11: 0.87301215 | DV11: 0.86853106 | DW11: 0.87456207 | DX11: 0.8922844 | DY11: 0.88736525 | DZ11: 0.8624663 | EA11: 0.86873322 | EB11: 0.87678583 | EC11: 0.88490587 | ED11: 0.89562008 | EE11: 0.91260102 | EF11: 0.92658366 | EG11: 0.95084238 | EH11: 0.92109159 | EI11: 0.90518875 | EJ11: 0.8859165 | EK11: 0.8734839 | EL11: 0.87149604 | EM11: 0.9054246 | EN11: 0.89363216 | EO11: 0.87574135 | EP11: 0.88675876 | EQ11: 0.91974401 | ER11: 0.88520903 | ES11: 0.89356473 | ET11: 0.89346362 | EU11: 0.90515495 | EV11: 0.90023597 | EW11: 0.87503369 | EX11: 0.87574135 | EY11: 0.86741926
A12: mean_trade_xs_univ_60d | B12: Mean trade excess vs same-month event universe (60d) | C12: 0.010602259 | D12: 0.0033915041 | E12: 0.010788755 | I12: 44432 | J12: 99.002995 | K12: 101.34544 | L12: -0.01406311 | M12: -0.0035321793 | N12: 19 | O12: Discovery | P12: =IF(O12="Discovery",$Q$2,0) -> 225 | Q12: =IF(O12="Holdout",$Q$2,0) -> 0 | T12: 44681 | U12: 2022 | V12: 4 | W12: -0.021167155 | X12: -0.0074624862 | Y12: -0.013704669 | AH12: 44802 | AI12: 0.14566638 | AJ12: 0.064672106 | AK12: 0.080994272 | AM12: 2023Q3 | AN12: Discovery | AO12: 73 | AP12: 55 | AQ12: 0.013593406 | AR12: =MAX(AQ12,0) -> 0.013593406 | AS12: =MIN(AQ12,0) -> 0 | AU12: 2023Q3 | AV12: 0.10444939 | AW12: 0.052501522 | AX12: 0.051947872 | AY12: =MAX(AX12,0) -> 0.051947872 | AZ12: =MIN(AX12,0) -> 0 | BB12: 9 | BC12: 586 | BD12: 0.096034356 | BE12: -0.016453578 | BF12: 0.65155748 | BG12: -0.045062482 | BI12: -0.0059821122 | BK12: 20 | BL12: 0.43738977 | BM12: 0.75837743 | BX12: Horizon 90d | BY12: 1377 | BZ12: 1438 | CA12: 0.018996268 | CB12: -0.020252133 | CC12: 0.0392484 | CD12: 2.0935775e-07 | CE12: 17 | CF12: 20 | CG12: 0.039736723 | CH12: 1 | CP12: T0009 | CQ12: 0.99466279 | CR12: 0.98805791 | CS12: 1.0015345 | CT12: 0.99049302 | CU12: 0.96113816 | CV12: 0.97414777 | CW12: 0.96584167 | CX12: 0.96007076 | CY12: 0.97291341 | CZ12: 0.98148646 | DA12: 1.0010008 | DB12: 0.99139371 | DC12: 1.0002335 | DD12: 1.0077057 | DE12: 1.0214157 | DF12: 1.0370606 | DG12: 1.0519048 | DH12: 1.0660484 | DI12: 1.0716859 | DJ12: 1.0753219 | DK12: 1.0719862 | DL12: 1.0530722 | DM12: 1.0466342 | DN12: 1.0244848 | DO12: 1.0388618 | DP12: 1.050537 | DQ12: 1.0720194 | DR12: 1.0872974 | DS12: 1.1000068 | DT12: 1.0999735 | DU12: 1.1140837 | DV12: 1.1137835 | DW12: 1.1189205 | DX12: 1.094903 | DY12: 1.0854625 | DZ12: 1.0667823 | EA12: 1.0621123 | EB12: 1.0666488 | EC12: 1.1019747 | ED12: 1.092568 | EE12: 1.1188537 | EF12: 1.1691909 | EG12: 1.1701581 | EH12: 1.1461071 | EI12: 1.1291613 | EJ12: 1.1647208 | EK12: 1.1433719 | EL12: 1.1412702 | EM12: 1.1604511 | EN12: 1.1531123 | EO12: 1.1357662 | EP12: 1.1482421 | EQ12: 1.1935419 | ER12: 1.1635533 | ES12: 1.1912403 | ET12: 1.1952765 | EU12: 1.2335379 | EV12: 1.2434785 | EW12: 1.2505504 | EX12: 1.230469 | EY12: 1.2398759
A13: mean_trade_xs_nifty | B13: Mean trade excess vs NIFTY 500 (per trade) | C13: 0.022942353 | D13: 0.029213073 | E13: 0.010525723 | I13: 44433 | J13: 99.247016 | K13: 101.56415 | L13: -0.011632984 | M13: -0.001381695 | N13: 19 | O13: Discovery | P13: =IF(O13="Discovery",$Q$2,0) -> 225 | Q13: =IF(O13="Holdout",$Q$2,0) -> 0 | T13: 44712 | U13: 2022 | V13: 5 | W13: -0.046541425 | X13: -0.044898484 | Y13: -0.0016429408 | AH13: 44803 | AI13: 0.16043128 | AJ13: 0.08737654 | AK13: 0.073054739 | AM13: 2023Q4 | AN13: Discovery | AO13: 93 | AP13: 53 | AQ13: 0.062666017 | AR13: =MAX(AQ13,0) -> 0.062666017 | AS13: =MIN(AQ13,0) -> 0 | AU13: 2023Q4 | AV13: 0.16862495 | AW13: 0.12355285 | AX13: 0.045072099 | AY13: =MAX(AX13,0) -> 0.045072099 | AZ13: =MIN(AX13,0) -> 0 | BB13: 10 | BC13: 584 | BD13: 0.087645365 | BE13: -0.02277412 | BF13: 0.58933332 | BG13: -0.022911856 | BI13: -0.13843074 | BK13: 30 | BL13: 0.36507937 | BM13: 0.67724868 | BX13: Horizon 126d | BY13: 1313 | BZ13: 1412 | CA13: 0.01372269 | CB13: -0.024874301 | CC13: 0.038596991 | CD13: 4.242228e-05 | CE13: 16 | CF13: 19 | CG13: 0.038001362 | CH13: 1 | CP13: T0010 | CQ13: 1.0357081 | CR13: 1.0546943 | CS13: 1.0520816 | CT13: 1.0013935 | CU13: 1.003658 | CV13: 1.0269987 | CW13: 1.0409335 | CX13: 1.0691515 | CY13: 1.1093886 | CZ13: 1.1189687 | DA13: 1.1579864 | DB13: 1.1581605 | DC13: 1.1499738 | DD13: 1.1353422 | DE13: 1.1153109 | DF13: 1.1228009 | DG13: 1.1046855 | DH13: 1.0905766 | DI13: 1.0592231 | DJ13: 1.0881379 | DK13: 1.0902281 | DL13: 1.0768158 | DM13: 1.0505138 | DN13: 1.0179411 | DO13: 1.0109676 | DP13: 1.0062607 | DQ13: 1.0245658 | DR13: 1.018464 | DS13: 1.0151518 | DT13: 1.0036457 | DU13: 1.0039943 | DV13: 0.99981036 | DW13: 1.0107934 | DX13: 1.011665 | DY13: 1.005912 | DZ13: 1.0031226 | EA13: 0.99562619 | EB13: 1.0067836 | EC13: 1.0402559 | ED13: 1.0385126 | EE13: 1.0894184 | EF13: 1.0684983 | EG13: 1.0726823 | EH13: 1.0526336 | EI13: 1.0549 | EJ13: 1.0660574 | EK13: 1.0196846 | EL13: 0.98220248 | EM13: 0.98499171 | EN13: 0.98621218 | EO13: 0.9881299 | EP13: 0.9755776 | EQ13: 0.99248811 | ER13: 1.0113165 | ES13: 1.0161977 | ET13: 1.0284013 | EU13: 1.0346772 | EV13: 1.0510647 | EW13: 1.0362463 | EX13: 1.0165463 | EY13: 0.99283685
A14: vol | B14: Annualised volatility | C14: 0.16071962 | D14: 0.14845989 | E14: 0.16698793 | F14: 0.14962272 | G14: 0.17029732 | I14: 44434 | J14: 99.130164 | K14: 101.66036 | L14: -0.012796675 | M14: -0.00043576535 | N14: 19 | O14: Discovery | P14: =IF(O14="Discovery",$Q$2,0) -> 225 | Q14: =IF(O14="Holdout",$Q$2,0) -> 0 | T14: 44742 | U14: 2022 | V14: 6 | W14: -0.065401015 | X14: -0.05184637 | Y14: -0.013554645 | AH14: 44805 | AI14: 0.16445691 | AJ14: 0.078277019 | AK14: 0.086179888 | AM14: 2024Q1 | AN14: Holdout | AO14: 67 | AP14: 79 | AQ14: 0.068514255 | AR14: =MAX(AQ14,0) -> 0.068514255 | AS14: =MIN(AQ14,0) -> 0 | AU14: 2024Q1 | AV14: 0.07377196 | AW14: 0.04251344 | AX14: 0.03125852 | AY14: =MAX(AX14,0) -> 0.03125852 | AZ14: =MIN(AX14,0) -> 0 | BB14: 11 | BC14: 583 | BD14: 0.14227518 | BE14: 0.029587454 | BF14: 0.89449989 | BG14: -0.014172441 | BI14: 0.28910216 | BK14: 50 | BL14: 0.2345679 | BM14: 0.58024691 | BX14: Non-Financials 60d | BY14: 1114 | BZ14: 1403 | CA14: 0.014836427 | CB14: -0.019594424 | CC14: 0.034430851 | CD14: 3.6533215e-08 | CE14: 17 | CF14: 20 | CG14: 0.035126845 | CH14: 0 | CP14: T0011 | CQ14: 0.98231165 | CR14: 1.0026181 | CS14: 1.0028736 | CT14: 0.96558108 | CU14: 0.97496816 | CV14: 0.98160918 | CW14: 1.0017241 | CX14: 0.98901673 | CY14: 0.98984673 | CZ14: 1.0220945 | DA14: 1.0170498 | DB14: 1.0102811 | DC14: 1.0059387 | DD14: 1.0157088 | DE14: 1.1019795 | DF14: 1.1181991 | DG14: 1.1000639 | DH14: 1.1452108 | DI14: 1.1291188 | DJ14: 1.1448276 | DK14: 1.166539 | DL14: 1.1972543 | DM14: 1.1537036 | DN14: 1.1809708 | DO14: 1.1756066 | DP14: 1.1785439 | DQ14: 1.1756066 | DR14: 1.1590039 | DS14: 1.1598979 | DT14: 1.1690933 | DU14: 1.1537676 | DV14: 1.1683908 | DW14: 1.1864622 | DX14: 1.1782249 | DY14: 1.1681355 | DZ14: 1.1922095 | EA14: 1.2239464 | EB14: 1.2074713 | EC14: 1.2137932 | ED14: 1.2000638 | EE14: 1.2116858 | EF14: 1.2001917 | EG14: 1.1911877 | EH14: 1.1547893 | EI14: 1.1257345 | EJ14: 1.0632185 | EK14: 1.0601532 | EL14: 1.0560666 | EM14: 1.0828225 | EN14: 1.0828225 | EO14: 1.0673054 | EP14: 1.0670499 | EQ14: 1.0763091 | ER14: 1.1177522 | ES14: 1.0660282 | ET14: 1.0856322 | EU14: 1.0957853 | EV14: 1.0955302 | EW14: 1.087484 | EX14: 1.0538314 | EY14: 1.0522988
A15: bench_vol | B15: NIFTY 500 volatility | C15: 0.14477536 | D15: 0.14061415 | E15: 0.14890391 | F15: 0.14098619 | G15: 0.14822808 | I15: 44435 | J15: 99.904068 | K15: 102.27686 | L15: -0.0050896326 | M15: 0 | N15: 19 | O15: Discovery | P15: =IF(O15="Discovery",$Q$2,0) -> 225 | Q15: =IF(O15="Holdout",$Q$2,0) -> 0 | T15: 44773 | U15: 2022 | V15: 7 | W15: 0.071264272 | X15: 0.095469298 | Y15: -0.024205026 | AH15: 44806 | AI15: 0.16772563 | AJ15: 0.071100934 | AK15: 0.096624694 | AM15: 2024Q2 | AN15: Holdout | AO15: 79 | AP15: 72 | AQ15: 0.038975767 | AR15: =MAX(AQ15,0) -> 0.038975767 | AS15: =MIN(AQ15,0) -> 0 | AU15: 2024Q2 | AV15: 0.18705065 | AW15: 0.113776 | AX15: 0.073274643 | AY15: =MAX(AX15,0) -> 0.073274643 | AZ15: =MIN(AX15,0) -> 0 | BB15: 12 | BC15: 583 | BD15: 0.10178958 | BE15: -0.010698353 | BF15: 0.69312381 | BG15: -0.019953215 | BI15: -0.16691971 | BK15: 75 | BL15: 0.14991182 | BM15: 0.4973545 | BX15: Financials 60d | BY15: 313 | BZ15: 100 | CA15: 0.011699911 | CB15: 0.035130698 | CC15: -0.023430787 | CD15: 0.19359791 | CE15: 9 | CF15: 17 | CG15: -0.024415901 | CH15: 3 | CP15: T0012 | CQ15: 0.96590107 | CR15: 0.92799779 | CS15: 0.92743427 | CT15: 0.89728068 | CU15: 0.84740041 | CV15: 0.84486413 | CW15: 0.84683683 | CX15: 0.84683683 | CY15: 0.86036355 | CZ15: 0.84401869 | DA15: 0.8693816 | DB15: 0.84458222 | DC15: 0.82851912 | DD15: 0.81301971 | DE15: 0.79554755 | DF15: 0.7713119 | DG15: 0.79892926 | DH15: 0.81978314 | DI15: 0.81950118 | DJ15: 0.81245598 | DK15: 0.8056926 | DL15: 0.81809226 | DM15: 0.80822892 | DN15: 0.78117533 | DO15: 0.79244759 | DP15: 0.80963794 | DQ15: 0.81189245 | DR15: 0.81358329 | DS15: 0.80287451 | DT15: 0.81668314 | DU15: 0.81330152 | DV15: 0.78568411 | DW15: 0.81499241 | DX15: 0.82513741 | DY15: 0.83838251 | DZ15: 0.81724677 | EA15: 0.81640138 | EB15: 0.82316486 | EC15: 0.81921947 | ED15: 0.81809226 | EE15: 0.82851912 | EF15: 0.86374542 | EG15: 0.8693816 | EH15: 0.82795555 | EI15: 0.83838251 | EJ15: 0.8107652 | EK15: 0.80625633 | EL15: 0.81611961 | EM15: 0.84232776 | EN15: 0.81950118 | EO15: 0.80033828 | EP15: 0.80991976 | EQ15: 0.80541083 | ER15: 0.8056926 | ES15: 0.80653819 | ET15: 0.83133732 | EU15: 0.81752863 | EV15: 0.81611961 | EW15: 0.87783571 | EX15: 0.86515449 | EY15: 0.84373693
A16: sharpe_rf0 | B16: Sharpe (rf = 0%) | C16: 1.0827253 | D16: 1.5005549 | E16: 0.59298964 | F16: 1.4166589 | G16: 0.81859279 | I16: 44438 | J16: 100.79672 | K16: 103.75706 | L16: 0 | M16: 0 | N16: 19 | O16: Discovery | P16: =IF(O16="Discovery",$Q$2,0) -> 225 | Q16: =IF(O16="Holdout",$Q$2,0) -> 0 | T16: 44804 | U16: 2022 | V16: 8 | W16: 0.067299623 | X16: 0.044962208 | Y16: 0.022337415 | AH16: 44809 | AI16: 0.16071017 | AJ16: 0.062266025 | AK16: 0.09844415 | AM16: 2024Q3 | AN16: Holdout | AO16: 71 | AP16: 71 | AQ16: -0.0014628253 | AR16: =MAX(AQ16,0) -> 0 | AS16: =MIN(AQ16,0) -> -0.0014628253 | AU16: 2024Q3 | AV16: 0.052147607 | AW16: 0.074712873 | AX16: -0.022565266 | AY16: =MAX(AX16,0) -> 0 | AZ16: =MIN(AX16,0) -> -0.022565266 | BB16: 13 | BC16: 582 | BD16: 0.087891347 | BE16: -0.024796376 | BF16: 0.61219672 | BG16: -0.031887912 | BI16: -0.067040245 | BK16: 100 | BL16: 0.095238095 | BM16: 0.43738977 | BX16: Size Small 60d | BY16: 358 | BZ16: 595 | CA16: 0.013769867 | CB16: -0.028702101 | CC16: 0.042471968 | CD16: 2.7411364e-05 | CE16: 19 | CF16: 20 | CG16: 0.040572279 | CH16: 0 | CP16: T0013 | CQ16: 1.0375226 | CR16: 0.99638328 | CS16: 0.92698915 | CT16: 0.90009047 | CU16: 0.98598551 | CV16: 1.0047469 | CW16: 1.0212477 | CX16: 1.0020344 | CY16: 1.0158228 | CZ16: 0.98282096 | DA16: 0.98146471 | DB16: 1.0418173 | DC16: 1.0250905 | DD16: 1.0519891 | DE16: 1.0465641 | DF16: 1.1028481 | DG16: 1.0793399 | DH16: 1.0689421 | DI16: 1.0440778 | DJ16: 1.0845389 | DK16: 1.1109855 | DL16: 1.0827306 | DM16: 1.1044304 | DN16: 1.153707 | DO16: 1.1882912 | DP16: 1.164557 | DQ16: 1.1489602 | DR16: 1.1717903 | DS16: 1.1769892 | DT16: 1.2032097 | DU16: 1.2163199 | DV16: 1.2904612 | DW16: 1.3273057 | DX16: 1.3476492 | DY16: 1.2843581 | DZ16: 1.2949822 | EA16: 1.2712477 | EB16: 1.2624321 | EC16: 1.2278481 | ED16: 1.2703435 | EE16: 1.3031194 | EF16: 1.2649185 | EG16: 1.2023057 | EH16: 1.1652351 | EI16: 1.233047 | EJ16: 1.2307867 | EK16: 1.2235534 | EL16: 1.2384721 | EM16: 1.2791592 | EN16: 1.1966547 | EO16: 1.2172243 | EP16: 1.2384721 | EQ16: 1.4859856 | ER16: 1.529159 | ES16: 1.5721066 | ET16: 1.6952983 | EU16: 1.6932639 | EV16: 1.6683996 | EW16: 1.6500905 | EX16: 1.6860309 | EY16: 1.630651
A17: sharpe_rf6 | B17: Sharpe (rf = 6%) | C17: 0.72013335 | D17: 1.1080203 | E17: 0.24400845 | F17: 1.027175 | G17: 0.47639337 | I17: 44439 | J17: 101.79638 | K17: 104.89567 | L17: 0 | M17: 0 | N17: 19 | O17: Discovery | P17: =IF(O17="Discovery",$Q$2,0) -> 225 | Q17: =IF(O17="Holdout",$Q$2,0) -> 0 | T17: 44834 | U17: 2022 | V17: 9 | W17: 0.014397621 | X17: -0.032345735 | Y17: 0.046743356 | AH17: 44810 | AI17: 0.16065083 | AJ17: 0.052016708 | AK17: 0.10863412 | AM17: 2024Q4 | AN17: Holdout | AO17: 68 | AP17: 94 | AQ17: 0.0092129462 | AR17: =MAX(AQ17,0) -> 0.0092129462 | AS17: =MIN(AQ17,0) -> 0 | AU17: 2024Q4 | AV17: -0.043348309 | AW17: -0.07712042 | AX17: 0.033772111 | AY17: =MAX(AX17,0) -> 0.033772111 | AZ17: =MIN(AX17,0) -> 0 | BB17: 14 | BC17: 585 | BD17: 0.1488899 | BE17: 0.03754004 | BF17: 0.93726303 | BG17: 0.0038274572 | BI17: 0.16223841 | BK17: 150 | BL17: 0.051146384 | BM17: 0.36507937 | BX17: Size Mid 60d | BY17: 483 | BZ17: 504 | CA17: 0.017130432 | CB17: -0.0051172498 | CC17: 0.022247681 | CD17: 0.037625719 | CE17: 13 | CF17: 20 | CG17: 0.0177489 | CH17: 1 | CP17: T0014 | CQ17: 1.0277724 | CR17: 1.0400078 | CS17: 1.0782677 | CT17: 1.0875897 | CU17: 1.087784 | CV17: 1.0906973 | CW17: 1.0780733 | CX17: 1.1439115 | CY17: 1.1097301 | CZ17: 1.1283745 | DA17: 1.1046805 | DB17: 1.0776851 | DC17: 1.1159449 | DD17: 1.1006021 | DE17: 1.070305 | DF17: 1.0899204 | DG17: 1.0772965 | DH17: 1.0576809 | DI17: 1.0772965 | DJ17: 1.0654495 | DK17: 1.0615654 | DL17: 1.0407846 | DM17: 1.0102933 | DN17: 1.0349584 | DO17: 1.0302971 | DP17: 1.0522432 | DQ17: 1.0547678 | DR17: 1.0351524 | DS17: 1.0225288 | DT17: 1.0223344 | DU17: 1.0234997 | DV17: 1.0320452 | DW17: 1.0883669 | DX17: 1.070305 | DY17: 1.0823459 | DZ17: 1.065838 | EA17: 1.0543796 | EB17: 1.0409788 | EC17: 1.0211692 | ED17: 1.0468052 | EE17: 1.0660322 | EF17: 1.0203924 | EG17: 0.99378524 | EH17: 0.98679353 | EI17: 1.0297145 | EJ17: 0.99495045 | EK17: 0.96678971 | EL17: 0.99922311 | EM17: 0.98504565 | EN17: 0.96640126 | EO17: 0.94892209 | EP17: 0.94154205 | EQ17: 0.96504176 | ER17: 0.97824823 | ES17: 0.98019039 | ET17: 0.97552923 | EU17: 1.0413673 | EV17: 1.0285491 | EW17: 0.98795881 | EX17: 0.99922311 | EY17: 1.0736064
A18: bench_sharpe_rf0 | B18: NIFTY 500 Sharpe (rf = 0%) | C18: 0.82364982 | D18: 1.092487 | E18: 0.59416204 | F18: 1.0888564 | G18: 0.59360632 | I18: 44440 | J18: 101.62042 | K18: 104.86288 | L18: -0.0017285044 | M18: -0.00031258802 | N18: 19 | O18: Discovery | P18: =IF(O18="Discovery",$Q$2,0) -> 225 | Q18: =IF(O18="Holdout",$Q$2,0) -> 0 | T18: 44865 | U18: 2022 | V18: 10 | W18: 0.012722327 | X18: 0.040099532 | Y18: -0.027377205 | AH18: 44811 | AI18: 0.17908089 | AJ18: 0.052782044 | AK18: 0.12629884 | AM18: 2025Q1 | AN18: Holdout | AO18: 70 | AP18: 85 | AQ18: 0.010027869 | AR18: =MAX(AQ18,0) -> 0.010027869 | AS18: =MIN(AQ18,0) -> 0 | AU18: 2025Q1 | AV18: -0.12373052 | AW18: -0.046294144 | AX18: -0.077436373 | AY18: =MAX(AX18,0) -> 0 | AZ18: =MIN(AX18,0) -> -0.077436373 | BB18: 15 | BC18: 586 | BD18: 0.060360836 | BE18: -0.050058648 | BF18: 0.45116498 | BG18: -0.037071539 | BI18: 0.62058446 | BX18: Size Large 60d | BY18: 586 | BZ18: 404 | CA18: 0.011921912 | CB18: -0.010695701 | CC18: 0.022617613 | CD18: 0.012214283 | CE18: 14 | CF18: 19 | CG18: 0.022999998 | CH18: 0 | CP18: T0015 | CQ18: 1.0156746 | CR18: 1.0032143 | CS18: 1.0061112 | CT18: 1.0260715 | CU18: 1.0169049 | CV18: 1.0265476 | CW18: 1.0057142 | CX18: 1.0248807 | CY18: 1.0444842 | CZ18: 1.0830556 | DA18: 1.078016 | DB18: 1.0748413 | DC18: 1.060238 | DD18: 1.0565872 | DE18: 1.1003968 | DF18: 1.0977778 | DG18: 1.0827777 | DH18: 1.0626191 | DI18: 1.0654366 | DJ18: 1.1004763 | DK18: 1.1569048 | DL18: 1.1611906 | DM18: 1.2013492 | DN18: 1.1925001 | DO18: 1.1813491 | DP18: 1.1857937 | DQ18: 1.1731349 | DR18: 1.141865 | DS18: 1.0846824 | DT18: 1.0960715 | DU18: 1.1086112 | DV18: 1.1005161 | DW18: 1.0596429 | DX18: 1.0545637 | DY18: 1.0231351 | DZ18: 1.0534129 | EA18: 1.0858731 | EB18: 1.0781349 | EC18: 1.0963096 | ED18: 1.0932938 | EE18: 1.0817064 | EF18: 1.1041666 | EG18: 1.0965078 | EH18: 1.0954366 | EI18: 1.1213889 | EJ18: 1.1251984 | EK18: 1.1011508 | EL18: 1.105238 | EM18: 1.1290874 | EN18: 1.1087698 | EO18: 1.1083335 | EP18: 1.1471429 | EQ18: 1.315238 | ER18: 1.2744841 | ES18: 1.319603 | ET18: 1.348254 | EU18: 1.3167859 | EV18: 1.3592855 | EW18: 1.3580158 | EX18: 1.385754 | EY18: 1.365873
A19: bench_sharpe_rf6 | B19: NIFTY 500 Sharpe (rf = 6%) | C19: 0.42112521 | D19: 0.67805043 | E19: 0.20279793 | F19: 0.67551347 | G19: 0.20045785 | I19: 44441 | J19: 102.21957 | K19: 105.82133 | L19: 0 | M19: 0 | N19: 19 | O19: Discovery | P19: =IF(O19="Discovery",$Q$2,0) -> 225 | Q19: =IF(O19="Holdout",$Q$2,0) -> 0 | T19: 44895 | U19: 2022 | V19: 11 | W19: 0.0046022394 | X19: 0.033853086 | Y19: -0.029250847 | AH19: 44812 | AI19: 0.17257631 | AJ19: 0.051507217 | AK19: 0.12106909 | AM19: 2025Q2 | AN19: Holdout | AO19: 100 | AP19: 76 | AQ19: 0.014965984 | AR19: =MAX(AQ19,0) -> 0.014965984 | AS19: =MIN(AQ19,0) -> 0 | AU19: 2025Q2 | AV19: 0.092316691 | AW19: 0.10673374 | AX19: -0.01441705 | AY19: =MAX(AX19,0) -> 0 | AZ19: =MIN(AX19,0) -> -0.01441705 | BB19: 16 | BC19: 588 | BD19: 0.10326227 | BE19: -0.0092256638 | BF19: 0.69820745 | BG19: -0.056321635 | BI19: 0.37580441 | BX19: KT2 ex-2021 | BY19: 1373 | BZ19: 1399 | CA19: 0.013286461 | CB19: -0.015469292 | CC19: 0.028755753 | CD19: 7.9384918e-07 | CE19: 15 | CF19: 18 | CG19: 0.025251396 | CH19: 0 | CP19: T0016 | CQ19: 0.99144588 | CR19: 0.99186207 | CS19: 0.97520786 | CT19: 0.94825884 | CU19: 0.96926558 | CV19: 0.96101419 | CW19: 0.94193787 | CX19: 0.94549568 | CY19: 0.9255866 | CZ19: 0.98236174 | DA19: 0.98258885 | DB19: 0.96729737 | DC19: 0.95291431 | DD19: 0.94560931 | DE19: 0.94568499 | DF19: 0.93955324 | DG19: 0.96411802 | DH19: 0.96453436 | DI19: 0.9682436 | DJ19: 0.97244493 | DK19: 0.96514 | DL19: 0.96044642 | DM19: 0.95283871 | DN19: 0.96093859 | DO19: 0.96161984 | DP19: 0.95654803 | DQ19: 0.96131705 | DR19: 0.94443582 | DS19: 0.93224831 | DT19: 0.89212691 | DU19: 0.8828159 | DV19: 0.87482957 | DW19: 0.90404982 | DX19: 0.88849351 | DY19: 0.88527628 | DZ19: 0.87702489 | EA19: 0.88228608 | EB19: 0.87464034 | EC19: 0.85147601 | ED19: 0.8850491 | EE19: 0.86370162 | EF19: 0.8802044 | EG19: 0.87202861 | EH19: 0.85844043 | EI19: 0.8898182 | EJ19: 0.86987116 | EK19: 0.86953058 | EL19: 0.87093103 | EM19: 0.86824361 | EN19: 0.84519291 | EO19: 0.86271751 | EP19: 0.84890223 | EQ19: 0.87081739 | ER19: 0.86555628 | ES19: 0.86555628 | ET19: 0.88217245 | EU19: 0.86332308 | EV19: 0.85215733 | EW19: 0.84632837 | EX19: 0.85503397 | EY19: 0.89507939
A20: sortino_rf0 | B20: Sortino (rf = 0%) | C20: 1.4756578 | D20: 2.0515544 | E20: 0.80115462 | F20: 1.9326267 | G20: 1.1154854 | I20: 44442 | J20: 102.24369 | K20: 106.36145 | L20: 0 | M20: 0 | N20: 19 | O20: Discovery | P20: =IF(O20="Discovery",$Q$2,0) -> 225 | Q20: =IF(O20="Holdout",$Q$2,0) -> 0 | T20: 44926 | U20: 2022 | V20: 12 | W20: -0.042758798 | X20: -0.031186211 | Y20: -0.011572587 | AH20: 44813 | AI20: 0.17207889 | AJ20: 0.04797653 | AK20: 0.12410236 | AM20: 2025Q3 | AN20: Holdout | AO20: 68 | AP20: 79 | AQ20: 0.021078692 | AR20: =MAX(AQ20,0) -> 0.021078692 | AS20: =MIN(AQ20,0) -> 0 | AU20: 2025Q3 | AV20: -0.0076903609 | AW20: -0.03739224 | AX20: 0.029701879 | AY20: =MAX(AX20,0) -> 0.029701879 | AZ20: =MIN(AX20,0) -> 0 | BB20: 17 | BC20: 577 | BD20: 0.14060051 | BE20: 0.028771495 | BF20: 0.92365884 | BG20: -0.0070264391 | BI20: 0.035945427 | BX20: KT3 Mid+Large only | BY20: 1069 | BZ20: 908 | CA20: 0.014275247 | CB20: -0.0075992921 | CC20: 0.021874539 | CD20: 0.0017494962 | CE20: 17 | CF20: 20 | CG20: 0.020908063 | CH20: 1 | CP20: T0017 | CQ20: 1.0096262 | CR20: 1.0124477 | CS20: 0.99278034 | CT20: 0.94332181 | CU20: 0.95751212 | CV20: 0.97124607 | CW20: 0.97514633 | CX20: 0.99265585 | CY20: 1.0028215 | CZ20: 0.98290522 | DA20: 0.99302934 | DB20: 0.98518739 | DC20: 0.98257329 | DD20: 0.97041614 | DE20: 0.96564451 | DF20: 0.96576901 | DG20: 0.95688969 | DH20: 0.97228337 | DI20: 0.96249118 | DJ20: 0.9722003 | DK20: 0.9724493 | DL20: 0.9492138 | DM20: 0.94576997 | DN20: 0.94336331 | DO20: 0.95406829 | DP20: 0.95245013 | DQ20: 0.96365305 | DR20: 0.95452473 | DS20: 0.93498198 | DT20: 0.95601839 | DU20: 1.0153935 | DV20: 0.9959753 | DW20: 1.000166 | DX20: 0.98867271 | DY20: 0.98269779 | DZ20: 1.0078835 | EA20: 1.0073441 | EB20: 1.0087548 | EC20: 0.9959753 | ED20: 0.99456451 | EE20: 0.99066431 | EF20: 0.98659805 | EG20: 0.98004226 | EH20: 0.95659932 | EI20: 0.94502304 | EJ20: 0.93261702 | EK20: 0.91456781 | EL20: 0.93950448 | EM20: 0.91241022 | EN20: 0.91448488 | EO20: 0.89212074 | EP20: 0.89212074 | EQ20: 0.92755489 | ER20: 0.92257583 | ES20: 0.93344675 | ET20: 0.93967061 | EU20: 0.94564547 | EV20: 0.93120616 | EW20: 0.96157838 | EX20: 0.97879746 | EY20: 1.0238164
A21: calmar | B21: Calmar (CAGR / |max DD|) | C21: 0.72459696 | D21: 1.2009616 | E21: 0.3490317 | F21: 1.1328598 | G21: 0.55101724 | I21: 44445 | J21: 102.49114 | K21: 106.69691 | L21: 0 | M21: 0 | N21: 19 | O21: Discovery | P21: =IF(O21="Discovery",$Q$2,0) -> 225 | Q21: =IF(O21="Holdout",$Q$2,0) -> 0 | T21: 44957 | U21: 2023 | V21: 1 | W21: -0.024490579 | X21: -0.033229011 | Y21: 0.0087384317 | AH21: 44816 | AI21: 0.17932527 | AJ21: 0.052111159 | AK21: 0.12721411 | AM21: 2025Q4 | AN21: Holdout | AO21: 80 | AP21: 69 | AQ21: 0.036012864 | AR21: =MAX(AQ21,0) -> 0.036012864 | AS21: =MIN(AQ21,0) -> 0 | AU21: 2025Q4 | AV21: 0.021082161 | AW21: 0.05003277 | AX21: -0.028950609 | AY21: =MAX(AX21,0) -> 0 | AZ21: =MIN(AX21,0) -> -0.028950609 | BB21: 18 | BC21: 576 | BD21: 0.091368032 | BE21: -0.02046098 | BF21: 0.62229888 | BG21: -0.053659316 | BI21: -0.03207 | BX21: KT4 ex-Layer-4-seen | BY21: 1395 | BZ21: 1476 | CA21: 0.014189698 | CB21: -0.016307054 | CC21: 0.030496752 | CD21: 1.0634336e-07 | CE21: 17 | CF21: 20 | CG21: 0.030977205 | CH21: 0 | CP21: T0018 | CQ21: 0.97365012 | CR21: 0.9689903 | CS21: 0.94330933 | CT21: 0.90245735 | CU21: 0.94498081 | CV21: 0.92527597 | CW21: 0.94220171 | CX21: 0.94353905 | CY21: 0.94015381 | CZ21: 0.94615112 | DA21: 0.91906981 | DB21: 0.91752339 | DC21: 0.936121 | DD21: 0.92339526 | DE21: 0.91163082 | DF21: 0.92069971 | DG21: 0.92019823 | DH21: 0.91685472 | DI21: 0.93534783 | DJ21: 0.98207137 | DK21: 0.97304015 | DL21: 1.0078894 | DM21: 0.96704038 | DN21: 0.95700589 | DO21: 0.95656671 | DP21: 0.95836464 | DQ21: 0.95359825 | DR21: 0.95069239 | DS21: 0.94408626 | DT21: 0.91803815 | DU21: 0.90480509 | DV21: 0.92249096 | DW21: 0.92518781 | DX21: 0.93513875 | DY21: 0.92698566 | DZ21: 0.91544588 | EA21: 0.9454869 | EB21: 0.97450355 | EC21: 0.94979347 | ED21: 0.93948706 | EE21: 0.9616885 | EF21: 0.95104779 | EG21: 0.93505512 | EH21: 0.91753636 | EI21: 0.85703631 | EJ21: 0.85682723 | EK21: 0.81961576 | EL21: 0.85105742 | EM21: 0.92531326 | EN21: 0.91542493 | EO21: 0.91168291 | EP21: 0.91448419 | EQ21: 0.89759259 | ER21: 0.97947902 | ES21: 0.9966423 | ET21: 0.98719308 | EU21: 0.99492808 | EV21: 1.0034157 | EW21: 0.99235668 | EX21: 0.98976448 | EY21: 1.0311361
A22: max_dd | B22: Maximum drawdown | C22: -0.23675278 | D22: -0.19281551 | E22: -0.24950465 | F22: -0.19281551 | G22: -0.23675278 | I22: 44446 | J22: 102.11149 | K22: 106.54125 | L22: -0.0037042073 | M22: -0.0014588828 | N22: 19 | O22: Discovery | P22: =IF(O22="Discovery",$Q$2,0) -> 225 | Q22: =IF(O22="Holdout",$Q$2,0) -> 0 | T22: 44985 | U22: 2023 | V22: 2 | W22: -0.0050317282 | X22: -0.027903318 | Y22: 0.022871589 | AH22: 44817 | AI22: 0.18343279 | AJ22: 0.059901584 | AK22: 0.1235312 | AM22: 2026Q1 | AN22: Holdout | AO22: 75 | AP22: 78 | AQ22: 0.028181966 | AR22: =MAX(AQ22,0) -> 0.028181966 | AS22: =MIN(AQ22,0) -> 0 | AU22: 2026Q1 | AV22: -0.1201194 | AW22: -0.14006212 | AX22: 0.019942729 | AY22: =MAX(AX22,0) -> 0.019942729 | AZ22: =MIN(AX22,0) -> 0 | BB22: 19 | BC22: 576 | BD22: 0.096184264 | BE22: -0.01630367 | BF22: 0.66832265 | BG22: -0.055638108 | BI22: -0.16218832 | BX22: KT6 8Q window | BY22: 1412 | BZ22: 1513 | CA22: 0.014769971 | CB22: -0.014356729 | CC22: 0.0291267 | CD22: 3.7179857e-07 | CE22: 16 | CF22: 19 | CG22: 0.027483593 | CH22: 0 | CP22: T0019 | CQ22: 0.99618216 | CR22: 0.98351784 | CS22: 0.97197102 | CT22: 0.97383352 | CU22: 0.9774651 | CV22: 0.9774651 | CW22: 0.97653394 | CX22: 0.97737205 | CY22: 0.99059497 | CZ22: 1.0165748 | DA22: 1.0230003 | DB22: 1.0399479 | DC22: 1.039482 | DD22: 1.0640653 | DE22: 1.0515876 | DF22: 1.0522393 | DG22: 1.0509358 | DH22: 1.101499 | DI22: 1.0932113 | DJ22: 1.090604 | DK22: 1.0696165 | DL22: 1.0519085 | DM22: 1.0183657 | DN22: 1.0295153 | DO22: 1.0074971 | DP22: 1.0068412 | DQ22: 0.99409875 | DR22: 0.98323028 | DS22: 0.96805169 | DT22: 0.97189329 | DU22: 0.99897076 | DV22: 0.99372398 | DW22: 0.98894559 | DX22: 0.98669697 | DY22: 0.96823911 | DZ22: 0.97292388 | EA22: 0.97142477 | EB22: 0.96402286 | EC22: 0.9538102 | ED22: 0.9659905 | EE22: 0.95530932 | EF22: 0.9538102 | EG22: 0.94743889 | EH22: 0.93516498 | EI22: 0.92073595 | EJ22: 0.89215924 | EK22: 0.87801118 | EL22: 0.88672491 | EM22: 0.8850383 | EN22: 0.86742387 | EO22: 0.88803666 | EP22: 0.89422049 | EQ22: 0.89497005 | ER22: 0.89384571 | ES22: 0.90124762 | ET22: 0.91914322 | EU22: 0.92570195 | EV22: 0.92026755 | EW22: 0.93628926 | EX22: 0.93263514 | EY22: 0.94603358
A23: bench_max_dd | B23: NIFTY 500 maximum drawdown | C23: -0.18843201 | D23: -0.18477731 | E23: -0.18843201 | F23: -0.18477731 | G23: -0.18843201 | I23: 44447 | J23: 102.46581 | K23: 106.6807 | L23: -0.00024715338 | M23: -0.00015196696 | N23: 19 | O23: Discovery | P23: =IF(O23="Discovery",$Q$2,0) -> 225 | Q23: =IF(O23="Holdout",$Q$2,0) -> 0 | T23: 45016 | U23: 2023 | V23: 3 | W23: -0.011204118 | X23: 0.0026930693 | Y23: -0.013897188 | AH23: 44818 | AI23: 0.18288853 | AJ23: 0.055871545 | AK23: 0.12701698 | AM23: 2026Q2 | AN23: Holdout | AO23: 114 | AP23: 91 | AQ23: 0.040631686 | AR23: =MAX(AQ23,0) -> 0.040631686 | AS23: =MIN(AQ23,0) -> 0 | AU23: 2026Q2 | AV23: 0.22244558 | AW23: 0.12020625 | AX23: 0.10223932 | AY23: =MAX(AX23,0) -> 0.10223932 | AZ23: =MIN(AX23,0) -> 0 | BB23: 20 | BC23: 581 | BD23: 0.073050175 | BE23: -0.039637548 | BF23: 0.52888593 | BG23: -0.067946265 | BI23: -0.045462277 | BX23: KT6 expanding window | BY23: 1470 | BZ23: 1543 | CA23: 0.013930812 | CB23: -0.014392857 | CC23: 0.028323669 | CD23: 5.483487e-07 | CE23: 17 | CF23: 20 | CG23: 0.028609544 | CH23: 1 | CP23: T0020 | CQ23: 0.98565842 | CR23: 0.98629247 | CS23: 0.97635712 | CT23: 0.9860087 | CU23: 0.98249408 | CV23: 0.97565413 | CW23: 0.95501303 | CX23: 0.94591579 | CY23: 0.94432062 | CZ23: 0.94152256 | DA23: 0.9434555 | DB23: 0.92504468 | DC23: 0.91858307 | DD23: 0.9398464 | DE23: 0.94195512 | DF23: 0.94413149 | DG23: 0.94856507 | DH23: 0.94696997 | DI23: 0.94776759 | DJ23: 0.94198204 | DK23: 0.94303652 | DL23: 0.95326929 | DM23: 0.96063629 | DN23: 0.96147434 | DO23: 0.95214733 | DP23: 0.93965696 | DQ23: 0.93498011 | DR23: 0.93656156 | DS23: 0.93089765 | DT23: 0.93160056 | DU23: 0.93185756 | DV23: 0.94676741 | DW23: 0.95410741 | DX23: 0.96725973 | DY23: 0.98485973 | DZ23: 0.98419724 | EA23: 0.9560672 | EB23: 0.96907134 | EC23: 0.98053414 | ED23: 0.97373492 | EE23: 0.98321064 | EF23: 0.97587049 | EG23: 0.97969602 | EH23: 0.96524588 | EI23: 0.96828714 | EJ23: 0.96903061 | EK23: 0.96160947 | EL23: 0.97550565 | EM23: 0.98157497 | EN23: 0.99021265 | EO23: 0.99242943 | EP23: 0.99924231 | EQ23: 1.0020674 | ER23: 0.99886382 | ES23: 1.0094209 | ET23: 1.0106647 | EU23: 1.0321303 | EV23: 1.0502438 | EW23: 1.0438095 | EX23: 1.0293457 | EY23: 1.0417954
A24: avg_dd_episode | B24: Average drawdown (mean episode trough) | C24: -0.027338901 | D24: -0.020194367 | E24: -0.033755378 | F24: -0.021551463 | G24: -0.037260221 | I24: 44448 | J24: 102.73715 | K24: 106.91743 | L24: 0 | M24: 0 | N24: 19 | O24: Discovery | P24: =IF(O24="Discovery",$Q$2,0) -> 225 | Q24: =IF(O24="Holdout",$Q$2,0) -> 0 | T24: 45046 | U24: 2023 | V24: 4 | W24: 0.045855692 | X24: 0.04545314 | Y24: 0.0004025516 | AH24: 44819 | AI24: 0.182878 | AJ24: 0.050140027 | AK24: 0.13273797 | AU24: 2026Q3 | AV24: 0.029970903 | AW24: 0.029809986 | AX24: 0.00016091746 | AY24: =MAX(AX24,0) -> 0.00016091746 | AZ24: =MIN(AX24,0) -> 0 | BB24: 21 | BC24: 580 | BD24: 0.083568305 | BE24: -0.029119417 | BF24: 0.57612755 | BG24: -0.09231302 | BI24: -0.069169111 | BX24: KT1 ex top-2 quarters (event level) | BY24: 1359 | BZ24: 1384 | CA24: 0.013484676 | CB24: -0.012730681 | CC24: 0.026215357 | CD24: 8.3915103e-06 | CE24: 15 | CF24: 18 | CG24: 0.025125156 | CH24: 0 | CP24: T0021 | CQ24: 1.0299713 | CR24: 1.0472127 | CS24: 1.0358333 | CT24: 1.0078448 | CU24: 0.98839088 | CV24: 0.98135063 | CW24: 0.98781536 | CX24: 1.0024554 | CY24: 0.98793143 | CZ24: 0.96697147 | DA24: 0.98569919 | DB24: 0.98445271 | DC24: 0.98711974 | DD24: 0.99071461 | DE24: 1.0074129 | DF24: 1.010312 | DG24: 1.0089495 | DH24: 1.0049777 | DI24: 1.0321705 | DJ24: 1.0362003 | DK24: 1.0391863 | DL24: 1.0363742 | DM24: 1.0317067 | DN24: 1.0201106 | DO24: 1.0070652 | DP24: 0.98335089 | DQ24: 0.99865788 | DR24: 0.98082876 | DS24: 0.98355387 | DT24: 0.99300468 | DU24: 0.9943094 | DV24: 1.0136459 | DW24: 1.0062823 | DX24: 0.98294517 | DY24: 0.99242498 | DZ24: 1.0166028 | EA24: 1.0224589 | EB24: 1.0200237 | EC24: 1.0115586 | ED24: 1.015907 | EE24: 1.0054995 | EF24: 1.0271842 | EG24: 1.0557397 | EH24: 1.043013 | EI24: 1.0503767 | EJ24: 1.057972 | EK24: 1.0770476 | EL24: 1.0804685 | EM24: 1.0820049 | EN24: 1.0946737 | EO24: 1.0932532 | EP24: 1.0974858 | EQ24: 1.0945288 | ER24: 1.1007326 | ES24: 1.1011385 | ET24: 1.0695391 | EU24: 1.0539713 | EV24: 1.0519421 | EW24: 1.073076 | EX24: 1.0758881 | EY24: 1.0885567
A25: longest_dd_sessions | B25: Longest drawdown (trading sessions) | C25: 423 | D25: 184 | E25: 431 | F25: 184 | G25: 423 | I25: 44452 | J25: 102.75553 | K25: 107.03093 | L25: 0 | M25: 0 | N25: 19 | O25: Discovery | P25: =IF(O25="Discovery",$Q$2,0) -> 225 | Q25: =IF(O25="Holdout",$Q$2,0) -> 0 | T25: 45077 | U25: 2023 | V25: 5 | W25: 0.034457254 | X25: 0.03593076 | Y25: -0.0014735056 | AH25: 44820 | AI25: 0.15905112 | AJ25: 0.026376564 | AK25: 0.13267456 | BB25: 22 | BC25: 582 | BD25: 0.0650193 | BE25: -0.047468634 | BF25: 0.481474 | BG25: -0.064959308 | BI25: -0.034773182 | CP25: T0022 | CQ25: 1.0087897 | CR25: 1.0072361 | CS25: 1.0124464 | CT25: 1.0081202 | CU25: 1.0256139 | CV25: 1.0437168 | CW25: 1.0626781 | CX25: 1.0678285 | CY25: 1.0617254 | CZ25: 1.076395 | DA25: 1.1004551 | DB25: 1.1316395 | DC25: 1.1249358 | DD25: 1.1363606 | DE25: 1.1329357 | DF25: 1.132206 | DG25: 1.0971246 | DH25: 1.0351588 | DI25: 1.0366439 | DJ25: 1.0321459 | DK25: 1.0216482 | DL25: 1.0022662 | DM25: 0.9749959 | DN25: 0.99255794 | DO25: 1.0100345 | DP25: 1.0265666 | DQ25: 1.0124035 | DR25: 0.97885856 | DS25: 1.012558 | DT25: 1.0111417 | DU25: 1.0203263 | DV25: 1.0289701 | DW25: 1.008352 | DX25: 1.0338112 | DY25: 1.0072877 | DZ25: 1.0144035 | EA25: 0.984146 | EB25: 0.93284122 | EC25: 0.93296135 | ED25: 0.94019751 | EE25: 0.94266108 | EF25: 0.94437766 | EG25: 0.93460962 | EH25: 0.94920171 | EI25: 0.97975975 | EJ25: 0.99813745 | EK25: 1.007382 | EL25: 1.0117854 | EM25: 1.0262233 | EN25: 1.0238284 | EO25: 1.0083349 | EP25: 0.99563089 | EQ25: 1.0288327 | ER25: 1.019528 | ES25: 1.049631 | ET25: 1.0990129 | EU25: 1.0836053 | EV25: 1.0983864 | EW25: 1.0946439 | EX25: 1.1978113 | EY25: 1.2756139
A26: beta | B26: Beta to NIFTY 500 (daily) | C26: 0.94573016 | D26: 0.87303271 | E26: 0.97843988 | F26: 0.87962237 | G26: 1.0002074 | I26: 44453 | J26: 102.99518 | K26: 107.40674 | L26: 0 | M26: 0 | N26: 19 | O26: Discovery | P26: =IF(O26="Discovery",$Q$2,0) -> 225 | Q26: =IF(O26="Holdout",$Q$2,0) -> 0 | T26: 45107 | U26: 2023 | V26: 6 | W26: 0.04995296 | X26: 0.042089507 | Y26: 0.0078634533 | AH26: 44823 | AI26: 0.15198269 | AJ26: 0.026113182 | AK26: 0.12586951 | BB26: 23 | BC26: 567 | BD26: 0.11830494 | BE26: 0.0058170057 | BF26: 0.80586802 | BG26: -0.035731251 | BI26: 0.10746279 | CP26: T0023 | CQ26: 1.0169484 | CR26: 1.005518 | CS26: 1.0508944 | CT26: 1.0544907 | CU26: 1.0517318 | CV26: 1.0638519 | CW26: 1.0707002 | CX26: 1.0798641 | CY26: 1.0641966 | CZ26: 1.0538503 | DA26: 1.0496624 | DB26: 1.0513869 | DC26: 1.0446865 | DD26: 1.0188697 | DE26: 1.0069468 | DF26: 0.99044191 | DG26: 0.97482387 | DH26: 0.98669758 | DI26: 0.97807559 | DJ26: 0.97610485 | DK26: 0.93861157 | DL26: 0.92077654 | DM26: 0.92727992 | DN26: 0.9309257 | DO26: 0.93703507 | DP26: 0.9369364 | DQ26: 0.92806816 | DR26: 0.945115 | DS26: 0.96467453 | DT26: 0.96925656 | DU26: 0.97817413 | DV26: 0.97068529 | DW26: 0.97807559 | DX26: 0.98413569 | DY26: 0.97516872 | DZ26: 0.96541362 | EA26: 0.93649307 | EB26: 0.95693945 | EC26: 0.9806376 | ED26: 0.98339653 | EE26: 0.97659752 | EF26: 0.96728582 | EG26: 0.97832183 | EH26: 0.97438047 | EI26: 0.97029117 | EJ26: 0.98940724 | EK26: 1.0117259 | EL26: 1.0094103 | EM26: 1.0142878 | EN26: 0.99290538 | EO26: 1.0133024 | EP26: 1.0315316 | EQ26: 1.0036951 | ER26: 1.0266543 | ES26: 1.0052225 | ET26: 0.99709311 | EU26: 1.0066512 | EV26: 0.95713648 | EW26: 0.94856381 | EX26: 0.93772483 | EY26: 0.92663943
A27: var95_daily | B27: VaR 95% (1-day) | C27: 0.016145473 | D27: 0.014830713 | E27: 0.016855544 | F27: 0.014895876 | G27: 0.017258338 | I27: 44454 | J27: 103.71477 | K27: 108.24412 | L27: 0 | M27: 0 | N27: 19 | O27: Discovery | P27: =IF(O27="Discovery",$Q$2,0) -> 225 | Q27: =IF(O27="Holdout",$Q$2,0) -> 0 | T27: 45138 | U27: 2023 | V27: 7 | W27: 0.087975714 | X27: 0.038283628 | Y27: 0.049692086 | AH27: 44824 | AI27: 0.15599099 | AJ27: 0.029945641 | AK27: 0.12604535 | BB27: 24 | BC27: 586 | BD27: 0.09983398 | BE27: -0.0097088069 | BF27: 0.67529088 | BG27: -0.032497142 | BI27: -0.029565473 | CP27: T0024 | CQ27: 0.99800244 | CR27: 1.0074714 | CS27: 0.99966805 | CT27: 0.99095948 | CU27: 0.96815939 | CV27: 0.9819856 | CW27: 0.97281231 | CX27: 0.96561863 | CY27: 0.96810494 | CZ27: 0.96829814 | DA27: 1.0006458 | DB27: 1.0020701 | DC27: 1.0067835 | DD27: 1.0079239 | DE27: 0.98610147 | DF27: 0.97361505 | DG27: 0.97774894 | DH27: 0.98138205 | DI27: 0.98750162 | DJ27: 0.99451428 | DK27: 0.96858193 | DL27: 0.95852736 | DM27: 0.94815332 | DN27: 0.95267362 | DO27: 0.95249246 | DP27: 0.94085703 | DQ27: 0.93809292 | DR27: 0.92885934 | DS27: 0.92450203 | DT27: 0.9250574 | DU27: 0.92496682 | DV27: 0.92995776 | DW27: 0.92217258 | DX27: 0.9138564 | DY27: 0.91447805 | DZ27: 0.90533497 | EA27: 0.91794818 | EB27: 0.9296077 | EC27: 0.93923352 | ED27: 0.93546779 | EE27: 0.93017512 | EF27: 0.92813522 | EG27: 0.93934228 | EH27: 0.93546166 | EI27: 0.95198563 | EJ27: 0.9389077 | EK27: 0.92911897 | EL27: 0.92070608 | EM27: 0.91475555 | EN27: 0.90588422 | EO27: 0.90758604 | EP27: 0.91603498 | EQ27: 0.91798438 | ER27: 0.90992761 | ES27: 0.91465914 | ET27: 0.90624632 | EU27: 0.90106226 | EV27: 0.89711521 | EW27: 0.89330715 | EX27: 0.883947 | EY27: 0.86756186
A28: cvar95_daily | B28: CVaR 95% (1-day) | C28: 0.025294984 | D28: 0.023651239 | E28: 0.02599451 | F28: 0.02382464 | G28: 0.026133472 | I28: 44455 | J28: 103.73063 | K28: 108.85198 | L28: 0 | M28: 0 | N28: 19 | O28: Discovery | P28: =IF(O28="Discovery",$Q$2,0) -> 225 | Q28: =IF(O28="Holdout",$Q$2,0) -> 0 | T28: 45169 | U28: 2023 | V28: 8 | W28: 0.021907845 | X28: -0.0078961252 | Y28: 0.02980397 | AH28: 44825 | AI28: 0.1464395 | AJ28: 0.016971314 | AK28: 0.12946819 | BB28: 25 | BC28: 584 | BD28: 0.12506853 | BE28: 0.013239517 | BF28: 0.81417451 | BG28: -0.039993498 | BI28: 0.024601184 | CP28: T0025 | CQ28: 0.96355856 | CR28: 0.9338827 | CS28: 0.98385574 | CT28: 0.99445941 | CU28: 0.99276581 | CV28: 0.99409021 | CW28: 0.98985576 | CX28: 0.97589189 | CY28: 0.98232416 | CZ28: 0.97870271 | DA28: 0.97565754 | DB28: 0.97135122 | DC28: 0.97426117 | DD28: 0.98089181 | DE28: 0.96915303 | DF28: 0.92191884 | DG28: 0.92406287 | DH28: 0.90727019 | DI28: 0.90208099 | DJ28: 0.89744136 | DK28: 0.88112601 | DL28: 0.9012072 | DM28: 0.88438735 | DN28: 0.89002689 | DO28: 0.88746832 | DP28: 0.87653154 | DQ28: 0.87333326 | DR28: 0.87726121 | DS28: 0.87462149 | DT28: 0.88069366 | DU28: 0.88843225 | DV28: 0.88104495 | DW28: 0.87167564 | DX28: 0.86560357 | DY28: 0.82855841 | DZ28: 0.85526115 | EA28: 0.88237835 | EB28: 0.88091883 | EC28: 0.87920715 | ED28: 0.87880179 | EE28: 0.87881987 | EF28: 0.88107203 | EG28: 0.87906294 | EH28: 0.87881987 | EI28: 0.86780167 | EJ28: 0.89036928 | EK28: 0.89440537 | EL28: 0.88487377 | EM28: 0.88327022 | EN28: 0.86991871 | EO28: 0.88407204 | EP28: 0.88325223 | EQ28: 0.8769459 | ER28: 0.88398199 | ES28: 0.88713502 | ET28: 0.90293687 | EU28: 0.88779281 | EV28: 0.87350436 | EW28: 0.86452242 | EX28: 0.84516199 | EY28: 0.80099087
A29: skew_daily | B29: Skewness (daily) | C29: -0.84651235 | D29: -0.86821847 | E29: -0.80798231 | F29: -0.85031217 | G29: -0.82742782 | I29: 44456 | J29: 102.69771 | K29: 108.29241 | L29: -0.0099577527 | M29: -0.0051407159 | N29: 19 | O29: Discovery | P29: =IF(O29="Discovery",$Q$2,0) -> 225 | Q29: =IF(O29="Holdout",$Q$2,0) -> 0 | T29: 45199 | U29: 2023 | V29: 9 | W29: -0.0066212008 | X29: 0.021761609 | Y29: -0.02838281 | AH29: 44826 | AI29: 0.17580264 | AJ29: 0.020499426 | AK29: 0.15530322 | BB29: 26 | BC29: 585 | BD29: 0.12588952 | BE29: 0.01406051 | BF29: 0.81573607 | BG29: 0.0058713426 | BI29: -0.20485913 | CP29: T0026 | CQ29: 0.96917574 | CR29: 0.96455391 | CS29: 0.94836058 | CT29: 0.94659043 | CU29: 0.95164956 | CV29: 0.95547396 | CW29: 0.95668691 | CX29: 0.96682665 | CY29: 0.96935073 | CZ29: 0.97174374 | DA29: 0.96960194 | DB29: 0.96707798 | DC29: 0.96147257 | DD29: 0.95690523 | DE29: 0.95008687 | DF29: 0.90939597 | DG29: 0.92296693 | DH29: 0.91408345 | DI29: 0.91647646 | DJ29: 0.89695041 | DK29: 0.89451383 | DL29: 0.90170361 | DM29: 0.92615743 | DN29: 0.93488799 | DO29: 0.93454928 | DP29: 0.92629953 | DQ29: 0.92725023 | DR29: 0.93823152 | DS29: 0.92955568 | DT29: 0.9380459 | DU29: 0.92561108 | DV29: 0.92896571 | DW29: 0.88830753 | DX29: 0.8847563 | DY29: 0.87804728 | DZ29: 0.83493061 | EA29: 0.83212238 | EB29: 0.83698479 | EC29: 0.82646236 | ED29: 0.82085694 | EE29: 0.82338108 | EF29: 0.82682296 | EG29: 0.81167863 | EH29: 0.82759879 | EI29: 0.82928151 | EJ29: 0.83144497 | EK29: 0.83305123 | EL29: 0.84633803 | EM29: 0.86939335 | EN29: 0.87329408 | EO29: 0.87599309 | EP29: 0.87409187 | EQ29: 0.87396075 | ER29: 0.87404818 | ES29: 0.87319578 | ET29: 0.87648476 | EU29: 0.87624436 | EV29: 0.87311945 | EW29: 0.86411584 | EX29: 0.83363022 | EY29: 0.79656695
A30: excess_kurt_daily | B30: Excess kurtosis (daily) | C30: 4.3629052 | D30: 3.9249457 | E30: 4.5016245 | F30: 3.8895558 | G30: 4.4270544 | I30: 44459 | J30: 101.47646 | K30: 106.84752 | L30: -0.021731052 | M30: -0.018414554 | N30: 19 | O30: Discovery | P30: =IF(O30="Discovery",$Q$2,0) -> 225 | Q30: =IF(O30="Holdout",$Q$2,0) -> 0 | T30: 45230 | U30: 2023 | V30: 10 | W30: -0.0095014938 | X30: -0.028422562 | Y30: 0.018921068 | AH30: 44827 | AI30: 0.17227456 | AJ30: 0.015573204 | AK30: 0.15670136 | BB30: 27 | BC30: 581 | BD30: 0.071966494 | BE30: -0.04052144 | BF30: 0.51809019 | BG30: -0.089333398 | BI30: -0.053405682 | CP30: T0027 | CQ30: 1.0251742 | CR30: 0.99340102 | CS30: 1.0085544 | CT30: 1.00095 | CU30: 0.99113786 | CV30: 1.0026669 | CW30: 1.0210647 | CX30: 1.0655867 | CY30: 1.0426511 | CZ30: 1.0323486 | DA30: 1.044123 | DB30: 1.0316125 | DC30: 1.0757667 | DD30: 1.1653017 | DE30: 1.1510741 | DF30: 1.1204116 | DG30: 1.2273626 | DH30: 1.1954736 | DI30: 1.225891 | DJ30: 1.1561027 | DK30: 1.1630938 | DL30: 1.1650562 | DM30: 1.1973133 | DN30: 1.1990303 | DO30: 1.1846804 | DP30: 1.147272 | DQ30: 1.161622 | DR30: 1.1813687 | DS30: 1.1892182 | DT30: 1.174991 | DU30: 1.2371748 | DV30: 1.2403636 | DW30: 1.2298158 | DX30: 1.2395049 | DY30: 1.2212303 | DZ30: 1.1470267 | EA30: 1.1632165 | EB30: 1.228344 | EC30: 1.2964148 | ED30: 1.3014434 | EE30: 1.2918768 | EF30: 1.3246244 | EG30: 1.3116236 | EH30: 1.3273228 | EI30: 1.3361535 | EJ30: 1.3907331 | EK30: 1.3727034 | EL30: 1.3514849 | EM30: 1.37209 | EN30: 1.4161216 | EO30: 1.4021395 | EP30: 1.4027527 | EQ30: 1.4104795 | ER30: 1.3972334 | ES30: 1.3663256 | ET30: 1.3480506 | EU30: 1.3116236 | EV30: 1.258148 | EW30: 1.2316554 | EX30: 1.1952283 | EY30: 1.1050802
A31: trades | B31: Total trades | C31: 567 | D31: 277 | E31: 296 | I31: 44460 | J31: 101.92737 | K31: 107.70905 | L31: -0.017384079 | M31: -0.010499904 | N31: 19 | O31: Discovery | P31: =IF(O31="Discovery",$Q$2,0) -> 225 | Q31: =IF(O31="Holdout",$Q$2,0) -> 0 | T31: 45260 | U31: 2023 | V31: 11 | W31: 0.11268064 | X31: 0.070641208 | Y31: 0.042039434 | AH31: 44830 | AI31: 0.1280915 | AJ31: -0.014759506 | AK31: 0.14285101 | BB31: 28 | BC31: 586 | BD31: 0.097617865 | BE31: -0.013731992 | BF31: 0.66408114 | BG31: -0.021044903 | BI31: 0.1809165 | CP31: T0028 | CQ31: 0.98037781 | CR31: 1.0124687 | CS31: 1.0217183 | CT31: 1.0715026 | CU31: 1.0811622 | CV31: 1.0873372 | CW31: 1.0673005 | CX31: 1.0622529 | CY31: 1.0151333 | CZ31: 1.0364767 | DA31: 1.0173881 | DB31: 1.0698883 | DC31: 1.042908 | DD31: 1.0247417 | DE31: 0.96714261 | DF31: 0.98459145 | DG31: 0.99906814 | DH31: 1.0186436 | DI31: 0.99238053 | DJ31: 1.0149283 | DK31: 1.0412681 | DL31: 1.005038 | DM31: 1.0071135 | DN31: 1.0000417 | DO31: 0.98159365 | DP31: 0.99358485 | DQ31: 1.0157995 | DR31: 1.0153383 | DS31: 1.0098807 | DT31: 1.0160044 | DU31: 1.1018651 | DV31: 1.1660748 | DW31: 1.2008444 | DX31: 1.1459356 | DY31: 1.0725786 | DZ31: 1.1604891 | EA31: 1.1482416 | EB31: 1.1253609 | EC31: 1.1237977 | ED31: 1.1752988 | EE31: 1.1830112 | EF31: 1.1879051 | EG31: 1.1957454 | EH31: 1.1880587 | EI31: 1.2760973 | EJ31: 1.313301 | EK31: 1.2842196 | EL31: 1.3095088 | EM31: 1.3138902 | EN31: 1.3433816 | EO31: 1.32314 | EP31: 1.3295967 | EQ31: 1.3472762 | ER31: 1.3784587 | ES31: 1.3985976 | ET31: 1.3845056 | EU31: 1.3950108 | EV31: 1.4417203 | EW31: 1.3926278 | EX31: 1.2697172 | EY31: 1.2215729
A32: win_rate | B32: Win rate | C32: 0.58377425 | D32: 0.59205776 | E32: 0.56418919 | I32: 44461 | J32: 102.03817 | K32: 108.02793 | L32: -0.016315939 | M32: -0.0075703911 | N32: 19 | O32: Discovery | P32: =IF(O32="Discovery",$Q$2,0) -> 225 | Q32: =IF(O32="Holdout",$Q$2,0) -> 0 | T32: 45291 | U32: 2023 | V32: 12 | W32: 0.060353799 | X32: 0.080120303 | Y32: -0.019766504 | AH32: 44831 | AI32: 0.13171557 | AJ32: -0.017561063 | AK32: 0.14927663 | BB32: 29 | BC32: 582 | BD32: 0.091449021 | BE32: -0.019900836 | BF32: 0.63132446 | BG32: -0.054234289 | BI32: -0.19016746 | CP32: T0029 | CQ32: 0.98093266 | CR32: 1.0120941 | CS32: 1.0091525 | CT32: 1.0767053 | CU32: 1.1158204 | CV32: 1.1810853 | CW32: 1.1278056 | CX32: 1.1612554 | CY32: 1.1734581 | CZ32: 1.1604927 | DA32: 1.1710612 | DB32: 1.1304207 | DC32: 1.1088474 | DD32: 1.0731097 | DE32: 1.0860754 | DF32: 1.0613424 | DG32: 1.0607975 | DH32: 1.1219221 | DI32: 1.1161475 | DJ32: 1.0680977 | DK32: 1.1487255 | DL32: 1.1139683 | DM32: 1.1102636 | DN32: 1.1083025 | DO32: 1.1124428 | DP32: 1.1142951 | DQ32: 1.1555893 | DR32: 1.1546087 | DS32: 1.1319461 | DT32: 1.1857703 | DU32: 1.2123557 | DV32: 1.2314229 | DW32: 1.3170629 | DX32: 1.2843757 | DY32: 1.2748965 | DZ32: 1.3229461 | EA32: 1.3262149 | EB32: 1.3265416 | EC32: 1.3399436 | ED32: 1.4619745 | EE32: 1.4573981 | EF32: 1.4790807 | EG32: 1.4752671 | EH32: 1.4584876 | EI32: 1.5357379 | EJ32: 1.5393331 | EK32: 1.5396603 | EL32: 1.559926 | EM32: 1.559708 | EN32: 1.5892352 | EO32: 1.596971 | EP32: 1.6247548 | EQ32: 1.6118981 | ER32: 1.6481804 | ES32: 1.6550448 | ET32: 1.6019831 | EU32: 1.6210504 | EV32: 1.6062322 | EW32: 1.5399871 | EX32: 1.3994334 | EY32: 1.3972543
A33: profit_factor | B33: Profit factor | C33: 2.0928063 | D33: 2.670276 | E33: 1.5129575 | I33: 44462 | J33: 102.44451 | K33: 109.57659 | L33: -0.01239869 | M33: 0 | N33: 19 | O33: Discovery | P33: =IF(O33="Discovery",$Q$2,0) -> 225 | Q33: =IF(O33="Holdout",$Q$2,0) -> 0 | T33: 45322 | U33: 2024 | V33: 1 | W33: 0.047025805 | X33: 0.019195384 | Y33: 0.027830421 | AH33: 44832 | AI33: 0.1239894 | AJ33: -0.038463183 | AK33: 0.16245258 | BB33: 30 | BC33: 585 | BD33: 0.088697183 | BE33: -0.022652674 | BF33: 0.61530696 | BG33: -0.04969185 | BI33: 0.055002057 | CP33: T0030 | CQ33: 0.9814157 | CR33: 1.0132316 | CS33: 1.0185841 | CT33: 1.0012506 | CU33: 1.0128438 | CV33: 1.0265383 | CW33: 1.0348548 | CX33: 1.0390696 | CY33: 1.0331539 | CZ33: 1.0372562 | DA33: 1.0644946 | DB33: 1.0758379 | DC33: 1.0796523 | DD33: 1.0408829 | DE33: 1.0261005 | DF33: 1.0449598 | DG33: 1.0273135 | DH33: 1.0165832 | DI33: 0.97776374 | DJ33: 1.0035642 | DK33: 1.0352173 | DL33: 1.0522636 | DM33: 1.0986995 | DN33: 1.0846047 | DO33: 1.0607055 | DP33: 1.0446097 | DQ33: 1.0722486 | DR33: 1.0850799 | DS33: 1.0849426 | DT33: 1.1038019 | DU33: 1.1025262 | DV33: 1.0964106 | DW33: 1.1264883 | DX33: 1.1606174 | DY33: 1.1049399 | DZ33: 1.1081289 | EA33: 1.1354676 | EB33: 1.158004 | EC33: 1.1550898 | ED33: 1.1562155 | EE33: 1.1623561 | EF33: 1.1626437 | EG33: 1.2032515 | EH33: 1.2267006 | EI33: 1.2186342 | EJ33: 1.2096548 | EK33: 1.1703226 | EL33: 1.1341045 | EM33: 1.1368434 | EN33: 1.1240246 | EO33: 1.1235493 | EP33: 1.1219358 | EQ33: 1.1301526 | ER33: 1.1119433 | ES33: 1.09501 | ET33: 1.0877941 | EU33: 1.0673463 | EV33: 1.0622062 | EW33: 1.0759378 | EX33: 1.017046 | EY33: 1.0365306
A34: avg_trade_net | B34: Average net trade | C34: 0.046084937 | D34: 0.062456471 | E34: 0.024053236 | I34: 44463 | J34: 102.08527 | K34: 109.4793 | L34: -0.015861903 | M34: -0.00088783956 | N34: 19 | O34: Discovery | P34: =IF(O34="Discovery",$Q$2,0) -> 225 | Q34: =IF(O34="Holdout",$Q$2,0) -> 0 | T34: 45351 | U34: 2024 | V34: 2 | W34: 0.018870931 | X34: 0.014541387 | Y34: 0.0043295443 | AH34: 44833 | AI34: 0.12893239 | AJ34: -0.038800154 | AK34: 0.16773254 | BB34: 31 | BC34: 577 | BD34: 0.11699403 | BE34: 0.0045061004 | BF34: 0.78185856 | BG34: -0.0039774571 | BI34: -0.15660264 | CP34: T0031 | CQ34: 1.0085414 | CR34: 0.9835742 | CS34: 0.95269368 | CT34: 0.97930349 | CU34: 0.98685923 | CV34: 0.95039415 | CW34: 0.92838356 | CX34: 0.94809456 | CY34: 0.93922457 | CZ34: 0.94842303 | DA34: 0.96222071 | DB34: 0.93758202 | DC34: 0.96616284 | DD34: 0.96649131 | DE34: 0.9921155 | DF34: 1.0029564 | DG34: 0.96714841 | DH34: 0.98718787 | DI34: 1.0190538 | DJ34: 1.0203678 | DK34: 1.0183967 | DL34: 1.0131405 | DM34: 1.0167542 | DN34: 0.99802875 | DO34: 0.97437574 | DP34: 0.96386326 | DQ34: 0.95565042 | DR34: 0.95959261 | DS34: 0.95630734 | DT34: 0.95860693 | DU34: 0.94973711 | DV34: 0.93988173 | DW34: 0.95236521 | DX34: 0.95729296 | DY34: 0.94710888 | DZ34: 0.95170817 | EA34: 0.96452036 | EB34: 0.95565042 | EC34: 0.97798953 | ED34: 0.95893557 | EE34: 1.0726018 | EF34: 1.1205651 | EG34: 1.0886989 | EH34: 1.0788434 | EI34: 1.1018395 | EJ34: 1.1399473 | EK34: 1.1360051 | EL34: 1.0939551 | EM34: 1.0883704 | EN34: 1.0735872 | EO34: 1.0528908 | EP34: 1.0039421 | EQ34: 1.0180683 | ER34: 1.0716161 | ES34: 1.0364651 | ET34: 1.0650459 | EU34: 1.1024967 | EV34: 1.0909986 | EW34: 1.0696452 | EX34: 1.0752298 | EY34: 1.0726018
A35: avg_win | B35: Average win | C35: 0.15118194 | D35: 0.16864803 | E35: 0.12574598 | I35: 44466 | J35: 101.91661 | K35: 109.4584 | L35: -0.017487791 | M35: -0.0010785606 | N35: 19 | O35: Discovery | P35: =IF(O35="Discovery",$Q$2,0) -> 225 | Q35: =IF(O35="Holdout",$Q$2,0) -> 0 | T35: 45382 | U35: 2024 | V35: 3 | W35: 0.0065503435 | X35: 0.0082179985 | Y35: -0.0016676549 | AH35: 44834 | AI35: 0.14630484 | AJ35: -0.023681534 | AK35: 0.16998638 | BB35: 32 | BC35: 583 | BD35: 0.061277836 | BE35: -0.050551176 | BF35: 0.45857365 | BG35: -0.041578623 | BI35: -0.020978248 | CP35: T0032 | CQ35: 0.96173744 | CR35: 0.94888027 | CS35: 0.94212346 | CT35: 0.91629353 | CU35: 0.89965246 | CV35: 0.92050196 | CW35: 0.91003858 | CX35: 0.90629347 | CY35: 0.85891891 | CZ35: 0.86081083 | DA35: 0.82718156 | DB35: 0.83594589 | DC35: 0.85899611 | DD35: 0.86332048 | DE35: 0.8562162 | DF35: 0.88710422 | DG35: 0.90579148 | DH35: 0.90876445 | DI35: 0.91119697 | DJ35: 0.89984559 | DK35: 0.90131278 | DL35: 0.89115826 | DM35: 0.89050193 | DN35: 0.87420853 | DO35: 0.82853275 | DP35: 0.85335916 | DQ35: 0.87169881 | DR35: 0.87077222 | DS35: 0.86135136 | DT35: 0.86625486 | DU35: 0.87061782 | DV35: 0.86196909 | DW35: 0.85019305 | DX35: 0.85826252 | DY35: 0.8822008 | DZ35: 0.88710422 | EA35: 0.90934365 | EB35: 0.89826254 | EC35: 0.89602322 | ED35: 0.90274137 | EE35: 0.87277994 | EF35: 0.8858687 | EG35: 0.94297299 | EH35: 0.93714283 | EI35: 0.94961387 | EJ35: 0.92266415 | EK35: 0.93405406 | EL35: 0.93181467 | EM35: 0.9032433 | EN35: 0.84880306 | EO35: 0.85644793 | EP35: 0.84042479 | EQ35: 0.83756762 | ER35: 0.83826254 | ES35: 0.90142865 | ET35: 0.90154431 | EU35: 0.90084938 | EV35: 0.90833972 | EW35: 0.91351348 | EX35: 0.94177606 | EY35: 0.94389958
A36: avg_loss | B36: Average loss | C36: -0.10131806 | D36: -0.091662251 | E36: -0.10759551 | I36: 44467 | J36: 101.85523 | K36: 108.78496 | L36: -0.018079526 | M36: -0.0072243834 | N36: 19 | O36: Discovery | P36: =IF(O36="Discovery",$Q$2,0) -> 225 | Q36: =IF(O36="Holdout",$Q$2,0) -> 0 | T36: 45412 | U36: 2024 | V36: 4 | W36: 0.041310772 | X36: 0.036635127 | Y36: 0.0046756444 | AH36: 44837 | AI36: 0.14175324 | AJ36: -0.030280347 | AK36: 0.17203358 | BB36: 33 | BC36: 577 | BD36: 0.096551354 | BE36: -0.016136369 | BF36: 0.65024498 | BG36: -0.050638013 | BI36: -0.32969656 | CP36: T0033 | CQ36: 1.0012923 | CR36: 0.99224593 | CS36: 0.9652364 | CT36: 0.96226401 | CU36: 0.95942102 | CV36: 0.97815973 | CW36: 1.011114 | CX36: 0.99625235 | CY36: 0.98901516 | CZ36: 1.0078832 | DA36: 1.0084001 | DB36: 1.032308 | DC36: 1.0063323 | DD36: 1.0094339 | DE36: 1.0060739 | DF36: 0.9906952 | DG36: 0.97906429 | DH36: 0.98487975 | DI36: 0.9873352 | DJ36: 0.98578431 | DK36: 0.97596275 | DL36: 0.98203676 | DM36: 0.96627035 | DN36: 0.92504514 | DO36: 0.91535274 | DP36: 0.92000517 | DQ36: 0.93086067 | DR36: 0.92336517 | DS36: 0.92323602 | DT36: 0.92504514 | DU36: 0.92336517 | DV36: 0.90540187 | DW36: 0.87916766 | DX36: 0.88265698 | DY36: 0.95489799 | DZ36: 1.0209356 | EA36: 0.96833802 | EB36: 0.96200562 | EC36: 0.96058405 | ED36: 0.96549486 | EE36: 0.96717491 | EF36: 0.9612303 | EG36: 0.97828889 | EH36: 0.98319962 | EI36: 0.99806147 | EJ36: 0.98268293 | EK36: 0.98332902 | EL36: 1.0081416 | EM36: 1.0326957 | EN36: 1.0334712 | EO36: 0.99508916 | EP36: 0.98681826 | EQ36: 0.99831994 | ER36: 0.99496001 | ES36: 0.99689844 | ET36: 0.98953218 | EU36: 0.9906952 | EV36: 0.98164889 | EW36: 0.9642026 | EX36: 1.0084001 | EY36: 1.0036185
A37: payoff | B37: Payoff ratio (avg win / |avg loss|) | C37: 1.4921519 | D37: 1.8398853 | E37: 1.1686917 | I37: 44468 | J37: 102.60047 | K37: 108.72263 | L37: -0.010895171 | M37: -0.0077932583 | N37: 19 | O37: Discovery | P37: =IF(O37="Discovery",$Q$2,0) -> 225 | Q37: =IF(O37="Holdout",$Q$2,0) -> 0 | T37: 45443 | U37: 2024 | V37: 5 | W37: 0.04875291 | X37: 0.0050530547 | Y37: 0.043699855 | AH37: 44838 | AI37: 0.15024455 | AJ37: -0.0080301187 | AK37: 0.15827467 | BB37: 34 | BC37: 576 | BD37: 0.082012987 | BE37: -0.030674736 | BF37: 0.56858433 | BG37: -0.038080423 | BI37: -0.094793767 | CP37: T0034 | CQ37: 0.99800003 | CR37: 0.98750013 | CS37: 0.94749996 | CT37: 0.9610002 | CU37: 0.99050017 | CV37: 0.97672189 | CW37: 0.98896928 | CX37: 0.89915556 | CY37: 0.90170743 | CZ37: 0.90170743 | DA37: 0.9180368 | DB37: 0.93181508 | DC37: 0.93589745 | DD37: 0.92058857 | DE37: 0.98590722 | DF37: 1.0032576 | DG37: 1.0185668 | DH37: 1.0098917 | DI37: 1.0185668 | DJ37: 1.0399995 | DK37: 1.0236699 | DL37: 1.0287731 | DM37: 1.0073401 | DN37: 0.95324789 | DO37: 1.0047886 | DP37: 1.0532674 | DQ37: 1.0593911 | DR37: 1.0287731 | DS37: 1.0297934 | DT37: 1.0211185 | DU37: 1.0068299 | DV37: 0.99611342 | DW37: 1.0308141 | DX37: 1.0527572 | DY37: 1.0420407 | DZ37: 1.0558191 | EA37: 1.0706177 | EB37: 1.1298131 | EC37: 1.1497149 | ED37: 1.1068492 | EE37: 1.1359369 | EF37: 1.1604315 | EG37: 1.1589004 | EH37: 1.1252204 | EI37: 1.0930714 | EJ37: 1.114504 | EK37: 1.129303 | EL37: 1.1048083 | EM37: 1.0328554 | EN37: 1.0946022 | EO37: 1.084396 | EP37: 1.1104216 | EQ37: 1.1109318 | ER37: 1.1578798 | ES37: 1.1844158 | ET37: 1.1920702 | EU37: 1.2027866 | EV37: 1.2145234 | EW37: 1.2165647 | EX37: 1.2726981 | EY37: 1.2849454
A38: best_trade | B38: Best trade | C38: 0.67123276 | D38: 0.67123276 | E38: 0.66616176 | I38: 44469 | J38: 102.59658 | K38: 108.47545 | L38: -0.010932711 | M38: -0.010049028 | N38: 19 | O38: Discovery | P38: =IF(O38="Discovery",$Q$2,0) -> 225 | Q38: =IF(O38="Holdout",$Q$2,0) -> 0 | T38: 45473 | U38: 2024 | V38: 6 | W38: 0.086965371 | X38: 0.069012903 | Y38: 0.017952468 | AH38: 44840 | AI38: 0.16467258 | AJ38: 2.6573394e-05 | AK38: 0.164646 | BB38: 35 | BC38: 582 | BD38: 0.072255572 | BE38: -0.039094285 | BF38: 0.50573377 | BG38: -0.059681169 | BI38: -0.13293287 | CP38: T0035 | CQ38: 0.96379341 | CR38: 0.94946267 | CS38: 0.95196895 | CT38: 0.93857142 | CU38: 0.96128719 | CV38: 0.96803265 | CW38: 1.0056922 | CX38: 0.97748414 | CY38: 0.94259736 | CZ38: 0.95718135 | DA38: 0.99874682 | DB38: 0.98337643 | DC38: 0.98525598 | DD38: 0.95884767 | DE38: 0.96897906 | DF38: 0.98925531 | DG38: 0.98533601 | DH38: 0.98441621 | DI38: 0.9743914 | DJ38: 0.99218805 | DK38: 1.0491641 | DL38: 1.0406857 | DM38: 1.0301943 | DN38: 0.97239167 | DO38: 0.9993867 | DP38: 0.99997335 | DQ38: 1.0004265 | DR38: 1.0003999 | DS38: 1.0118245 | DT38: 1.0000933 | DU38: 0.9961607 | DV38: 0.98304315 | DW38: 0.99018845 | DX38: 1.0123842 | DY38: 1.0213693 | DZ38: 1.0071587 | EA38: 0.99453433 | EB38: 0.97688422 | EC38: 0.96657955 | ED38: 0.9975471 | EE38: 1.003826 | EF38: 1.0045592 | EG38: 0.99536076 | EH38: 1.0150638 | EI38: 1.0016662 | EJ38: 0.97973705 | EK38: 1.00016 | EL38: 1.0054923 | EM38: 0.953462 | EN38: 0.99460096 | EO38: 0.99545413 | EP38: 1.0190764 | EQ38: 1.029381 | ER38: 1.0215825 | ES38: 1.0490309 | ET38: 1.0398192 | EU38: 1.0894633 | EV38: 1.0899832 | EW38: 1.0565759 | EX38: 1.0469645 | EY38: 1.0590423
A39: worst_trade | B39: Worst trade | C39: -0.58684997 | D39: -0.31865708 | E39: -0.58684997 | I39: 44470 | J39: 102.8913 | K39: 108.19656 | L39: -0.008091494 | M39: -0.012594169 | N39: 19 | O39: Discovery | P39: =IF(O39="Discovery",$Q$2,0) -> 225 | Q39: =IF(O39="Holdout",$Q$2,0) -> 0 | T39: 45504 | U39: 2024 | V39: 7 | W39: 0.060782482 | X39: 0.043045785 | Y39: 0.017736697 | AH39: 44841 | AI39: 0.1684047 | AJ39: 0.0015152575 | AK39: 0.16688945 | BB39: 36 | BC39: 581 | BD39: 0.12920118 | BE39: 0.016513457 | BF39: 0.86844704 | BG39: -0.0072273134 | BI39: -0.1304734 | CP39: T0036 | CQ39: 0.98588457 | CR39: 0.98745302 | CS39: 0.96800497 | CT39: 0.95336807 | CU39: 0.95434359 | CV39: 0.99825508 | CW39: 1.0089891 | CX39: 0.95694582 | CY39: 0.93742963 | CZ39: 0.92441885 | DA39: 0.9253945 | DB39: 0.93677915 | DC39: 0.94913951 | DD39: 0.93255066 | DE39: 0.94913951 | DF39: 0.96540294 | DG39: 0.95857208 | DH39: 0.95987323 | DI39: 0.94946456 | DJ39: 0.95564468 | DK39: 0.93645378 | DL39: 0.94556144 | DM39: 0.90685402 | DN39: 0.87172495 | DO39: 0.88506116 | DP39: 0.88994019 | DQ39: 0.91401005 | DR39: 0.90099921 | DS39: 0.89351807 | DT39: 0.90750483 | DU39: 0.90360157 | DV39: 0.91401005 | DW39: 0.92637041 | DX39: 0.93059891 | DY39: 0.96149955 | DZ39: 0.97808834 | EA39: 0.98101581 | EB39: 1.0216745 | EC39: 1.0301318 | ED39: 1.0470455 | EE39: 1.0730674 | EF39: 1.0665619 | EG39: 1.0476965 | EH39: 1.0789226 | EI39: 1.0659114 | EJ39: 1.1075461 | EK39: 1.0854279 | EL39: 1.0646106 | EM39: 1.0779466 | EN39: 1.0743683 | EO39: 1.0779466 | EP39: 1.0981134 | EQ39: 1.122834 | ER39: 1.1120998 | ES39: 1.1143769 | ET39: 1.0896561 | EU39: 1.1033176 | EV39: 1.1195812 | EW39: 1.0860785 | EX39: 1.0665619 | EY39: 1.1000648
A40: avg_holding_sessions | B40: Average holding period (sessions) | C40: 60 | D40: 60 | E40: 60 | I40: 44473 | J40: 103.20921 | K40: 109.40147 | L40: -0.0050266755 | M40: -0.0015981112 | N40: 19 | O40: Discovery | P40: =IF(O40="Discovery",$Q$2,0) -> 225 | Q40: =IF(O40="Holdout",$Q$2,0) -> 0 | T40: 45535 | U40: 2024 | V40: 8 | W40: -0.0096241418 | X40: 0.0086588641 | Y40: -0.018283006 | AH40: 44844 | AI40: 0.14581957 | AJ40: -0.015117432 | AK40: 0.160937 | BB40: 37 | BC40: 569 | BD40: 0.071949901 | BE40: -0.040737822 | BF40: 0.52125683 | BG40: -0.054193604 | BI40: -0.072487751 | CP40: T0037 | CQ40: 0.99898325 | CR40: 1.0171712 | CS40: 1.021464 | CT40: 1.0100542 | CU40: 0.94215993 | CV40: 0.94927703 | CW40: 0.93255764 | CX40: 0.96000904 | CY40: 0.97627651 | CZ40: 0.95944422 | DA40: 0.95198826 | DB40: 0.99977411 | DC40: 1.0335518 | DD40: 1.0294848 | DE40: 1.0282423 | DF40: 1.0353593 | DG40: 1.043154 | DH40: 1.0355852 | DI40: 1.0178491 | DJ40: 1.0170583 | DK40: 0.97853596 | DL40: 1.0064393 | DM40: 1.0468821 | DN40: 1.0422504 | DO40: 1.0368278 | DP40: 1.0230456 | DQ40: 1.0351334 | DR40: 1.0263217 | DS40: 1.0159285 | DT40: 1.0744465 | DU40: 1.0800948 | DV40: 1.0756891 | DW40: 1.0739946 | DX40: 1.0824673 | DY40: 1.1150023 | DZ40: 1.1136466 | EA40: 1.0988478 | EB40: 1.1250565 | EC40: 1.1466335 | ED40: 1.1440352 | EE40: 1.1431315 | EF40: 1.1206507 | EG40: 1.1405332 | EH40: 1.1373701 | EI40: 1.144826 | EJ40: 1.0808857 | EK40: 1.0974922 | EL40: 1.105174 | EM40: 1.1078853 | EN40: 1.104948 | EO40: 1.1545414 | EP40: 1.1612065 | EQ40: 1.1582693 | ER40: 1.1865115 | ES40: 1.1807501 | ET40: 1.1902396 | EU40: 1.2252597 | EV40: 1.2364437 | EW40: 1.2261635 | EX40: 1.1777 | EY40: 1.2061681
A41: turnover_one_way | B41: Annual one-way turnover | C41: 3.8142463 | D41: 3.7094262 | E41: 3.8571927 | I41: 44474 | J41: 102.98874 | K41: 110.11455 | L41: -0.0071520771 | M41: 0 | N41: 19 | O41: Discovery | P41: =IF(O41="Discovery",$Q$2,0) -> 225 | Q41: =IF(O41="Holdout",$Q$2,0) -> 0 | T41: 45565 | U41: 2024 | V41: 9 | W41: 0.0014984637 | X41: 0.021515049 | Y41: -0.020016585 | AH41: 44845 | AI41: 0.12876511 | AJ41: -0.036531175 | AK41: 0.16529628 | BB41: 38 | BC41: 587 | BD41: 0.097107587 | BE41: -0.015380347 | BF41: 0.66788536 | BG41: -0.077976536 | BI41: -0.17696674 | CP41: T0038 | CQ41: 1.0140381 | CR41: 1.0258232 | CS41: 1.0263433 | CT41: 0.97920265 | CU41: 1.0181975 | CV41: 1.0126516 | CW41: 0.9925478 | CX41: 0.9261699 | CY41: 0.96135176 | CZ41: 0.94419395 | DA41: 0.95580598 | DB41: 0.96117838 | DC41: 0.9925478 | DD41: 0.99670711 | DE41: 0.99878677 | DF41: 0.98994812 | DG41: 0.97989616 | DH41: 0.96533803 | DI41: 0.9870018 | DJ41: 0.99913352 | DK41: 0.96412482 | DL41: 0.89428079 | DM41: 0.96100523 | DN41: 0.94783367 | DO41: 0.95476604 | DP41: 0.94523411 | DQ41: 0.91958407 | DR41: 0.89376082 | DS41: 0.92894285 | DT41: 0.84800687 | DU41: 0.89774698 | DV41: 0.91213173 | DW41: 0.90987865 | DX41: 0.91750447 | DY41: 0.89566727 | DZ41: 0.8693241 | EA41: 0.90190651 | EB41: 0.94679385 | EC41: 0.94748692 | ED41: 0.97746975 | EE41: 0.99566729 | EF41: 0.96152514 | EG41: 0.98110915 | EH41: 0.98908145 | EI41: 1.0840555 | EJ41: 1.0556326 | EK41: 1.0611786 | EL41: 1.0850952 | EM41: 1.1097053 | EN41: 1.1086655 | EO41: 1.1445407 | EP41: 1.1254768 | EQ41: 1.1440207 | ER41: 1.1542461 | ES41: 1.1564992 | ET41: 1.1232235 | EU41: 1.1532063 | EV41: 1.1289429 | EW41: 1.1384749 | EX41: 1.1176777 | EY41: 1.0994801
A42: median_adv20_cr | B42: Median 20-day ADV of traded names (INR Cr) | C42: 48.739937 | D42: 33.072791 | E42: 80.634739 | I42: 44475 | J42: 102.18689 | K42: 109.06565 | L42: -0.014882223 | M42: -0.0095254612 | N42: 19 | O42: Discovery | P42: =IF(O42="Discovery",$Q$2,0) -> 225 | Q42: =IF(O42="Holdout",$Q$2,0) -> 0 | T42: 45596 | U42: 2024 | V42: 10 | W42: -0.041877595 | X42: -0.064171465 | Y42: 0.02229387 | AH42: 44846 | AI42: 0.14360171 | AJ42: -0.020126135 | AK42: 0.16372784 | BB42: 39 | BC42: 583 | BD42: 0.10814182 | BE42: -0.0043461109 | BF42: 0.72428288 | BG42: -0.065840124 | BI42: -0.12059348 | CP42: T0039 | CQ42: 1.0251594 | CR42: 1.0305526 | CS42: 1.0205898 | CT42: 0.99205634 | CU42: 0.96902231 | CV42: 0.94883103 | CW42: 0.92284825 | CX42: 0.91506377 | CY42: 0.89192345 | CZ42: 0.89596181 | DA42: 0.92252921 | DB42: 0.94157818 | DC42: 0.94957495 | DD42: 0.92377797 | DE42: 0.9251328 | DF42: 0.91126473 | DG42: 0.91248669 | DH42: 0.92311377 | DI42: 0.94027628 | DJ42: 0.91463866 | DK42: 0.89383633 | DL42: 0.92361845 | DM42: 0.92098829 | DN42: 0.9164719 | DO42: 0.90698728 | DP42: 0.91960674 | DQ42: 0.9215462 | DR42: 0.92606274 | DS42: 0.89168443 | DT42: 0.90042505 | DU42: 0.91158332 | DV42: 0.90478215 | DW42: 0.91437292 | DX42: 0.91567483 | DY42: 0.9244686 | DZ42: 0.94484589 | EA42: 0.96352282 | EB42: 0.97019134 | EC42: 0.96811901 | ED42: 1.0046227 | EE42: 0.97731147 | EF42: 1.003932 | EG42: 0.98544104 | EH42: 0.98461754 | EI42: 1.0028694 | EJ42: 0.99489894 | EK42: 1.0024974 | EL42: 0.99710414 | EM42: 0.99569616 | EN42: 1.0021253 | EO42: 1.0116631 | EP42: 1.013204 | EQ42: 1.0114505 | ER42: 1.0005049 | ES42: 0.98889484 | ET42: 0.97175869 | EU42: 0.96227414 | EV42: 0.96418695 | EW42: 0.93865578 | EX42: 0.92585015 | EY42: 0.92909136
A43: p10_adv20_cr | B43: 10th-pct 20-day ADV (INR Cr) | C43: 5.4258696 | D43: 4.1569299 | E43: 8.144975 | I43: 44476 | J43: 102.6081 | K43: 110.18697 | L43: -0.010821637 | M43: 0 | N43: 19 | O43: Discovery | P43: =IF(O43="Discovery",$Q$2,0) -> 225 | Q43: =IF(O43="Holdout",$Q$2,0) -> 0 | T43: 45626 | U43: 2024 | V43: 11 | W43: 0.010715634 | X43: -0.00010357282 | Y43: 0.010819207 | AH43: 44847 | AI43: 0.1331825 | AJ43: -0.036615076 | AK43: 0.16979757 | BB43: 40 | BC43: 582 | BD43: 0.095183346 | BE43: -0.017304588 | BF43: 0.64720433 | BG43: -0.07643576 | BI43: -0.026186611 | CP43: T0040 | CQ43: 1.0252941 | CR43: 1.0181174 | CS43: 1.0125882 | CT43: 0.96299995 | CU43: 0.96070587 | CV43: 0.94582337 | CW43: 0.96447053 | CX43: 0.95411763 | CY43: 0.96923527 | CZ43: 1.0061176 | DA43: 1.0018235 | DB43: 0.98911745 | DC43: 0.96994132 | DD43: 0.95341179 | DE43: 0.95682342 | DF43: 0.94852926 | DG43: 0.91511759 | DH43: 0.8831175 | DI43: 0.91652938 | DJ43: 0.9186469 | DK43: 0.91388206 | DL43: 0.89517611 | DM43: 0.86976456 | DN43: 0.84958825 | DO43: 0.85682339 | DP43: 0.8178234 | DQ43: 0.86947043 | DR43: 0.86423535 | DS43: 0.86194111 | DT43: 0.88958806 | DU43: 0.88776467 | DV43: 0.88217652 | DW43: 0.8898233 | DX43: 0.9087646 | DY43: 0.9191175 | DZ43: 0.88811759 | EA43: 0.89558813 | EB43: 0.88188248 | EC43: 0.89070581 | ED43: 0.91494103 | EE43: 0.91799995 | EF43: 0.91017649 | EG43: 0.92423527 | EH43: 0.91176443 | EI43: 0.90223515 | EJ43: 0.89505864 | EK43: 0.88788256 | EL43: 0.87105878 | EM43: 0.86988229 | EN43: 0.88429393 | EO43: 0.90211758 | EP43: 0.91117637 | EQ43: 0.92494111 | ER43: 0.92405881 | ES43: 0.94111772 | ET43: 0.95317633 | EU43: 0.93741185 | EV43: 0.9407057 | EW43: 0.92894123 | EX43: 0.92370568 | EY43: 0.93941169
A44: capacity_1pct_90fit_cr | B44: Capacity @1% ADV, 90% of trades fit (INR Cr) | C44: 1.6277609 | D44: 1.247079 | E44: 2.4434925 | I44: 44477 | J44: 103.04921 | K44: 110.72781 | L44: -0.0065691788 | M44: 0 | N44: 19 | O44: Discovery | P44: =IF(O44="Discovery",$Q$2,0) -> 225 | Q44: =IF(O44="Holdout",$Q$2,0) -> 0 | T44: 45657 | U44: 2024 | V44: 12 | W44: -0.012120748 | X44: -0.013734738 | Y44: 0.0016139898 | AH44: 44848 | AI44: 0.12629874 | AJ44: -0.035801682 | AK44: 0.16210042 | BI44: -0.0047317303 | CP44: T0041 | CQ44: 0.95753992 | CR44: 0.93626342 | CS44: 0.95468088 | CT44: 0.92741356 | CU44: 0.95520624 | CV44: 1.0116158 | CW44: 0.99266627 | CX44: 0.99501335 | CY44: 0.96992691 | CZ44: 0.98734042 | DA44: 1.0159641 | DB44: 1.0127129 | DC44: 1.019641 | DD44: 1.0111171 | DE44: 0.9837235 | DF44: 0.91906254 | DG44: 0.94561832 | DH44: 0.93065158 | DI44: 0.92303861 | DJ44: 0.92892291 | DK44: 0.89534576 | DL44: 0.87245346 | DM44: 0.87815821 | DN44: 0.80772605 | DO44: 0.86432847 | DP44: 0.85529921 | DQ44: 0.87297875 | DR44: 0.88557844 | DS44: 0.8874468 | DT44: 0.87164232 | DU44: 0.87402933 | DV44: 0.92992029 | DW44: 0.93218759 | DX44: 0.94696809 | DY44: 0.95341083 | DZ44: 0.93051197 | EA44: 0.95922867 | EB44: 0.98826465 | EC44: 0.98454127 | ED44: 0.99901596 | EE44: 1.0228724 | EF44: 1.0115558 | EG44: 1.1221011 | EH44: 1.201529 | EI44: 1.1373471 | EJ44: 1.1963829 | EK44: 1.175552 | EL44: 1.1852127 | EM44: 1.1980984 | EN44: 1.1806316 | EO44: 1.1826664 | EP44: 1.1632711 | EQ44: 1.1549468 | ER44: 1.1583977 | ES44: 1.1182513 | ET44: 1.1148669 | EU44: 1.0393551 | EV44: 1.0230253 | EW44: 1.0382581 | EX44: 1.051044 | EY44: 1.1114362
A45: capacity_5pct_90fit_cr | B45: Capacity @5% ADV, 90% of trades fit (INR Cr) | C45: 8.1388043 | D45: 6.2353948 | E45: 12.217462 | I45: 44480 | J45: 104.07158 | K45: 111.18037 | L45: 0 | M45: 0 | N45: 19 | O45: Discovery | P45: =IF(O45="Discovery",$Q$2,0) -> 225 | Q45: =IF(O45="Holdout",$Q$2,0) -> 0 | T45: 45688 | U45: 2025 | V45: 1 | W45: -0.080404479 | X45: -0.035507745 | Y45: -0.044896734 | AH45: 44851 | AI45: 0.11923505 | AJ45: -0.033824864 | AK45: 0.15305992 | BI45: -0.10385942 | CP45: T0042 | CQ45: 1.0287946 | CR45: 1.0023437 | CS45: 0.99575891 | CT45: 1.0168527 | CU45: 0.99676342 | CV45: 1.0558658 | CW45: 1.0590119 | CX45: 1.1463173 | CY45: 1.1240695 | CZ45: 1.1254177 | DA45: 1.0801359 | DB45: 1.0560906 | DC45: 1.090361 | DD45: 1.0722706 | DE45: 1.0684503 | DF45: 1.0323821 | DG45: 1.045416 | DH45: 1.0254157 | DI45: 1.0367642 | DJ45: 1.026764 | DK45: 1.0318203 | DL45: 1.0240672 | DM45: 1.0213705 | DN45: 0.95676237 | DO45: 0.98541467 | DP45: 1.0062017 | DQ45: 0.95440285 | DR45: 0.93811033 | DS45: 0.91339076 | DT45: 0.85833337 | DU45: 0.84619833 | DV45: 0.83698464 | DW45: 0.87046842 | DX45: 0.84945672 | DY45: 0.85215348 | DZ45: 0.87574944 | EA45: 0.88417662 | EB45: 0.90058158 | EC45: 0.8819294 | ED45: 0.87743489 | EE45: 0.90507595 | EF45: 0.91170531 | EG45: 0.90597475 | EH45: 0.89687357 | EI45: 0.9183346 | EJ45: 0.92575061 | EK45: 0.90721087 | EL45: 0.93417773 | EM45: 0.92080663 | EN45: 0.92080663 | EO45: 0.93136874 | EP45: 0.91586272 | EQ45: 0.91855941 | ER45: 0.93035728 | ES45: 0.93496423 | ET45: 0.93417773 | EU45: 0.90597475 | EV45: 0.85260281 | EW45: 0.87709771 | EX45: 0.87428865 | EY45: 0.87226631
A46: capacity_1pct_50fit_cr | B46: Capacity @1% ADV, only 50% of trades fit (INR Cr) | C46: 14.621981 | D46: 9.9218373 | E46: 24.190422 | I46: 44481 | J46: 103.51273 | K46: 111.5688 | L46: -0.0053698915 | M46: 0 | N46: 20 | O46: Discovery | P46: =IF(O46="Discovery",$Q$2,0) -> 225 | Q46: =IF(O46="Holdout",$Q$2,0) -> 0 | T46: 45716 | U46: 2025 | V46: 2 | W46: -0.11975303 | X46: -0.07877336 | Y46: -0.040979675 | AH46: 44852 | AI46: 0.13612177 | AJ46: -0.027474018 | AK46: 0.16359579 | BI46: 0.45263959 | CP46: T0043 | CQ46: 0.94959129 | CR46: 0.96778355 | CS46: 0.95434892 | CT46: 1.006023 | CU46: 1.032564 | CV46: 1.0552328 | CW46: 1.0410237 | CX46: 1.0190823 | CY46: 1.0081935 | CZ46: 0.9932804 | DA46: 0.97701778 | DB46: 1.024679 | DC46: 1.0355911 | DD46: 0.98472686 | DE46: 0.92550822 | DF46: 0.97571531 | DG46: 0.94351899 | DH46: 0.91828036 | DI46: 0.90544394 | DJ46: 0.90051596 | DK46: 0.92154225 | DL46: 0.92920407 | DM46: 0.88613088 | DN46: 0.90902267 | DO46: 0.92407667 | DP46: 0.91187393 | DQ46: 0.96046207 | DR46: 0.95561598 | DS46: 0.97258256 | DT46: 0.98470311 | DU46: 0.99475873 | DV46: 1.0042745 | DW46: 1.0228368 | DX46: 1.050164 | DY46: 1.0153862 | DZ46: 1.0392168 | EA46: 1.0524754 | EB46: 1.0397446 | EC46: 1.0658164 | ED46: 1.0538483 | EE46: 1.088802 | EF46: 1.0972969 | EG46: 1.0868544 | EH46: 1.1165516 | EI46: 1.1234038 | EJ46: 1.1182645 | EK46: 1.1082795 | EL46: 1.1244129 | EM46: 1.1535588 | EN46: 1.1439373 | EO46: 1.1043253 | EP46: 1.1054987 | EQ46: 1.059621 | ER46: 1.0284924 | ES46: 1.0161018 | ET46: 0.98920903 | EU46: 0.97951709 | EV46: 0.93532901 | EW46: 0.94145394 | EX46: 0.94510296 | EY46: 0.94039797
I47: 44482 | J47: 104.67958 | K47: 112.64615 | L47: 0 | M47: 0 | N47: 20 | O47: Discovery | P47: =IF(O47="Discovery",$Q$2,0) -> 225 | Q47: =IF(O47="Holdout",$Q$2,0) -> 0 | T47: 45747 | U47: 2025 | V47: 3 | W47: 0.082520934 | X47: 0.073369415 | Y47: 0.0091515191 | AH47: 44853 | AI47: 0.12510652 | AJ47: -0.036004453 | AK47: 0.16111098 | BI47: -0.010458305 | CP47: T0044 | CQ47: 0.97678404 | CR47: 0.99501884 | CS47: 0.98138016 | CT47: 0.97633509 | CU47: 0.97214492 | CV47: 0.98578371 | CW47: 0.99529683 | CX47: 0.98257711 | CY47: 0.98619001 | CZ47: 0.96523988 | DA47: 0.96812606 | DB47: 0.97381244 | DC47: 0.97616401 | DD47: 0.96541107 | DE47: 0.95281965 | DF47: 0.97913551 | DG47: 0.97759641 | DH47: 0.9865962 | DI47: 0.98873393 | DJ47: 0.98114505 | DK47: 0.9705203 | DL47: 0.96643705 | DM47: 0.92838526 | DN47: 0.92808566 | DO47: 0.92868447 | DP47: 0.9188507 | DQ47: 0.89400996 | DR47: 0.86344007 | DS47: 0.83113847 | DT47: 0.83329764 | DU47: 0.85420506 | DV47: 0.89869162 | DW47: 0.89546363 | DX47: 0.88045659 | DY47: 0.8714352 | DZ47: 0.88595051 | EA47: 0.89873444 | EB47: 0.87699338 | EC47: 0.85232371 | ED47: 0.84593189 | EE47: 0.84052322 | EF47: 0.83500781 | EG47: 0.84445678 | EH47: 0.84956595 | EI47: 0.86190092 | EJ47: 0.87590307 | EK47: 0.88851593 | EL47: 0.91002182 | EM47: 0.9148745 | EN47: 0.91583644 | EO47: 0.92556323 | EP47: 0.93336601 | EQ47: 0.92481501 | ER47: 0.91164639 | ES47: 0.9201548 | ET47: 0.93105732 | EU47: 0.90343748 | EV47: 0.92562727 | EW47: 0.93973645 | EX47: 0.90938047 | EY47: 0.89817845
I48: 44483 | J48: 105.02063 | K48: 113.63956 | L48: 0 | M48: 0 | N48: 20 | O48: Discovery | P48: =IF(O48="Discovery",$Q$2,0) -> 225 | Q48: =IF(O48="Holdout",$Q$2,0) -> 0 | T48: 45777 | U48: 2025 | V48: 4 | W48: 0.020443284 | X48: 0.032357758 | Y48: -0.011914474 | AH48: 44854 | AI48: 0.1178959 | AJ48: -0.041672876 | AK48: 0.15956878 | BI48: -0.002231542 | CP48: T0045 | CQ48: 1.0100871 | CR48: 0.99512659 | CS48: 0.99416898 | CT48: 1.0157689 | CU48: 1.0124066 | CV48: 1.0144708 | CW48: 1.0013619 | CX48: 0.99223242 | CY48: 0.98618886 | CZ48: 1.0027665 | DA48: 1.0144495 | DB48: 1.0134067 | DC48: 1.0114277 | DD48: 0.99531816 | DE48: 1.029112 | DF48: 1.0269837 | DG48: 1.0399862 | DH48: 1.0318572 | DI48: 1.0214296 | DJ48: 1.0167904 | DK48: 1.0104275 | DL48: 0.96007727 | DM48: 0.97207962 | DN48: 1.004256 | DO48: 1.020855 | DP48: 1.0122363 | DQ48: 0.9897854 | DR48: 0.95318255 | DS48: 0.95145867 | DT48: 1.0019366 | DU48: 1.0181736 | DV48: 1.0211103 | DW48: 1.0294949 | DX48: 1.005916 | DY48: 1.0228981 | DZ48: 1.0562448 | EA48: 1.0501585 | EB48: 1.0772914 | EC48: 1.0807174 | ED48: 1.0975079 | EE48: 1.1048285 | EF48: 1.115937 | EG48: 1.1161923 | EH48: 1.1376434 | EI48: 1.121385 | EJ48: 1.1303652 | EK48: 1.1337066 | EL48: 1.1176821 | EM48: 1.1147027 | EN48: 1.0950395 | EO48: 1.1132557 | EP48: 1.1109363 | EQ48: 1.0900173 | ER48: 1.0860163 | ES48: 1.0826965 | ET48: 1.1239598 | EU48: 1.1570086 | EV48: 1.184099 | EW48: 1.1741823 | EX48: 1.1470281 | EY48: 1.1813539
A49: Source: corrected/*.csv (see block titles) · Built from CORRECTED_REPORT.md (revision 2) outputs · Workbook generated 2026-09-23 | I49: 44487 | J49: 105.34134 | K49: 114.48199 | L49: 0 | M49: 0 | N49: 21 | O49: Discovery | P49: =IF(O49="Discovery",$Q$2,0) -> 225 | Q49: =IF(O49="Holdout",$Q$2,0) -> 0 | T49: 45808 | U49: 2025 | V49: 5 | W49: 0.035162618 | X49: 0.035038504 | Y49: 0.00012411407 | AH49: 44855 | AI49: 0.11819155 | AJ49: -0.050676218 | AK49: 0.16886777 | BI49: -0.022177621 | CP49: T0046 | CQ49: 1.0176 | CR49: 1.0588776 | CS49: 1.0843666 | CT49: 1.0383221 | CU49: 1.029122 | CV49: 0.99919996 | CW49: 1.0084112 | CX49: 1.0146111 | CY49: 1.0174335 | CZ49: 1.0014444 | DA49: 0.99743328 | DB49: 0.98325546 | DC49: 0.96395534 | DD49: 0.97065559 | DE49: 0.96377783 | DF49: 0.95765552 | DG49: 0.94534452 | DH49: 0.92137784 | DI49: 0.92716673 | DJ49: 0.93802228 | DK49: 0.94147763 | DL49: 0.93556664 | DM49: 0.96097774 | DN49: 0.96156667 | DO49: 0.97112214 | DP49: 0.96541103 | DQ49: 0.95037777 | DR49: 0.9621667 | DS49: 0.97443327 | DT49: 0.97758884 | DU49: 0.99439998 | DV49: 0.98086657 | DW49: 0.99872221 | DX49: 1.0230333 | DY49: 1.0477555 | DZ49: 1.0602777 | EA49: 1.0597222 | EB49: 1.0617778 | EC49: 1.0576777 | ED49: 1.0660665 | EE49: 1.0546889 | EF49: 1.0383221 | EG49: 1.0703444 | EH49: 1.104989 | EI49: 1.0794444 | EJ49: 1.0702666 | EK49: 1.0689444 | EL49: 1.0670224 | EM49: 1.0401222 | EN49: 1.0463333 | EO49: 1.0591222 | EP49: 1.0752556 | EQ49: 1.0577555 | ER49: 0.99018893 | ES49: 1.0019776 | ET49: 0.98831108 | EU49: 0.99925544 | EV49: 0.98134432 | EW49: 0.94968899 | EX49: 0.92474444 | EY49: 0.93889995
I50: 44488 | J50: 103.72228 | K50: 113.5574 | L50: -0.015369655 | M50: -0.0080762173 | N50: 21 | O50: Discovery | P50: =IF(O50="Discovery",$Q$2,0) -> 225 | Q50: =IF(O50="Holdout",$Q$2,0) -> 0 | T50: 45838 | U50: 2025 | V50: 6 | W50: 0.034072807 | X50: 0.035753521 | Y50: -0.0016807137 | AH50: 44858 | AI50: 0.14535941 | AJ50: -0.035480729 | AK50: 0.18084014 | BI50: -0.062507475 | CP50: T0047 | CQ50: 1.004749 | CR50: 1.0070293 | CS50: 1.023933 | CT50: 1.026569 | CU50: 1.022817 | CV50: 1.0211819 | CW50: 1.0274286 | CX50: 1.0611758 | CY50: 1.0831849 | CZ50: 1.0834994 | DA50: 1.0382233 | DB50: 0.98334723 | DC50: 1.0454339 | DD50: 1.0323962 | DE50: 1.0198825 | DF50: 0.99898433 | DG50: 0.99581904 | DH50: 0.99588194 | DI50: 1.0046227 | DJ50: 0.95222002 | DK50: 1.0165705 | DL50: 0.99927755 | DM50: 0.98498224 | DN50: 0.98255069 | DO50: 0.93668786 | DP50: 0.90271007 | DQ50: 0.91799063 | DR50: 0.93226497 | DS50: 0.95779567 | DT50: 0.94356305 | DU50: 0.98743475 | DV50: 1.0145165 | DW50: 1.0351421 | DX50: 1.0850295 | DY50: 1.0922609 | DZ50: 1.1027416 | EA50: 1.0879638 | EB50: 1.0933719 | EC50: 1.0960758 | ED50: 1.0923867 | EE50: 1.0988847 | EF50: 1.134351 | EG50: 1.1232415 | EH50: 1.0991362 | EI50: 1.105194 | EJ50: 1.1358809 | EK50: 1.1254842 | EL50: 1.1271193 | EM50: 1.1518533 | EN50: 1.1314372 | EO50: 1.1049635 | EP50: 1.0946086 | EQ50: 1.0965791 | ER50: 1.0601906 | ES50: 1.065934 | ET50: 1.067925 | EU50: 1.0435896 | EV50: 1.0206999 | EW50: 1.0541537 | EX50: 1.0411788 | EY50: 1.0530637
I51: 44489 | J51: 102.39727 | K51: 112.19395 | L51: -0.027947937 | M51: -0.019985963 | N51: 21 | O51: Discovery | P51: =IF(O51="Discovery",$Q$2,0) -> 225 | Q51: =IF(O51="Holdout",$Q$2,0) -> 0 | T51: 45869 | U51: 2025 | V51: 7 | W51: 0.0014951721 | X51: -0.029734685 | Y51: 0.031229857 | AH51: 44859 | AI51: 0.15704513 | AJ51: -0.026370302 | AK51: 0.18341543 | BI51: -0.079782114 | CP51: T0048 | CQ51: 0.99158785 | CR51: 0.9989485 | CS51: 1.0042062 | CT51: 1.0057834 | CU51: 0.99947434 | CV51: 0.98895905 | CW51: 0.98633024 | CX51: 0.97739215 | CY51: 0.98107264 | CZ51: 0.97686647 | DA51: 0.97003158 | DB51: 0.95636165 | DC51: 0.97266039 | DD51: 0.97739215 | DE51: 0.98002095 | DF51: 0.97844383 | DG51: 0.9526814 | DH51: 0.94111467 | DI51: 0.93796002 | DJ51: 0.92481593 | DK51: 0.94321763 | DL51: 0.94164043 | DM51: 0.94216611 | DN51: 0.94584643 | DO51: 0.92902209 | DP51: 0.90378542 | DQ51: 0.90168246 | DR51: 0.91114615 | DS51: 0.99421665 | DT51: 0.96635126 | DU51: 0.96529974 | DV51: 0.96792854 | DW51: 0.98843329 | DX51: 0.98370144 | DY51: 0.98107264 | DZ51: 0.99158785 | EA51: 0.97055734 | EB51: 0.99106209 | EC51: 0.97266039 | ED51: 0.9474238 | EE51: 0.96635126 | EF51: 0.95110404 | EG51: 0.94216611 | EH51: 0.96687694 | EI51: 0.97686647 | EJ51: 0.97634071 | EK51: 0.97213455 | EL51: 0.96792854 | EM51: 0.97949528 | EN51: 0.99737122 | EO51: 0.97844383 | EP51: 0.98264984 | EQ51: 0.99001057 | ER51: 0.97739215 | ES51: 0.97528919 | ET51: 0.99053625 | EU51: 0.99526817 | EV51: 0.98527864 | EW51: 0.98212408 | EX51: 0.97791807 | EY51: 0.98107264
I52: 44490 | J52: 102.53898 | K52: 111.61023 | L52: -0.026602699 | M52: -0.025084744 | N52: 21 | O52: Discovery | P52: =IF(O52="Discovery",$Q$2,0) -> 225 | Q52: =IF(O52="Holdout",$Q$2,0) -> 0 | T52: 45900 | U52: 2025 | V52: 8 | W52: 0.00038051484 | X52: -0.019725114 | Y52: 0.020105629 | AH52: 44861 | AI52: 0.16129437 | AJ52: -0.015715748 | AK52: 0.17701011 | BI52: -0.13358369 | CP52: T0049 | CQ52: 0.98591723 | CR52: 0.96877598 | CS52: 0.97629512 | CT52: 0.98776518 | CU52: 0.96807488 | CV52: 0.99668643 | CW52: 0.96125661 | CX52: 0.91072448 | CY52: 0.92378763 | CZ52: 0.95902632 | DA52: 0.92996878 | DB52: 0.88332368 | DC52: 0.93474789 | DD52: 0.92729233 | DE52: 0.92436118 | DF52: 0.93787041 | DG52: 0.89606832 | DH52: 0.86439807 | DI52: 0.95743323 | DJ52: 0.88536285 | DK52: 0.92812082 | DL52: 0.93487544 | DM52: 0.96998658 | DN52: 0.93041485 | DO52: 0.89307335 | DP52: 0.83846304 | DQ52: 0.86044737 | DR52: 0.87510353 | DS52: 0.89899947 | DT52: 0.90384255 | DU52: 0.90390621 | DV52: 0.87835345 | DW52: 0.89543103 | DX52: 0.90836671 | DY52: 0.94099277 | DZ52: 0.98489776 | EA52: 0.98617209 | EB52: 0.97119733 | EC52: 0.96081054 | ED52: 0.93015983 | EE52: 0.95985473 | EF52: 1.0676097 | EG52: 1.0892117 | EH52: 1.0797808 | EI52: 1.0911234 | EJ52: 1.0519339 | EK52: 1.0791435 | EL52: 1.0958388 | EM52: 1.1162301 | EN52: 1.172115 | EO52: 1.2165933 | EP52: 1.1860702 | EQ52: 1.1443956 | ER52: 1.1261709 | ES52: 1.0974957 | ET52: 1.1612184 | EU52: 1.1599439 | EV52: 1.12821 | EW52: 1.1312687 | EX52: 1.1003632 | EY52: 1.0593894
I53: 44491 | J53: 101.28374 | K53: 110.97643 | L53: -0.0385186 | M53: -0.030621013 | N53: 21 | O53: Discovery | P53: =IF(O53="Discovery",$Q$2,0) -> 225 | Q53: =IF(O53="Holdout",$Q$2,0) -> 0 | T53: 45930 | U53: 2025 | V53: 9 | W53: -0.0095487009 | X53: 0.012070988 | Y53: -0.021619689 | AH53: 44862 | AI53: 0.16817367 | AJ53: -0.010266434 | AK53: 0.1784401 | BI53: 0.10558619 | CP53: T0050 | CQ53: 0.93519277 | CR53: 0.93642331 | CS53: 0.96308453 | CT53: 1.0065628 | CU53: 1.0869566 | CV53: 1.0996719 | CW53: 1.0857261 | CX53: 1.105004 | CY53: 1.147662 | CZ53: 1.0877769 | DA53: 1.0086136 | DB53: 1.1349467 | DC53: 1.169401 | DD53: 1.1480723 | DE53: 1.1111568 | DF53: 1.11895 | DG53: 1.059475 | DH53: 1.1501231 | DI53: 1.038146 | DJ53: 1.0890073 | DK53: 1.088187 | DL53: 1.1259229 | DM53: 1.2776866 | DN53: 1.3277277 | DO53: 1.3748974 | DP53: 1.3137818 | DQ53: 1.3445447 | DR53: 1.3642331 | DS53: 1.3707957 | DT53: 1.3921247 | DU53: 1.3654635 | DV53: 1.3404429 | DW53: 1.3486464 | DX53: 1.3461854 | DY53: 1.3301885 | DZ53: 1.3289581 | EA53: 1.4544709 | EB53: 1.5520919 | EC53: 1.5734208 | ED53: 1.5672682 | EE53: 1.5660375 | EF53: 1.5566038 | EG53: 1.5771124 | EH53: 1.6365874 | EI53: 1.7272353 | EJ53: 1.771534 | EK53: 1.752256 | EL53: 1.7895815 | EM53: 1.730927 | EN53: 1.6993437 | EO53: 1.6948319 | EP53: 1.6004921 | EQ53: 1.6886794 | ER53: 1.6431502 | ES53: 1.6706315 | ET53: 1.6517639 | EU53: 1.6636588 | EV53: 1.6546347 | EW53: 1.5926988 | EX53: 1.5406071 | EY53: 1.5332238
I54: 44494 | J54: 100.29649 | K54: 110.50549 | L54: -0.047890467 | M54: -0.034734659 | N54: 21 | O54: Discovery | P54: =IF(O54="Discovery",$Q$2,0) -> 225 | Q54: =IF(O54="Holdout",$Q$2,0) -> 0 | T54: 45961 | U54: 2025 | V54: 10 | W54: 0.038607839 | X54: 0.0429443 | Y54: -0.0043364605 | AH54: 44865 | AI54: 0.17964069 | AJ54: 0.0058463515 | AK54: 0.17379433 | BI54: 0.060395859 | CP54: T0051 | CQ54: 1.0124354 | CR54: 1.0140003 | CS54: 1.0389182 | CT54: 1.0293417 | CU54: 1.0240004 | CV54: 1.0139415 | CW54: 1.0169416 | CX54: 1.0279534 | CY54: 1.0284123 | CZ54: 1.0177533 | DA54: 0.98932932 | DB54: 1.0064943 | DC54: 1.0156473 | DD54: 1.012012 | DE54: 1.0167533 | DF54: 1.011365 | DG54: 0.99260014 | DH54: 0.98847057 | DI54: 0.96295268 | DJ54: 0.98274101 | DK54: 0.95610553 | DL54: 0.9066342 | DM54: 0.87503393 | DN54: 0.90086945 | DO54: 0.88692819 | DP54: 0.91025797 | DQ54: 0.92482282 | DR54: 0.91589326 | DS54: 0.93544643 | DT54: 0.9311405 | DU54: 0.91762264 | DV54: 0.92796396 | DW54: 0.95110541 | DX54: 0.94235244 | DY54: 0.94832889 | DZ54: 0.97114107 | EA54: 1.0184828 | EB54: 1.0262357 | EC54: 1.0083532 | ED54: 1.017318 | EE54: 1.0245769 | EF54: 1.0107061 | EG54: 1.0069414 | EH54: 1.0158121 | EI54: 1.0188121 | EJ54: 1.006306 | EK54: 1.0158708 | EL54: 1.0424477 | EM54: 1.030718 | EN54: 1.0288003 | EO54: 1.0115885 | EP54: 1.0082354 | EQ54: 0.99052945 | ER54: 1.0102237 | ES54: 1.0165533 | ET54: 0.98654115 | EU54: 0.96835267 | EV54: 0.9775528 | EW54: 0.95931726 | EX54: 0.96992921 | EY54: 0.9722352
I55: 44495 | J55: 101.70886 | K55: 111.69671 | L55: -0.03448299 | M55: -0.024329369 | N55: 22 | O55: Discovery | P55: =IF(O55="Discovery",$Q$2,0) -> 225 | Q55: =IF(O55="Holdout",$Q$2,0) -> 0 | T55: 45991 | U55: 2025 | V55: 11 | W55: -0.03867425 | X55: 0.0093967204 | Y55: -0.04807097 | AH55: 44866 | AI55: 0.17019914 | AJ55: 0.0024355389 | AK55: 0.1677636 | BI55: -0.063137636 | CP55: T0052 | CQ55: 0.98824605 | CR55: 1.0072087 | CS55: 1.0367311 | CT55: 1.0219469 | CU55: 1.009642 | CV55: 1.004626 | CW55: 0.97209105 | CX55: 0.96509618 | CY55: 0.95280931 | CZ55: 0.92363371 | DA55: 0.92575054 | DB55: 0.94250128 | DC55: 0.92924792 | DD55: 0.92096468 | DE55: 0.91705313 | DF55: 0.916777 | DG55: 0.93026037 | DH55: 0.95221108 | DI55: 0.91429201 | DJ55: 0.94029238 | DK55: 0.90941408 | DL55: 0.96808741 | DM55: 0.97232117 | DN55: 0.92308145 | DO55: 0.94273135 | DP55: 0.95754926 | DQ55: 0.96863957 | DR55: 0.93978612 | DS55: 0.93058246 | DT55: 0.94967998 | DU55: 0.94217913 | DV55: 0.92427795 | DW55: 1.0414406 | DX55: 1.0642656 | DY55: 1.0529912 | DZ55: 1.0444319 | EA55: 1.1081212 | EB55: 1.0958803 | EC55: 1.1046237 | ED55: 1.0884714 | EE55: 1.1004362 | EF55: 1.160582 | EG55: 1.1486173 | EH55: 1.1640335 | EI55: 1.1349958 | EJ55: 1.1215585 | EK55: 1.1447518 | EL55: 1.1741574 | EM55: 1.1768726 | EN55: 1.1550599 | EO55: 1.1365144 | EP55: 1.1433251 | EQ55: 1.1058202 | ER55: 1.0992396 | ES55: 1.1125389 | ET55: 1.0983192 | EU55: 1.0830413 | EV55: 1.1147017 | EW55: 1.0996998 | EX55: 1.1519305 | EY55: 1.1110663
I56: 44496 | J56: 101.87969 | K56: 111.58645 | L56: -0.032861221 | M56: -0.025292472 | N56: 23 | O56: Discovery | P56: =IF(O56="Discovery",$Q$2,0) -> 225 | Q56: =IF(O56="Holdout",$Q$2,0) -> 0 | T56: 46022 | U56: 2025 | V56: 12 | W56: 0.022677067 | X56: -0.0025759196 | Y56: 0.025252986 | AH56: 44867 | AI56: 0.17136104 | AJ56: 0.00085247363 | AK56: 0.17050857 | BI56: 0.0017590409 | CP56: T0053 | CQ56: 1.0444768 | CR56: 1.0295974 | CS56: 1.0239366 | CT56: 1.020055 | CU56: 0.98862469 | CV56: 0.98091539 | CW56: 1.0114291 | CX56: 1.012669 | CY56: 0.98344911 | CZ56: 0.93422828 | DA56: 0.97153471 | DB56: 0.97514692 | DC56: 0.96819249 | DD56: 0.96107601 | DE56: 0.96236972 | DF56: 0.9617771 | DG56: 1.0058225 | DH56: 0.92571021 | DI56: 0.96954017 | DJ56: 0.97816592 | DK56: 0.96086045 | DL56: 0.9382716 | DM56: 0.91142374 | DN56: 0.85972277 | DO56: 0.89756858 | DP56: 0.94404 | DQ56: 0.97498521 | DR56: 0.98813955 | DS56: 0.96813852 | DT56: 0.95924305 | DU56: 0.99902956 | DV56: 0.98431185 | DW56: 0.9821554 | DX56: 0.98501268 | DY56: 0.99504015 | DZ56: 1.0033964 | EA56: 0.99288369 | EB56: 1.0172517 | EC56: 1.0151489 | ED56: 1.0085179 | EE56: 1.01337 | EF56: 1.0626447 | EG56: 1.0553668 | EH56: 1.0543425 | EI56: 1.0659333 | EJ56: 1.0568225 | EK56: 1.0328321 | EL56: 1.0795191 | EM56: 1.0744515 | EN56: 1.0755296 | EO56: 1.0749906 | EP56: 1.0371989 | EQ56: 1.0395168 | ER56: 1.0587094 | ES56: 1.041943 | ET56: 0.98846298 | EU56: 1.030352 | EV56: 1.0458784 | EW56: 1.0404874 | EX56: 1.0353656 | EY56: 1.0231818
I57: 44497 | J57: 100.35811 | K57: 109.47137 | L57: -0.047305582 | M57: -0.043767684 | N57: 27 | O57: Discovery | P57: =IF(O57="Discovery",$Q$2,0) -> 225 | Q57: =IF(O57="Holdout",$Q$2,0) -> 0 | T57: 46053 | U57: 2026 | V57: 1 | W57: -0.012001884 | X57: -0.033179664 | Y57: 0.02117778 | AH57: 44868 | AI57: 0.18960362 | AJ57: 0.019343881 | AK57: 0.17025973 | BI57: -0.065452033 | CP57: T0054 | CQ57: 0.9664122 | CR57: 0.97251914 | CS57: 0.97709932 | CT57: 0.98702304 | CU57: 1.0122139 | CV57: 0.99580163 | CW57: 0.99236649 | CX57: 0.9809161 | CY57: 0.99274827 | CZ57: 0.93473288 | DA57: 0.97595434 | DB57: 1.0320611 | DC57: 1.0221375 | DD57: 0.99160315 | DE57: 0.93931306 | DF57: 0.91832073 | DG57: 0.93931306 | DH57: 0.89083975 | DI57: 0.92824444 | DJ57: 0.95763367 | DK57: 0.93778631 | DL57: 0.93587793 | DM57: 0.96793902 | DN57: 0.99236649 | DO57: 0.98816808 | DP57: 1.0083971 | DQ57: 0.99961848 | DR57: 1.0622137 | DS57: 1.09771 | DT57: 1.0664123 | DU57: 1.0839696 | DV57: 1.1206107 | DW57: 1.1370231 | DX57: 1.1480917 | DY57: 1.1148857 | DZ57: 1.1316795 | EA57: 1.1129772 | EB57: 1.1748093 | EC57: 1.2507636 | ED57: 1.2141223 | EE57: 1.2370229 | EF57: 1.3286261 | EG57: 1.4545801 | EH57: 1.4671756 | EI57: 1.408397 | EJ57: 1.3106871 | EK57: 1.3507635 | EL57: 1.3740459 | EM57: 1.3000003 | EN57: 1.3305346 | EO57: 1.3423664 | EP57: 1.2969467 | EQ57: 1.3580153 | ER57: 1.3385498 | ES57: 1.3129772 | ET57: 1.3225194 | EU57: 1.3431297 | EV57: 1.3297711 | EW57: 1.3412214 | EX57: 1.3099238 | EY57: 1.3053436
I58: 44498 | J58: 100.08654 | K58: 108.72227 | L58: -0.049883546 | M58: -0.05031112 | N58: 30 | O58: Discovery | P58: =IF(O58="Discovery",$Q$2,0) -> 225 | Q58: =IF(O58="Holdout",$Q$2,0) -> 0 | T58: 46081 | U58: 2026 | V58: 2 | W58: -0.015040304 | X58: 0.003784744 | Y58: -0.018825048 | AH58: 44869 | AI58: 0.19286766 | AJ58: 0.029426191 | AK58: 0.16344147 | BI58: 0.0040942204 | CP58: T0055 | CQ58: 1.0003501 | CR58: 1.023327 | CS58: 0.9993999 | CT58: 0.96927079 | CU58: 0.95959789 | CV58: 0.95532667 | CW58: 0.98291485 | CX58: 0.97799333 | CY58: 0.91940589 | CZ58: 0.90255085 | DA58: 0.93679101 | DB58: 0.9163049 | DC58: 0.90985289 | DD58: 0.88579583 | DE58: 0.88879667 | DF58: 0.89242769 | DG58: 0.88262485 | DH58: 0.85632686 | DI58: 0.89039703 | DJ58: 0.89112734 | DK58: 0.91398426 | DL58: 0.91813539 | DM58: 0.86823054 | DN58: 0.85783741 | DO58: 0.87748329 | DP58: 0.91301395 | DQ58: 0.92354698 | DR58: 0.92327689 | DS58: 0.90561177 | DT58: 0.88872663 | DU58: 0.89516854 | DV58: 0.91600489 | DW58: 0.92889869 | DX58: 0.95237581 | DY58: 0.92552761 | DZ58: 0.90626188 | EA58: 0.89932983 | EB58: 0.87878388 | EC58: 0.8990097 | ED58: 0.92414718 | EE58: 0.90216067 | EF58: 0.92002602 | EG58: 0.93731119 | EH58: 0.94939484 | EI58: 0.9460538 | EJ58: 0.96389909 | EK58: 0.97032112 | EL58: 0.9769131 | EM58: 0.95766737 | EN58: 0.95105527 | EO58: 0.93359006 | EP58: 0.92266698 | EQ58: 0.92888872 | ER58: 0.92668792 | ES58: 0.93148941 | ET58: 0.90076017 | EU58: 0.90809238 | EV58: 0.89634905 | EW58: 0.93292992 | EX58: 0.93052914 | EY58: 0.90628188
I59: 44501 | J59: 101.63553 | K59: 110.27741 | L59: -0.03517903 | M59: -0.03672696 | N59: 30 | O59: Discovery | P59: =IF(O59="Discovery",$Q$2,0) -> 225 | Q59: =IF(O59="Holdout",$Q$2,0) -> 0 | T59: 46112 | U59: 2026 | V59: 3 | W59: -0.095831925 | X59: -0.11390413 | Y59: 0.018072209 | AH59: 44872 | AI59: 0.17661797 | AJ59: 0.020417965 | AK59: 0.15620001 | BI59: 0.038117497 | CP59: T0056 | CQ59: 0.97991961 | CR59: 0.99574768 | CS59: 0.98251809 | CT59: 0.96763512 | CU59: 0.95487825 | CV59: 0.94259382 | CW59: 0.96449229 | CX59: 0.96544463 | CY59: 0.95378129 | CZ59: 0.93259662 | DA59: 0.94711642 | DB59: 0.94735451 | DC59: 0.95687549 | DD59: 0.9521148 | DE59: 0.94330797 | DF59: 0.93949933 | DG59: 0.94735451 | DH59: 0.89427411 | DI59: 0.95282911 | DJ59: 1.001863 | DK59: 1.0282842 | DL59: 1.0237616 | DM59: 1.0230477 | DN59: 1.0199531 | DO59: 1.0140024 | DP59: 1.05899 | DQ59: 1.0318548 | DR59: 1.0225715 | DS59: 0.99876865 | DT59: 0.97853604 | DU59: 0.99495996 | DV59: 0.99686442 | DW59: 0.99448414 | DX59: 0.99876865 | DY59: 0.98734304 | DZ59: 0.9950156 | EA59: 0.98782267 | EB59: 0.98326718 | EC59: 0.9945361 | ED59: 0.99957109 | EE59: 1.0108399 | EF59: 1.0314596 | EG59: 1.052319 | EH59: 1.0482432 | EI59: 1.0549563 | EJ59: 1.1237683 | EK59: 1.1489434 | EL59: 1.1698026 | EM59: 1.1623701 | EN59: 1.1849078 | EO59: 1.2225507 | EP59: 1.2002524 | EQ59: 1.2146384 | ER59: 1.2127203 | ES59: 1.2067261 | ET59: 1.1786739 | EU59: 1.2012116 | EV59: 1.1820307 | EW59: 1.1827501 | EX59: 1.1439083 | EY59: 1.1419903
I60: 44502 | J60: 103.23235 | K60: 110.36353 | L60: -0.020020516 | M60: -0.035974733 | N60: 30 | O60: Discovery | P60: =IF(O60="Discovery",$Q$2,0) -> 225 | Q60: =IF(O60="Holdout",$Q$2,0) -> 0 | T60: 46142 | U60: 2026 | V60: 4 | W60: 0.13566435 | X60: 0.10500267 | Y60: 0.030661682 | AH60: 44874 | AI60: 0.15487181 | AJ60: 0.016494011 | AK60: 0.1383778 | BI60: -0.16801224 | CP60: T0057 | CQ60: 0.98432797 | CR60: 0.98701913 | CS60: 0.99224314 | CT60: 0.97182202 | CU60: 0.96042422 | CV60: 0.96502445 | CW60: 0.91719773 | CX60: 0.85620432 | CY60: 0.91489736 | CZ60: 0.93964369 | DA60: 0.91584915 | DB60: 0.89030996 | DC60: 0.8575528 | DD60: 0.90696605 | DE60: 0.90633152 | DF60: 0.86191508 | DG60: 0.89816206 | DH60: 0.9018106 | DI60: 0.89475156 | DJ60: 0.89958975 | DK60: 0.8664362 | DL60: 0.86009101 | DM60: 0.87849196 | DN60: 0.91577004 | DO60: 0.93512297 | DP60: 0.916563 | DQ60: 0.89705163 | DR60: 0.89015143 | DS60: 0.91489736 | DT60: 0.92758794 | DU60: 0.93877131 | DV60: 0.95336538 | DW60: 0.94963752 | DX60: 0.95550672 | DY60: 0.93956448 | DZ60: 0.91140755 | EA60: 0.90807637 | EB60: 0.94797179 | EC60: 0.9534445 | ED60: 0.96486572 | EE60: 0.98834319 | EF60: 0.98778798 | EG60: 0.98604293 | EH60: 0.95431688 | EI60: 0.9760492 | EJ60: 0.94995479 | EK60: 0.90403125 | EL60: 0.90744184 | EM60: 0.86826037 | EN60: 0.86627757 | EO60: 0.8639775 | EP60: 0.86484998 | EQ60: 0.86040828 | ER60: 0.8317755 | ES60: 0.8270959 | ET60: 0.93044332 | EU60: 0.91013869 | EV60: 0.87857137 | EW60: 0.85255598 | EX60: 0.84105544 | EY60: 0.86992601
I61: 44503 | J61: 103.91411 | K61: 110.13364 | L61: -0.013548585 | M61: -0.037982771 | N61: 30 | O61: Discovery | P61: =IF(O61="Discovery",$Q$2,0) -> 225 | Q61: =IF(O61="Holdout",$Q$2,0) -> 0 | T61: 46173 | U61: 2026 | V61: 5 | W61: 0.052378408 | X61: -0.0011704517 | Y61: 0.053548859 | AH61: 44875 | AI61: 0.14467557 | AJ61: 0.010289379 | AK61: 0.13438619 | BI61: -0.18314798 | CP61: T0058 | CQ61: 0.99851438 | CR61: 0.99546168 | CS61: 0.9624323 | CT61: 0.94987583 | CU61: 0.96249332 | CV61: 0.96609553 | CW61: 0.93449058 | CX61: 0.95842326 | CY61: 0.9487769 | CZ61: 0.91802672 | DA61: 0.90013835 | DB61: 0.87020231 | DC61: 0.85734057 | DD61: 0.90237692 | DE61: 0.86830963 | DF61: 0.89157068 | DG61: 0.87541209 | DH61: 0.86698678 | DI61: 0.88463106 | DJ61: 0.91243034 | DK61: 0.94657904 | DL61: 0.97857058 | DM61: 1.0084456 | DN61: 1.0001017 | DO61: 1.0213887 | DP61: 0.99892144 | DQ61: 0.993793 | DR61: 0.98414657 | DS61: 0.94836983 | DT61: 0.9387845 | DU61: 0.96322597 | DV61: 0.96060073 | DW61: 0.95640839 | DX61: 0.93622035 | DY61: 0.91493339 | DZ61: 0.94008711 | EA61: 0.94798316 | EB61: 0.96511864 | EC61: 0.95935936 | ED61: 0.97077619 | EE61: 0.98353612 | EF61: 1.0147543 | EG61: 1.013574 | EH61: 1.0248891 | EI61: 0.99261266 | EJ61: 0.96080426 | EK61: 0.97850941 | EL61: 0.96391798 | EM61: 0.98740281 | EN61: 0.98803365 | EO61: 0.99035363 | EP61: 0.96102811 | EQ61: 0.95048628 | ER61: 0.96890384 | ES61: 0.96485409 | ET61: 0.99008907 | EU61: 0.98005619 | EV61: 0.95974596 | EW61: 0.92950465 | EX61: 0.94226466 | EY61: 0.91324432
... I64: 44509 | J64: 106.36994 | K64: 112.00154 | L64: 0 | M64: -0.021666672 | N64: 30 | O64: Discovery | P64: =IF(O64="Discovery",$Q$2,0) -> 225 | Q64: =IF(O64="Holdout",$Q$2,0) -> 0 | T64: 46265 | U64: 2026 | V64: 8 | W64: 0.0051722537 | X64: 0.0093965653 | Y64: -0.0042243117 | AH64: 44880 | AI64: 0.11821913 | AJ64: 0.0097767655 | AK64: 0.10844236 | BI64: -0.076621019 | CP64: T0061 | CQ64: 1.0433139 | CR64: 1.0591085 | CS64: 1.1061046 | CT64: 1.0967054 | CU64: 1.0452518 | CV64: 1.081589 | CW64: 1.0751938 | CX64: 1.0737401 | CY64: 1.0624031 | CZ64: 1.0417635 | DA64: 1.0064922 | DB64: 1.0477714 | DC64: 0.98449606 | DD64: 1.0589147 | DE64: 1.0717053 | DF64: 1.1291665 | DG64: 1.1335272 | DH64: 1.160465 | DI64: 1.1786821 | DJ64: 1.1801357 | DK64: 1.1995155 | DL64: 1.2218991 | DM64: 1.37374 | DN64: 1.415213 | DO64: 1.3513564 | DP64: 1.3716084 | DQ64: 1.4715114 | DR64: 1.4776161 | DS64: 1.5493216 | DT64: 1.5056201 | DU64: 1.5481587 | DV64: 1.4882751 | DW64: 1.5884691 | DX64: 1.6234494 | DY64: 1.586434 | DZ64: 1.6365311 | EA64: 1.6719961 | EB64: 1.7069764 | EC64: 1.7497091 | ED64: 1.7396315 | EE64: 1.6826549 | EF64: 1.711337 | EG64: 1.6437984 | EH64: 1.661434 | EI64: 1.6767441 | EJ64: 1.7205425 | EK64: 1.6499998 | EL64: 1.6800386 | EM64: 1.701744 | EN64: 1.6442829 | EO64: 1.5820735 | EP64: 1.6602712 | EQ64: 1.6438952 | ER64: 1.6317828 | ES64: 1.6037788 | ET64: 1.6143408 | EU64: 1.6012595 | EV64: 1.613275 | EW64: 1.5492247 | EX64: 1.4691859 | EY64: 1.5832362
I65: 44510 | J65: 106.32518 | K65: 111.85129 | L65: -0.00042079213 | M65: -0.022979136 | N65: 29 | O65: Discovery | P65: =IF(O65="Discovery",$Q$2,0) -> 225 | Q65: =IF(O65="Holdout",$Q$2,0) -> 0 | AH65: 44881 | AI65: 0.11641546 | AJ65: 0.0091617218 | AK65: 0.10725374 | BI65: -0.21934052 | CP65: T0062 | CQ65: 1.0588414 | CR65: 1.0408535 | CS65: 0.98932905 | CT65: 1.0371951 | CU65: 1.0121951 | CV65: 1.0060975 | CW65: 0.97774382 | CX65: 0.95213386 | CY65: 0.93323154 | CZ65: 0.93993886 | DA65: 0.88140234 | DB65: 0.93658526 | DC65: 0.93445118 | DD65: 0.93628026 | DE65: 0.94237793 | DF65: 0.94207304 | DG65: 0.8987804 | DH65: 0.89847552 | DI65: 0.91249982 | DJ65: 0.90975598 | DK65: 0.90853639 | DL65: 0.90914627 | DM65: 0.90792673 | DN65: 0.8987804 | DO65: 0.90792673 | DP65: 0.91371929 | DQ65: 0.90365831 | DR65: 0.91067052 | DS65: 0.9216462 | DT65: 0.89999977 | DU65: 0.86768281 | DV65: 0.84664626 | DW65: 0.89542674 | DX65: 0.88384135 | DY65: 0.91524382 | DZ65: 0.91371929 | EA65: 0.92317062 | EB65: 0.92774386 | EC65: 0.92439015 | ED65: 0.93567061 | EE65: 0.962195 | EF65: 0.96432918 | EG65: 1.0167682 | EH65: 1.0134144 | EI65: 0.97439022 | EJ65: 0.95640233 | EK65: 0.97439022 | EL65: 0.99725602 | EM65: 0.95548779 | EN65: 0.96707313 | EO65: 0.9411585 | EP65: 0.92560968 | EQ65: 0.93384131 | ER65: 0.91737784 | ES65: 0.91432906 | ET65: 0.87865839 | EU65: 0.8432926 | EV65: 0.86371933 | EW65: 0.82896331 | EX65: 0.78475597 | EY65: 0.80945112
I66: 44511 | J66: 105.66375 | K66: 111.05858 | L66: -0.0066390321 | M66: -0.029903406 | N66: 30 | O66: Discovery | P66: =IF(O66="Discovery",$Q$2,0) -> 225 | Q66: =IF(O66="Holdout",$Q$2,0) -> 0 | AH66: 44882 | AI66: 0.11725784 | AJ66: 0.012078956 | AK66: 0.10517888 | BI66: -0.11701441 | CP66: T0063 | CQ66: 0.96791668 | CR66: 0.91875011 | CS66: 0.96000001 | CT66: 0.96395838 | CU66: 0.94895837 | CV66: 0.94062491 | CW66: 0.93749999 | CX66: 0.92770833 | CY66: 0.9216666 | CZ66: 0.85125005 | DA66: 0.91666661 | DB66: 0.9293751 | DC66: 0.93916663 | DD66: 0.94416668 | DE66: 0.92270834 | DF66: 0.90083328 | DG66: 0.94562496 | DH66: 0.95520839 | DI66: 0.96770825 | DJ66: 0.97145825 | DK66: 0.9647917 | DL66: 0.94749996 | DM66: 0.96020831 | DN66: 0.96562495 | DO66: 0.94979169 | DP66: 0.96416668 | DQ66: 0.97625001 | DR66: 0.99791664 | DS66: 1.005625 | DT66: 0.99833336 | DU66: 0.99625007 | DV66: 1.0070833 | DW66: 0.994375 | DX66: 1.0227084 | DY66: 1.0497917 | DZ66: 1.14 | EA66: 1.2075 | EB66: 1.1574999 | EC66: 1.15875 | ED66: 1.17875 | EE66: 1.1464584 | EF66: 1.1379168 | EG66: 1.0745833 | EH66: 1.026875 | EI66: 1.0402083 | EJ66: 1.0785417 | EK66: 1.0545833 | EL66: 1.0306251 | EM66: 1.036875 | EN66: 1.0306251 | EO66: 1.034375 | EP66: 1.0097917 | EQ66: 1.0354167 | ER66: 1.020625 | ES66: 1.03125 | ET66: 1.0216666 | EU66: 0.95833337 | EV66: 0.92562503 | EW66: 0.94374996 | EX66: 0.91270831 | EY66: 0.92833328
I67: 44512 | J67: 105.98467 | K67: 112.26854 | L67: -0.0036220072 | M67: -0.019334452 | N67: 25 | O67: Discovery | P67: =IF(O67="Discovery",$Q$2,0) -> 225 | Q67: =IF(O67="Holdout",$Q$2,0) -> 0 | AH67: 44883 | AI67: 0.10653349 | AJ67: -0.0018069196 | AK67: 0.10834041 | BI67: -0.018897772 | CP67: T0064 | CQ67: 0.99809069 | CR67: 0.97653935 | CS67: 0.97054897 | CT67: 0.98133646 | CU67: 0.98599032 | CV67: 1.0029118 | CW67: 0.9867781 | CX67: 1.0010502 | CY67: 0.97639623 | CZ67: 1.0176133 | DA67: 1.0307636 | DB67: 1.040191 | DC67: 1.0307636 | DD67: 1.0288304 | DE67: 1.0066586 | DF67: 1.019117 | DG67: 1.0227924 | DH67: 1.0300478 | DI67: 1.0119091 | DJ67: 0.99212412 | DK67: 0.99842469 | DL67: 1.0457995 | DM67: 1.0030312 | DN67: 0.99830538 | DO67: 0.99147959 | DP67: 0.97890215 | DQ67: 0.9731027 | DR67: 0.94954655 | DS67: 0.95603817 | DT67: 0.97317426 | DU67: 0.9945108 | DV67: 1.0300478 | DW67: 1.0092124 | DX67: 1.0169689 | DY67: 1.0537231 | DZ67: 1.05463 | EA67: 1.0463724 | EB67: 1.0687112 | EC67: 1.0571839 | ED67: 1.0532219 | EE67: 1.0628639 | EF67: 1.0422434 | EG67: 1.0273032 | EH67: 1.0202625 | EI67: 1.0231504 | EJ67: 1.0315515 | EK67: 1.0023866 | EL67: 0.99658705 | EM67: 0.997544 | EN67: 1.0038607 | EO67: 1.0032384 | EP67: 0.98160956 | EQ67: 0.96395209 | ER67: 1.062838 | ES67: 1.0786769 | ET67: 1.1033205 | EU67: 1.0673602 | EV67: 1.0862374 | EW67: 1.0687476 | EX67: 1.0960952 | EY67: 1.0775286
I68: 44515 | J68: 106.15598 | K68: 112.36655 | L68: -0.0020114486 | M68: -0.01847836 | N68: 20 | O68: Discovery | P68: =IF(O68="Discovery",$Q$2,0) -> 225 | Q68: =IF(O68="Holdout",$Q$2,0) -> 0 | AH68: 44886 | AI68: 0.10490566 | AJ68: -0.0089016585 | AK68: 0.11380731 | BI68: -0.17157582 | CP68: T0065 | CQ68: 1.0107009 | CR68: 1.0432593 | CS68: 1.0378973 | CT68: 1.0171495 | CU68: 0.99492994 | CV68: 0.9871028 | CW68: 0.97700947 | CX68: 0.91977806 | CY68: 0.96690426 | CZ68: 0.99649546 | DA68: 0.97217294 | DB68: 0.9720678 | DC68: 0.95670572 | DD68: 0.95209119 | DE68: 0.97295576 | DF68: 0.98926402 | DG68: 1.004883 | DH68: 1.0138786 | DI68: 1.0265887 | DJ68: 1.0248247 | DK68: 1.0285633 | DL68: 1.0524183 | DM68: 1.0411799 | DN68: 1.039381 | DO68: 1.0639136 | DP68: 1.0501519 | DQ68: 1.0406894 | DR68: 1.0319041 | DS68: 1.0657944 | DT68: 1.0604207 | DU68: 1.0285163 | DV68: 1.0232946 | DW68: 1.0508413 | DX68: 1.0423365 | DY68: 1.0249768 | DZ68: 1.0393576 | EA68: 1.0527923 | EB68: 1.0522897 | EC68: 1.045187 | ED68: 1.0512268 | EE68: 1.0572197 | EF68: 1.030701 | EG68: 1.0410397 | EH68: 1.0581893 | EI68: 1.0496496 | EJ68: 1.0303972 | EK68: 1.0559814 | EL68: 1.0585515 | EM68: 1.0664955 | EN68: 1.0526635 | EO68: 1.0536566 | EP68: 1.0149884 | EQ68: 1.0200467 | ER68: 0.97332953 | ES68: 0.98857494 | ET68: 1.0038202 | EU68: 1.0032243 | EV68: 0.98911242 | EW68: 1.0002571 | EX68: 0.98553745 | EY68: 1.0054557
I69: 44516 | J69: 106.12532 | K69: 111.88228 | L69: -0.0022996825 | M69: -0.02270846 | N69: 17 | O69: Discovery | P69: =IF(O69="Discovery",$Q$2,0) -> 225 | Q69: =IF(O69="Holdout",$Q$2,0) -> 0 | AH69: 44887 | AI69: 0.10234074 | AJ69: -0.0010434514 | AK69: 0.10338419 | BI69: -0.05173284 | CP69: T0066 | CQ69: 0.98313957 | CR69: 1.0388082 | CS69: 1.0399709 | CT69: 1.019622 | CU69: 1.0031976 | CV69: 0.95872089 | CW69: 0.97514536 | CX69: 0.9110465 | CY69: 0.9524708 | CZ69: 0.93880811 | DA69: 0.9505814 | DB69: 0.94578483 | DC69: 0.91642431 | DD69: 0.87340109 | DE69: 0.8777617 | DF69: 0.87151151 | DG69: 0.88124992 | DH69: 0.92398256 | DI69: 0.9361918 | DJ69: 0.92412775 | DK69: 0.90726742 | DL69: 0.94927306 | DM69: 0.94127894 | DN69: 0.94404063 | DO69: 0.96438946 | DP69: 0.97304331 | DQ69: 0.95485567 | DR69: 1.012499 | DS69: 1.0356736 | DT69: 1.0540081 | DU69: 1.0513679 | DV69: 1.0408073 | DW69: 1.035087 | DX69: 1.0528347 | DY69: 1.0673556 | DZ69: 1.0449143 | EA69: 1.0541548 | EB69: 1.0849566 | EC69: 1.1131182 | ED69: 1.1009441 | EE69: 1.0679422 | EF69: 1.077476 | EG69: 1.0661821 | EH69: 1.0732226 | EI69: 1.0895035 | EJ69: 1.0479944 | EK69: 1.0466743 | EL69: 1.041834 | EM69: 1.0604618 | EN69: 1.024673 | EO69: 1.0009116 | EP69: 0.96262947 | EQ69: 0.96600296 | ER69: 0.99357789 | ES69: 0.97113653 | ET69: 0.94414836 | EU69: 0.96893637 | EV69: 0.93050763 | EW69: 0.95720242 | EX69: 0.93622787 | EY69: 0.94458843
I70: 44517 | J70: 106.09204 | K70: 111.37459 | L70: -0.0026125752 | M70: -0.02714314 | N70: 17 | O70: Discovery | P70: =IF(O70="Discovery",$Q$2,0) -> 225 | Q70: =IF(O70="Holdout",$Q$2,0) -> 0 | AH70: 44888 | AI70: 0.10417981 | AJ70: 0.0053833885 | AK70: 0.098796418 | BI70: -0.11640405 | CP70: T0067 | CQ70: 1.0042553 | CR70: 1.025 | CS70: 1.0324468 | CT70: 0.99202128 | CU70: 0.96702129 | CV70: 0.97925535 | CW70: 0.8691489 | CX70: 0.97287231 | CY70: 0.99042552 | CZ70: 0.97234044 | DA70: 0.97925535 | DB70: 0.96010638 | DC70: 0.91914895 | DD70: 0.94840427 | DE70: 0.95744681 | DF70: 0.96063833 | DG70: 0.96861705 | DH70: 0.9611702 | DI70: 0.94680851 | DJ70: 0.95372342 | DK70: 0.97500002 | DL70: 0.97500002 | DM70: 0.96436172 | DN70: 0.95372342 | DO70: 0.95478723 | DP70: 0.95212766 | DQ70: 0.93351064 | DR70: 0.91702124 | DS70: 0.91276599 | DT70: 0.91276599 | DU70: 0.95159571 | DV70: 0.95797876 | DW70: 0.98723408 | DX70: 1.0005319 | DY70: 0.9893617 | DZ70: 0.98882975 | EA70: 0.99946805 | EB70: 0.98723408 | EC70: 0.96861705 | ED70: 0.94414894 | EE70: 0.94414894 | EF70: 0.94627656 | EG70: 0.95478723 | EH70: 0.95691486 | EI70: 0.9292553 | EJ70: 0.93138301 | EK70: 0.93351064 | EL70: 0.92659573 | EM70: 0.91968082 | EN70: 0.90319151 | EO70: 0.88882982 | EP70: 0.8808511 | EQ70: 0.85478722 | ER70: 0.82872342 | ES70: 0.81117021 | ET70: 0.77712769 | EU70: 0.7606383 | EV70: 0.77925532 | EW70: 0.79095743 | EX70: 0.80053191 | EY70: 0.79255319
I71: 44518 | J71: 104.8718 | K71: 110.27633 | L71: -0.014084299 | M71: -0.036736402 | N71: 17 | O71: Discovery | P71: =IF(O71="Discovery",$Q$2,0) -> 225 | Q71: =IF(O71="Holdout",$Q$2,0) -> 0 | AH71: 44889 | AI71: 0.12367069 | AJ71: 0.024718103 | AK71: 0.098952591 | BI71: -0.20850788 | CP71: T0068 | CQ71: 0.95438852 | CR71: 0.97009135 | CS71: 0.98909364 | CT71: 0.96871642 | CU71: 0.95383865 | CV71: 0.96599764 | CW71: 0.94876735 | CX71: 0.96697515 | CY71: 0.95777958 | CZ71: 0.94155735 | DA71: 0.93822742 | DB71: 0.96853316 | DC71: 0.94268773 | DD71: 0.95949047 | DE71: 0.94888941 | DF71: 0.93285062 | DG71: 0.92188305 | DH71: 0.91919465 | DI71: 0.90984638 | DJ71: 0.92777924 | DK71: 0.92212742 | DL71: 0.87199458 | DM71: 0.88910264 | DN71: 0.89719856 | DO71: 0.88045702 | DP71: 0.86179095 | DQ71: 0.8700394 | DR71: 0.89289094 | DS71: 0.93288127 | DT71: 0.92843538 | DU71: 0.91296776 | DV71: 0.9311523 | DW71: 0.93961159 | DX71: 0.94476761 | DY71: 0.93034948 | DZ71: 0.92621248 | EA71: 0.93547459 | EB71: 0.91188704 | EC71: 0.87959317 | ED71: 0.88950362 | EE71: 0.87817284 | EF71: 0.86273595 | EG71: 0.85662297 | EH71: 0.87320229 | EI71: 0.89527699 | EJ71: 0.88746585 | EK71: 0.89685147 | EL71: 0.88984315 | EM71: 0.91052858 | EN71: 0.91395571 | EO71: 0.90352018 | EP71: 0.90268671 | EQ71: 0.91349259 | ER71: 0.91880266 | ES71: 0.91136221 | ET71: 0.92105646 | EU71: 0.92540966 | EV71: 0.93513489 | EW71: 0.90963315 | EX71: 0.88829957 | EY71: 0.89191165
I72: 44522 | J72: 103.71028 | K72: 107.92812 | L72: -0.02500391 | M72: -0.05724798 | N72: 18 | O72: Discovery | P72: =IF(O72="Discovery",$Q$2,0) -> 225 | Q72: =IF(O72="Holdout",$Q$2,0) -> 0 | AH72: 44890 | AI72: 0.1318408 | AJ72: 0.050114511 | AK72: 0.081726285 | BI72: -0.14947065 | CP72: T0069 | CQ72: 0.99357275 | CR72: 0.99762968 | CS72: 0.99881497 | CT72: 1.0126255 | CU72: 1.0003441 | CV72: 0.98889723 | CW72: 0.96855201 | CX72: 0.99367071 | CY72: 0.973418 | CZ72: 0.9974246 | DA72: 0.99413419 | DB72: 0.98333581 | DC72: 0.98194538 | DD72: 0.97522567 | DE72: 0.96818131 | DF72: 1.0037274 | DG72: 0.99520005 | DH72: 0.93560109 | DI72: 0.95362884 | DJ72: 0.9438504 | DK72: 0.91924143 | DL72: 0.90320629 | DM72: 0.90899938 | DN72: 0.93050322 | DO72: 0.96387103 | DP72: 0.96465889 | DQ72: 0.9434797 | DR72: 0.96368568 | DS72: 0.96674448 | DT72: 0.96146126 | DU72: 0.94811409 | DV72: 0.95488018 | DW72: 0.95344376 | DX72: 0.94111605 | DY72: 0.91928782 | DZ72: 0.92401499 | EA72: 0.91752675 | EB72: 0.89440093 | EC72: 0.88865403 | ED72: 0.88985912 | EE72: 0.91446802 | EF72: 0.89101761 | EG72: 0.90024027 | EH72: 0.89602297 | EI72: 0.91979749 | EJ72: 0.92869563 | EK72: 0.91534845 | EL72: 0.90209412 | EM72: 0.90404061 | EN72: 0.91261423 | EO72: 0.91034329 | EP72: 0.91446802 | EQ72: 0.91748036 | ER72: 0.91164095 | ES72: 0.87456558 | ET72: 0.85996693 | EU72: 0.8506517 | EV72: 0.83698007 | EW72: 0.81858148 | EX72: 0.83447746 | EY72: 0.83391494
I73: 44523 | J73: 104.55667 | K73: 108.87288 | L73: -0.017046824 | M73: -0.048995509 | N73: 18 | O73: Discovery | P73: =IF(O73="Discovery",$Q$2,0) -> 225 | Q73: =IF(O73="Holdout",$Q$2,0) -> 0 | AH73: 44893 | AI73: 0.12523425 | AJ73: 0.044788123 | AK73: 0.080446127 | BI73: -0.26677306 | CP73: T0070 | CQ73: 1.0016616 | CR73: 0.99216886 | CS73: 0.99675374 | CT73: 0.97572234 | CU73: 0.98949213 | CV73: 0.97962998 | CW73: 0.98304571 | CX73: 0.98126088 | CY73: 0.97561456 | CZ73: 0.96404493 | DA73: 0.97109137 | DB73: 0.9644758 | DC73: 0.96789127 | DD73: 0.97016821 | DE73: 0.9849995 | DF73: 0.98549179 | DG73: 0.99184591 | DH73: 1.0060462 | DI73: 0.99686133 | DJ73: 0.99781531 | DK73: 0.98512255 | DL73: 0.98615331 | DM73: 0.98787657 | DN73: 0.98316876 | DO73: 0.98575338 | DP73: 0.98344557 | DQ73: 0.98335332 | DR73: 0.98527643 | DS73: 0.98113788 | DT73: 0.98099929 | DU73: 0.97596846 | DV73: 0.96789127 | DW73: 0.95270621 | DX73: 0.95013681 | DY73: 0.9438752 | DZ73: 0.93105945 | EA73: 0.90841243 | EB73: 0.91058191 | EC73: 0.90773558 | ED73: 0.90445857 | EE73: 0.9202898 | EF73: 0.9408289 | EG73: 0.94212124 | EH73: 0.94135208 | EI73: 0.93982896 | EJ73: 0.93325936 | EK73: 0.94367511 | EL73: 0.96222967 | EM73: 0.96878362 | EN73: 0.99703055 | EO73: 1.004877 | EP73: 1.0160775 | EQ73: 1.0162312 | ER73: 1.0179825 | ES73: 0.98760141 | ET73: 1.0020126 | EU73: 1.0063666 | EV73: 1.0145925 | EW73: 1.0179343 | EX73: 1.0210992 | EY73: 1.0223847
I74: 44524 | J74: 104.36818 | K74: 108.43113 | L74: -0.018818822 | M74: -0.052854216 | N74: 18 | O74: Discovery | P74: =IF(O74="Discovery",$Q$2,0) -> 225 | Q74: =IF(O74="Holdout",$Q$2,0) -> 0 | AH74: 44894 | AI74: 0.12752514 | AJ74: 0.050905526 | AK74: 0.076619612 | BI74: -0.036123107 | CP74: T0071 | CQ74: 0.99285343 | CR74: 0.95301881 | CS74: 0.94493021 | CT74: 0.95455832 | CU74: 0.93318783 | CV74: 0.91736659 | CW74: 0.90795655 | CX74: 0.88173728 | CY74: 0.8504624 | CZ74: 0.82593212 | DA74: 0.82787385 | DB74: 0.85619575 | DC74: 0.88645949 | DD74: 0.83101056 | DE74: 0.84996846 | DF74: 0.86982252 | DG74: 0.83135526 | DH74: 0.78431672 | DI74: 0.7917045 | DJ74: 0.81489049 | DK74: 0.86348026 | DL74: 0.86399727 | DM74: 0.85922914 | DN74: 0.87035101 | DO74: 0.87343021 | DP74: 0.85961982 | DQ74: 0.85065791 | DR74: 0.83051651 | DS74: 0.82752915 | DT74: 0.80307922 | DU74: 0.76403744 | DV74: 0.77319468 | DW74: 0.78197284 | DX74: 0.74658473 | DY74: 0.73241809 | DZ74: 0.72266336 | EA74: 0.76109617 | EB74: 0.73936927 | EC74: 0.77384963 | ED74: 0.74936521 | EE74: 0.79440462 | EF74: 0.8096283 | EG74: 0.80464187 | EH74: 0.7817085 | EI74: 0.76153277 | EJ74: 0.74891725 | EK74: 0.74773374 | EL74: 0.77126455 | EM74: 0.77714707 | EN74: 0.78078933 | EO74: 0.75712447 | EP74: 0.76775234 | EQ74: 0.76506648 | ER74: 0.7313157 | ES74: 0.72431878 | ET74: 0.74941304 | EU74: 0.76724524 | EV74: 0.8102407 | EW74: 0.82141029 | EX74: 0.83749035 | EY74: 0.83145023
I75: 44525 | J75: 105.04589 | K75: 109.18132 | L75: -0.012447575 | M75: -0.046301338 | N75: 18 | O75: Discovery | P75: =IF(O75="Discovery",$Q$2,0) -> 225 | Q75: =IF(O75="Holdout",$Q$2,0) -> 0 | AH75: 44895 | AI75: 0.13148957 | AJ75: 0.052509472 | AK75: 0.078980096 | BI75: -0.11278047 | CP75: T0072 | CQ75: 0.96531586 | CR75: 0.93673188 | CS75: 0.92409585 | CT75: 0.95581692 | CU75: 0.94579531 | CV75: 0.91189534 | CW75: 0.88793016 | CX75: 0.84348576 | CY75: 0.83668827 | CZ75: 0.86562079 | DA75: 0.88784302 | DB75: 0.87895405 | DC75: 0.89960774 | DD75: 0.87511978 | DE75: 0.88479292 | DF75: 0.86875809 | DG75: 0.84871448 | DH75: 0.79564261 | DI75: 0.80226564 | DJ75: 0.82980391 | DK75: 0.90928076 | DL75: 0.92426982 | DM75: 0.94762518 | DN75: 0.93594777 | DO75: 0.96261419 | DP75: 0.93838757 | DQ75: 0.92435707 | DR75: 0.92148143 | DS75: 0.91590406 | DT75: 0.88888878 | DU75: 0.84915017 | DV75: 0.81978202 | DW75: 0.83877991 | DX75: 0.8187362 | DY75: 0.81655752 | DZ75: 0.79206951 | EA75: 0.81986917 | EB75: 0.82779941 | EC75: 0.8589977 | ED75: 0.86483657 | EE75: 0.8791284 | EF75: 0.89986929 | EG75: 0.91407402 | EH75: 0.90222215 | EI75: 0.87032674 | EJ75: 0.87154675 | EK75: 0.875904 | EL75: 0.87843127 | EM75: 0.88418283 | EN75: 0.88435718 | EO75: 0.8683223 | EP75: 0.85690611 | EQ75: 0.862135 | ER75: 0.84235279 | ES75: 0.85525037 | ET75: 0.87738545 | EU75: 0.88174281 | EV75: 0.92810441 | EW75: 0.93141578 | EX75: 0.93019583 | EY75: 0.92470566
I76: 44526 | J76: 103.27731 | K76: 105.986 | L76: -0.02907427 | M76: -0.074212443 | N76: 18 | O76: Discovery | P76: =IF(O76="Discovery",$Q$2,0) -> 225 | Q76: =IF(O76="Holdout",$Q$2,0) -> 0 | AH76: 44896 | AI76: 0.1545539 | AJ76: 0.0881711 | AK76: 0.066382802 | BI76: -0.0062811391 | CP76: T0073 | CQ76: 1.0211184 | CR76: 1.0073937 | CS76: 1.0159887 | CT76: 0.99408503 | CU76: 0.97865047 | CV76: 0.99981507 | CW76: 0.96987044 | CX76: 0.98359494 | CY76: 1.008364 | CZ76: 1.0207023 | DA76: 1.0257857 | DB76: 1.0195933 | DC76: 0.98073002 | DD76: 1.0197321 | DE76: 0.99727349 | DF76: 1.025 | DG76: 0.98294817 | DH76: 0.98955643 | DI76: 1.0070239 | DJ76: 1.0053142 | DK76: 0.97643244 | DL76: 1.0250464 | DM76: 1.0526803 | DN76: 1.0170518 | DO76: 1.0162431 | DP76: 1.0301755 | DQ76: 1.0324629 | DR76: 1.0258779 | DS76: 1.0459796 | DT76: 1.0370379 | DU76: 1.0725971 | DV76: 1.0908272 | DW76: 1.0801524 | DX76: 1.0411968 | DY76: 1.0429989 | DZ76: 1.0240756 | EA76: 1.0376616 | EB76: 1.0446626 | EC76: 1.0681607 | ED76: 1.0762708 | EE76: 1.0812616 | EF76: 1.088401 | EG76: 1.0959565 | EH76: 1.1007391 | EI76: 1.0897874 | EJ76: 1.1026107 | EK76: 1.1381699 | EL76: 1.1467653 | EM76: 1.1763632 | EN76: 1.1856515 | EO76: 1.1831562 | EP76: 1.2126154 | EQ76: 1.1573011 | ER76: 1.1459334 | ES76: 1.1868993 | ET76: 1.2187154 | EU76: 1.2384704 | EV76: 1.2088031 | EW76: 1.2092884 | EX76: 1.2129619 | EY76: 1.2173985
... I570: 45252 | J570: 146.48808 | K570: 127.0323 | L570: -0.0063759075 | M570: -0.0021567096 | N570: 30 | O570: Discovery | P570: =IF(O570="Discovery",$Q$2,0) -> 225 | Q570: =IF(O570="Holdout",$Q$2,0) -> 0 | AH570: 45624 | AI570: 0.41112337 | AJ570: 0.27721427 | AK570: 0.1339091 | BI570: 0.017328619 | CP570: T0567 | CQ570: 0.96555988 | CR570: 0.95989589 | CS570: 1.0115886 | CT570: 0.98834633 | CU570: 1.000651 | CV570: 1.0271484 | CW570: 1.0339193 | CX570: 1.0203777 | CY570: 1.0031901 | CZ570: 0.98164067 | DA570: 0.95970052 | DB570: 0.98776037 | DC570: 0.93710936 | DD570: 0.91640626 | DE570: 0.89850263 | DF570: 0.90156252 | DG570: 0.92128907 | DH570: 0.88528652 | DI570: 0.87037765 | DJ570: 0.90885414 | DK570: 0.91542971 | DL570: 0.93496089 | DM570: 0.94817708 | DN570: 0.94277343 | DO570: 0.92363276 | DP570: 0.94388023 | DQ570: 0.90136722 | DR570: 0.90761717 | DS570: 0.91438804 | DT570: 0.87584643 | DU570: 0.86256511 | DV570: 0.86744793 | DW570: 0.90579433 | DX570: 0.96927086 | DY570: 0.97545576 | DZ570: 0.9775391 | EA570: 0.96178386 | EB570: 1.0132812 | EC570: 1.0557942 | ED570: 1.0826172 | EE570: 1.118685 | EF570: 1.1156901 | EG570: 1.145638 | EH570: 1.2889324 | EI570: 1.2223307 | EJ570: 1.2526042 | EK570: 1.2675131 | EL570: 1.2300782 | EM570: 1.2119141 | EN570: 1.1794922 | EO570: 1.2354817 | EP570: 1.2707032 | EQ570: 1.2440755 | ER570: 1.2014974 | ES570: 1.2514323 | ET570: 1.2494792 | EU570: 1.2485678 | EV570: 1.2190104 | EW570: 1.1517578 | EX570: 1.1479818 | EY570: 1.1690104
I571: 45253 | J571: 146.48956 | K571: 127.11661 | L571: -0.0063658209 | M571: -0.0014944129 | N571: 30 | O571: Discovery | P571: =IF(O571="Discovery",$Q$2,0) -> 225 | Q571: =IF(O571="Holdout",$Q$2,0) -> 0 | AH571: 45625 | AI571: 0.41930187 | AJ571: 0.28615486 | AK571: 0.13314701 | BI571: 0.026296813
I572: 45254 | J572: 146.84104 | K572: 127.14616 | L572: -0.0039817325 | M572: -0.0012623261 | N572: 30 | O572: Discovery | P572: =IF(O572="Discovery",$Q$2,0) -> 225 | Q572: =IF(O572="Holdout",$Q$2,0) -> 0 | AH572: 45628 | AI572: 0.42610787 | AJ572: 0.29429252 | AK572: 0.13181535 | BI572: -0.10544998
I573: 45258 | J573: 149.29616 | K573: 127.85455 | L573: 0 | M573: 0 | N573: 30 | O573: Discovery | P573: =IF(O573="Discovery",$Q$2,0) -> 225 | Q573: =IF(O573="Holdout",$Q$2,0) -> 0 | AH573: 45629 | AI573: 0.41848385 | AJ573: 0.29754873 | AK573: 0.12093512 | BI573: -0.020363239
I574: 45259 | J574: 149.5802 | K574: 129.02415 | L574: 0 | M574: 0 | N574: 30 | O574: Discovery | P574: =IF(O574="Discovery",$Q$2,0) -> 225 | Q574: =IF(O574="Holdout",$Q$2,0) -> 0 | AH574: 45630 | AI574: 0.421231 | AJ574: 0.29017934 | AK574: 0.13105165 | BI574: 0.1345026
I575: 45260 | J575: 150.98114 | K575: 129.6284 | L575: 0 | M575: 0 | N575: 30 | O575: Discovery | P575: =IF(O575="Discovery",$Q$2,0) -> 225 | Q575: =IF(O575="Holdout",$Q$2,0) -> 0 | AH575: 45631 | AI575: 0.41585474 | AJ575: 0.29408576 | AK575: 0.12176898 | BI575: 0.21034497
I576: 45261 | J576: 152.80568 | K576: 130.5465 | L576: 0 | M576: 0 | N576: 30 | O576: Discovery | P576: =IF(O576="Discovery",$Q$2,0) -> 225 | Q576: =IF(O576="Holdout",$Q$2,0) -> 0 | AH576: 45632 | AI576: 0.38325698 | AJ576: 0.28686997 | AK576: 0.096387008 | BI576: -0.033043912
I577: 45264 | J577: 154.00234 | K577: 132.94731 | L577: 0 | M577: 0 | N577: 30 | O577: Discovery | P577: =IF(O577="Discovery",$Q$2,0) -> 225 | Q577: =IF(O577="Holdout",$Q$2,0) -> 0 | AH577: 45635 | AI577: 0.37610524 | AJ577: 0.26254167 | AK577: 0.11356357 | BI577: -0.12914734
I578: 45265 | J578: 155.59802 | K578: 133.95657 | L578: 0 | M578: 0 | N578: 30 | O578: Discovery | P578: =IF(O578="Discovery",$Q$2,0) -> 225 | Q578: =IF(O578="Holdout",$Q$2,0) -> 0 | AH578: 45636 | AI578: 0.36703098 | AJ578: 0.25426136 | AK578: 0.11276962 | BI578: 0.00086610857
I579: 45266 | J579: 154.64412 | K579: 134.61559 | L579: -0.0061305998 | M579: 0 | N579: 30 | O579: Discovery | P579: =IF(O579="Discovery",$Q$2,0) -> 225 | Q579: =IF(O579="Holdout",$Q$2,0) -> 0 | AH579: 45637 | AI579: 0.38440402 | AJ579: 0.2504363 | AK579: 0.13396773 | BI579: 0.054821541
I580: 45267 | J580: 155.1121 | K580: 134.78747 | L580: -0.0031229616 | M580: 0 | N580: 30 | O580: Discovery | P580: =IF(O580="Discovery",$Q$2,0) -> 225 | Q580: =IF(O580="Holdout",$Q$2,0) -> 0 | AH580: 45638 | AI580: 0.37087761 | AJ580: 0.24340176 | AK580: 0.12747586 | BI580: 0.014690565
I581: 45268 | J581: 155.16216 | K581: 134.78494 | L581: -0.0028012102 | M581: -1.8712725e-05 | N581: 30 | O581: Discovery | P581: =IF(O581="Discovery",$Q$2,0) -> 225 | Q581: =IF(O581="Holdout",$Q$2,0) -> 0 | AH581: 45639 | AI581: 0.37076858 | AJ581: 0.24890796 | AK581: 0.12186062 | BI581: 0.64113456
I582: 45271 | J582: 154.44937 | K582: 135.26561 | L582: -0.0073821657 | M582: 0 | N582: 30 | O582: Discovery | P582: =IF(O582="Discovery",$Q$2,0) -> 225 | Q582: =IF(O582="Holdout",$Q$2,0) -> 0 | AH582: 45642 | AI582: 0.38377706 | AJ582: 0.24412366 | AK582: 0.1396534 | BI582: 0.097596053
... I991: 45870 | J991: 194.1418 | K991: 163.39544 | L991: -0.10875404 | M991: -0.074427785 | N991: 28 | O991: Holdout | P991: =IF(O991="Discovery",$Q$2,0) -> 0 | Q991: =IF(O991="Holdout",$Q$2,0) -> 225 | AH991: 46245 | AI991: 0.13668117 | AJ991: 0.04443484 | AK991: 0.092246334 | BI991: -0.11615369
I992: 45873 | J992: 198.06603 | K992: 164.74124 | L992: -0.090739077 | M992: -0.066804371 | N992: 30 | O992: Holdout | P992: =IF(O992="Discovery",$Q$2,0) -> 0 | Q992: =IF(O992="Holdout",$Q$2,0) -> 225 | BI992: 0.064769493
I993: 45874 | J993: 197.35715 | K993: 164.29516 | L993: -0.093993353 | M993: -0.069331222 | N993: 30 | O993: Holdout | P993: =IF(O993="Discovery",$Q$2,0) -> 0 | Q993: =IF(O993="Holdout",$Q$2,0) -> 225 | BI993: 0.094670891
I994: 45875 | J994: 195.52366 | K994: 163.34644 | L994: -0.10241032 | M994: -0.074705371 | N994: 30 | O994: Holdout | P994: =IF(O994="Discovery",$Q$2,0) -> 0 | Q994: =IF(O994="Holdout",$Q$2,0) -> 225 | BI994: -0.13087578
I995: 45876 | J995: 197.12287 | K995: 163.54281 | L995: -0.095068823 | M995: -0.073592985 | N995: 30 | O995: Holdout | P995: =IF(O995="Discovery",$Q$2,0) -> 0 | Q995: =IF(O995="Holdout",$Q$2,0) -> 225 | BI995: -0.0061286989
I996: 45877 | J996: 194.90985 | K996: 161.73436 | L996: -0.10522814 | M996: -0.083837139 | N996: 28 | O996: Holdout | P996: =IF(O996="Discovery",$Q$2,0) -> 0 | Q996: =IF(O996="Holdout",$Q$2,0) -> 225 | BI996: -0.053596252
I997: 45880 | J997: 195.83681 | K997: 163.10574 | L997: -0.10097273 | M997: -0.076068809 | N997: 27 | O997: Holdout | P997: =IF(O997="Discovery",$Q$2,0) -> 0 | Q997: =IF(O997="Holdout",$Q$2,0) -> 225 | BI997: -0.20749358
I998: 45881 | J998: 197.0989 | K998: 162.63841 | L998: -0.095178885 | M998: -0.078716082 | N998: 30 | O998: Holdout | P998: =IF(O998="Discovery",$Q$2,0) -> 0 | Q998: =IF(O998="Holdout",$Q$2,0) -> 225 | BI998: 0.11565727
I999: 45882 | J999: 197.51733 | K999: 163.57164 | L999: -0.093258015 | M999: -0.073429699 | N999: 30 | O999: Holdout | P999: =IF(O999="Discovery",$Q$2,0) -> 0 | Q999: =IF(O999="Holdout",$Q$2,0) -> 225 | BI999: 0.11323428
I1000: 45883 | J1000: 197.61572 | K1000: 163.443 | L1000: -0.092806316 | M1000: -0.074158363 | N1000: 30 | O1000: Holdout | P1000: =IF(O1000="Discovery",$Q$2,0) -> 0 | Q1000: =IF(O1000="Holdout",$Q$2,0) -> 225 | BI1000: 0.11270729
I1001: 45887 | J1001: 199.69876 | K1001: 165.25361 | L1001: -0.083243712 | M1001: -0.063901963 | N1001: 30 | O1001: Holdout | P1001: =IF(O1001="Discovery",$Q$2,0) -> 0 | Q1001: =IF(O1001="Holdout",$Q$2,0) -> 225 | BI1001: -0.051721467
I1002: 45888 | J1002: 199.93168 | K1002: 166.2272 | L1002: -0.082174427 | M1002: -0.05838698 | N1002: 30 | O1002: Holdout | P1002: =IF(O1002="Discovery",$Q$2,0) -> 0 | Q1002: =IF(O1002="Holdout",$Q$2,0) -> 225 | BI1002: -0.059178794
I1003: 45889 | J1003: 200.4076 | K1003: 166.77885 | L1003: -0.079989636 | M1003: -0.055262094 | N1003: 30 | O1003: Holdout | P1003: =IF(O1003="Discovery",$Q$2,0) -> 0 | Q1003: =IF(O1003="Holdout",$Q$2,0) -> 225 | BI1003: 0.10259323
...
